Workbook

Sheet Karbon Entry
A1: Enter in Karbon (Time & Budget → Add Budget Estimate)
A2: Enter ONE budget per recurring series (section 1) and per one-time item (section 3). Section 2 is planning only. Two separate estimates per item: WORK time (e.g. Staff Accountant · Bookkeeping) and REVIEW time (Reviewer · Review). Review is NOT included in Work.
A4: 1. RECURRING WORK – set once on the recurring series; every future item gets it
A5: Client Name | B5: Work Item | C5: Repeats | D5: Work time (h:mm) | E5: Work $ | F5: Review time (h:mm) | G5: Review $ | H5: Work done by
A6: 1402 W Victory LLC | B6: 1099 Quarterly Review (ongoing, after Oct 30) | C6: Quarterly | D6: =ROUND('Recurring Budgets'!F2*60,0)/1440 -> 0.052083333 | E6: =ROUND('Recurring Budgets'!F2*IF(H6="CFO",Assumptions!$B$5,Assumptions!$B$4),0) -> 119 | F6: =ROUND('Recurring Budgets'!G2*60,0)/1440 -> 0 | G6: =ROUND('Recurring Budgets'!G2*Assumptions!$B$5,0) -> 0 | H6: ='Recurring Budgets'!L2 -> Staff
B7: Month End Close | C7: Monthly | D7: =ROUND('Recurring Budgets'!F3*60,0)/1440 -> 0.020833333 | E7: =ROUND('Recurring Budgets'!F3*IF(H7="CFO",Assumptions!$B$5,Assumptions!$B$4),0) -> 48 | F7: =ROUND('Recurring Budgets'!G3*60,0)/1440 -> 0.029166667 | G7: =ROUND('Recurring Budgets'!G3*Assumptions!$B$5,0) -> 175 | H7: ='Recurring Budgets'!L3 -> Staff
A8: 15650 Northsight LLC | B8: 1099 Quarterly Review (ongoing, after Oct 30) | C8: Quarterly | D8: =ROUND('Recurring Budgets'!F4*60,0)/1440 -> 0.052083333 | E8: =ROUND('Recurring Budgets'!F4*IF(H8="CFO",Assumptions!$B$5,Assumptions!$B$4),0) -> 119 | F8: =ROUND('Recurring Budgets'!G4*60,0)/1440 -> 0 | G8: =ROUND('Recurring Budgets'!G4*Assumptions!$B$5,0) -> 0 | H8: ='Recurring Budgets'!L4 -> Staff
B9: Quarter End Close | C9: Quarterly | D9: =ROUND('Recurring Budgets'!F5*60,0)/1440 -> 0.020833333 | E9: =ROUND('Recurring Budgets'!F5*IF(H9="CFO",Assumptions!$B$5,Assumptions!$B$4),0) -> 48 | F9: =ROUND('Recurring Budgets'!G5*60,0)/1440 -> 0.052083333 | G9: =ROUND('Recurring Budgets'!G5*Assumptions!$B$5,0) -> 313 | H9: ='Recurring Budgets'!L5 -> Staff
B10: Quarterly Sales Tax Filing - Onyx Prepares the Returns for Client | C10: Quarterly | D10: =ROUND('Recurring Budgets'!F6*60,0)/1440 -> 0.020833333 | E10: =ROUND('Recurring Budgets'!F6*IF(H10="CFO",Assumptions!$B$5,Assumptions!$B$4),0) -> 48 | F10: =ROUND('Recurring Budgets'!G6*60,0)/1440 -> 0 | G10: =ROUND('Recurring Budgets'!G6*Assumptions!$B$5,0) -> 0 | H10: ='Recurring Budgets'!L6 -> Staff
A11: 1915 NORTH 16TH STREET LLC | B11: Year-End Tax Coordination | C11: Annual | D11: =ROUND('Recurring Budgets'!F7*60,0)/1440 -> 0.041666667 | E11: =ROUND('Recurring Budgets'!F7*IF(H11="CFO",Assumptions!$B$5,Assumptions!$B$4),0) -> 95 | F11: =ROUND('Recurring Budgets'!G7*60,0)/1440 -> 0 | G11: =ROUND('Recurring Budgets'!G7*Assumptions!$B$5,0) -> 0 | H11: ='Recurring Budgets'!L7 -> Staff
A12: 3540 E Boot Track LLC | B12: 1099 Quarterly Review (ongoing, after Oct 30) | C12: Quarterly | D12: =ROUND('Recurring Budgets'!F8*60,0)/1440 -> 0.052083333 | E12: =ROUND('Recurring Budgets'!F8*IF(H12="CFO",Assumptions!$B$5,Assumptions!$B$4),0) -> 119 | F12: =ROUND('Recurring Budgets'!G8*60,0)/1440 -> 0 | G12: =ROUND('Recurring Budgets'!G8*Assumptions!$B$5,0) -> 0 | H12: ='Recurring Budgets'!L8 -> Staff
B13: Month End Close | C13: Monthly | D13: =ROUND('Recurring Budgets'!F9*60,0)/1440 -> 0.09375 | E13: =ROUND('Recurring Budgets'!F9*IF(H13="CFO",Assumptions!$B$5,Assumptions!$B$4),0) -> 214 | F13: =ROUND('Recurring Budgets'!G9*60,0)/1440 -> 0.029166667 | G13: =ROUND('Recurring Budgets'!G9*Assumptions!$B$5,0) -> 175 | H13: ='Recurring Budgets'!L9 -> Staff
A14: 4530 W Flint LLC | B14: 1099 Quarterly Review (ongoing, after Oct 30) | C14: Quarterly | D14: =ROUND('Recurring Budgets'!F10*60,0)/1440 -> 0.052083333 | E14: =ROUND('Recurring Budgets'!F10*IF(H14="CFO",Assumptions!$B$5,Assumptions!$B$4),0) -> 119 | F14: =ROUND('Recurring Budgets'!G10*60,0)/1440 -> 0 | G14: =ROUND('Recurring Budgets'!G10*Assumptions!$B$5,0) -> 0 | H14: ='Recurring Budgets'!L10 -> Staff
B15: Month End Close | C15: Monthly | D15: =ROUND('Recurring Budgets'!F11*60,0)/1440 -> 0.034722222 | E15: =ROUND('Recurring Budgets'!F11*IF(H15="CFO",Assumptions!$B$5,Assumptions!$B$4),0) -> 79 | F15: =ROUND('Recurring Budgets'!G11*60,0)/1440 -> 0.029166667 | G15: =ROUND('Recurring Budgets'!G11*Assumptions!$B$5,0) -> 175 | H15: ='Recurring Budgets'!L11 -> Staff
A16: 7327 Tierra Buena LLC | B16: 1099 Quarterly Review (ongoing, after Oct 30) | C16: Quarterly | D16: =ROUND('Recurring Budgets'!F12*60,0)/1440 -> 0.03125 | E16: =ROUND('Recurring Budgets'!F12*IF(H16="CFO",Assumptions!$B$5,Assumptions!$B$4),0) -> 71 | F16: =ROUND('Recurring Budgets'!G12*60,0)/1440 -> 0 | G16: =ROUND('Recurring Budgets'!G12*Assumptions!$B$5,0) -> 0 | H16: ='Recurring Budgets'!L12 -> Staff
B17: Month End Close | C17: Monthly | D17: =ROUND('Recurring Budgets'!F13*60,0)/1440 -> 0.048611111 | E17: =ROUND('Recurring Budgets'!F13*IF(H17="CFO",Assumptions!$B$5,Assumptions!$B$4),0) -> 111 | F17: =ROUND('Recurring Budgets'!G13*60,0)/1440 -> 0.029166667 | G17: =ROUND('Recurring Budgets'!G13*Assumptions!$B$5,0) -> 175 | H17: ='Recurring Budgets'!L13 -> Staff
A18: 7730 Evans LLC | B18: 1099 Quarterly Review (ongoing, after Oct 30) | C18: Quarterly | D18: =ROUND('Recurring Budgets'!F14*60,0)/1440 -> 0.015972222 | E18: =ROUND('Recurring Budgets'!F14*IF(H18="CFO",Assumptions!$B$5,Assumptions!$B$4),0) -> 36 | F18: =ROUND('Recurring Budgets'!G14*60,0)/1440 -> 0 | G18: =ROUND('Recurring Budgets'!G14*Assumptions!$B$5,0) -> 0 | H18: ='Recurring Budgets'!L14 -> Staff
B19: Month End Close | C19: Monthly | D19: =ROUND('Recurring Budgets'!F15*60,0)/1440 -> 0.03125 | E19: =ROUND('Recurring Budgets'!F15*IF(H19="CFO",Assumptions!$B$5,Assumptions!$B$4),0) -> 71 | F19: =ROUND('Recurring Budgets'!G15*60,0)/1440 -> 0.015972222 | G19: =ROUND('Recurring Budgets'!G15*Assumptions!$B$5,0) -> 96 | H19: ='Recurring Budgets'!L15 -> Staff
A20: 909 MAIN LLC | B20: 1099 Quarterly Review (ongoing, after Oct 30) | C20: Quarterly | D20: =ROUND('Recurring Budgets'!F16*60,0)/1440 -> 0.015972222 | E20: =ROUND('Recurring Budgets'!F16*IF(H20="CFO",Assumptions!$B$5,Assumptions!$B$4),0) -> 36 | F20: =ROUND('Recurring Budgets'!G16*60,0)/1440 -> 0 | G20: =ROUND('Recurring Budgets'!G16*Assumptions!$B$5,0) -> 0 | H20: ='Recurring Budgets'!L16 -> Staff
B21: Month End Close | C21: Monthly | D21: =ROUND('Recurring Budgets'!F17*60,0)/1440 -> 0.052083333 | E21: =ROUND('Recurring Budgets'!F17*IF(H21="CFO",Assumptions!$B$5,Assumptions!$B$4),0) -> 119 | F21: =ROUND('Recurring Budgets'!G17*60,0)/1440 -> 0.020138889 | G21: =ROUND('Recurring Budgets'!G17*Assumptions!$B$5,0) -> 121 | H21: ='Recurring Budgets'!L17 -> Staff
A22: Amerisource HR Consulting Group LLC | B22: 1099 Quarterly Review (ongoing, after Oct 30) | C22: Quarterly | D22: =ROUND('Recurring Budgets'!F18*60,0)/1440 -> 0.03125 | E22: =ROUND('Recurring Budgets'!F18*IF(H22="CFO",Assumptions!$B$5,Assumptions!$B$4),0) -> 71 | F22: =ROUND('Recurring Budgets'!G18*60,0)/1440 -> 0 | G22: =ROUND('Recurring Budgets'!G18*Assumptions!$B$5,0) -> 0 | H22: ='Recurring Budgets'!L18 -> Staff
B23: Adjusting Journal Entry Request | C23: Annual | D23: =ROUND('Recurring Budgets'!F19*60,0)/1440 -> 0.23611111 | E23: =ROUND('Recurring Budgets'!F19*IF(H23="CFO",Assumptions!$B$5,Assumptions!$B$4),0) -> 538 | F23: =ROUND('Recurring Budgets'!G19*60,0)/1440 -> 0 | G23: =ROUND('Recurring Budgets'!G19*Assumptions!$B$5,0) -> 0 | H23: ='Recurring Budgets'!L19 -> Staff
B24: Month End Close | C24: Monthly | D24: =ROUND('Recurring Budgets'!F20*60,0)/1440 -> 0.67361111 | E24: =ROUND('Recurring Budgets'!F20*IF(H24="CFO",Assumptions!$B$5,Assumptions!$B$4),0) -> 1536 | F24: =ROUND('Recurring Budgets'!G20*60,0)/1440 -> 0.041666667 | G24: =ROUND('Recurring Budgets'!G20*Assumptions!$B$5,0) -> 250 | H24: ='Recurring Budgets'!L20 -> Staff
B25: Bookkeeping & Bill Pay | C25: Weekly | D25: =ROUND('Recurring Budgets'!F21*60,0)/1440 -> 0.076388889 | E25: =ROUND('Recurring Budgets'!F21*IF(H25="CFO",Assumptions!$B$5,Assumptions!$B$4),0) -> 174 | F25: =ROUND('Recurring Budgets'!G21*60,0)/1440 -> 0 | G25: =ROUND('Recurring Budgets'!G21*Assumptions!$B$5,0) -> 0 | H25: ='Recurring Budgets'!L21 -> Staff
A26: BSD Contracting LLC | B26: 1099 Quarterly Review (ongoing, after Oct 30) | C26: Quarterly | D26: =ROUND('Recurring Budgets'!F22*60,0)/1440 -> 0.083333333 | E26: =ROUND('Recurring Budgets'!F22*IF(H26="CFO",Assumptions!$B$5,Assumptions!$B$4),0) -> 190 | F26: =ROUND('Recurring Budgets'!G22*60,0)/1440 -> 0 | G26: =ROUND('Recurring Budgets'!G22*Assumptions!$B$5,0) -> 0 | H26: ='Recurring Budgets'!L22 -> Staff
B27: Month End Close | C27: Monthly | D27: =ROUND('Recurring Budgets'!F23*60,0)/1440 -> 0.03125 | E27: =ROUND('Recurring Budgets'!F23*IF(H27="CFO",Assumptions!$B$5,Assumptions!$B$4),0) -> 71 | F27: =ROUND('Recurring Budgets'!G23*60,0)/1440 -> 0.020833333 | G27: =ROUND('Recurring Budgets'!G23*Assumptions!$B$5,0) -> 125 | H27: ='Recurring Budgets'!L23 -> Staff
A28: Barrett Living Trust | B28: Adjusting Journal Entry Request | C28: Annual | D28: =ROUND('Recurring Budgets'!F24*60,0)/1440 -> 0.020833333 | E28: =ROUND('Recurring Budgets'!F24*IF(H28="CFO",Assumptions!$B$5,Assumptions!$B$4),0) -> 48 | F28: =ROUND('Recurring Budgets'!G24*60,0)/1440 -> 0 | G28: =ROUND('Recurring Budgets'!G24*Assumptions!$B$5,0) -> 0 | H28: ='Recurring Budgets'!L24 -> Staff
B29: Month End Close | C29: Monthly | D29: =ROUND('Recurring Budgets'!F25*60,0)/1440 -> 0.11805556 | E29: =ROUND('Recurring Budgets'!F25*IF(H29="CFO",Assumptions!$B$5,Assumptions!$B$4),0) -> 269 | F29: =ROUND('Recurring Budgets'!G25*60,0)/1440 -> 0.045833333 | G29: =ROUND('Recurring Budgets'!G25*Assumptions!$B$5,0) -> 275 | H29: ='Recurring Budgets'!L25 -> Staff
A30: BeckShar Development LLC | B30: 1099 Quarterly Review (ongoing, after Oct 30) | C30: Quarterly | D30: =ROUND('Recurring Budgets'!F26*60,0)/1440 -> 0.03125 | E30: =ROUND('Recurring Budgets'!F26*IF(H30="CFO",Assumptions!$B$5,Assumptions!$B$4),0) -> 71 | F30: =ROUND('Recurring Budgets'!G26*60,0)/1440 -> 0 | G30: =ROUND('Recurring Budgets'!G26*Assumptions!$B$5,0) -> 0 | H30: ='Recurring Budgets'!L26 -> Staff
B31: Month End Close | C31: Monthly | D31: =ROUND('Recurring Budgets'!F27*60,0)/1440 -> 0.28819444 | E31: =ROUND('Recurring Budgets'!F27*IF(H31="CFO",Assumptions!$B$5,Assumptions!$B$4),0) -> 657 | F31: =ROUND('Recurring Budgets'!G27*60,0)/1440 -> 0.033333333 | G31: =ROUND('Recurring Budgets'!G27*Assumptions!$B$5,0) -> 200 | H31: ='Recurring Budgets'!L27 -> Staff
A32: BeckShar Diamond Commercial LLC | B32: 1099 Quarterly Review (ongoing, after Oct 30) | C32: Quarterly | D32: =ROUND('Recurring Budgets'!F28*60,0)/1440 -> 0.03125 | E32: =ROUND('Recurring Budgets'!F28*IF(H32="CFO",Assumptions!$B$5,Assumptions!$B$4),0) -> 71 | F32: =ROUND('Recurring Budgets'!G28*60,0)/1440 -> 0 | G32: =ROUND('Recurring Budgets'!G28*Assumptions!$B$5,0) -> 0 | H32: ='Recurring Budgets'!L28 -> Staff
B33: Month End Close | C33: Monthly | D33: =ROUND('Recurring Budgets'!F29*60,0)/1440 -> 0.017361111 | E33: =ROUND('Recurring Budgets'!F29*IF(H33="CFO",Assumptions!$B$5,Assumptions!$B$4),0) -> 40 | F33: =ROUND('Recurring Budgets'!G29*60,0)/1440 -> 0.020833333 | G33: =ROUND('Recurring Budgets'!G29*Assumptions!$B$5,0) -> 125 | H33: ='Recurring Budgets'!L29 -> Staff
A34: BeckShar LLC | B34: 1099 Quarterly Review (ongoing, after Oct 30) | C34: Quarterly | D34: =ROUND('Recurring Budgets'!F30*60,0)/1440 -> 0.083333333 | E34: =ROUND('Recurring Budgets'!F30*IF(H34="CFO",Assumptions!$B$5,Assumptions!$B$4),0) -> 190 | F34: =ROUND('Recurring Budgets'!G30*60,0)/1440 -> 0 | G34: =ROUND('Recurring Budgets'!G30*Assumptions!$B$5,0) -> 0 | H34: ='Recurring Budgets'!L30 -> Staff
B35: Month End Close | C35: Monthly | D35: =ROUND('Recurring Budgets'!F31*60,0)/1440 -> 0.12152778 | E35: =ROUND('Recurring Budgets'!F31*IF(H35="CFO",Assumptions!$B$5,Assumptions!$B$4),0) -> 277 | F35: =ROUND('Recurring Budgets'!G31*60,0)/1440 -> 0.052083333 | G35: =ROUND('Recurring Budgets'!G31*Assumptions!$B$5,0) -> 313 | H35: ='Recurring Budgets'!L31 -> Staff
A36: Building and Development Professionals LLC | B36: 1099 Quarterly Review (ongoing, after Oct 30) | C36: Quarterly | D36: =ROUND('Recurring Budgets'!F32*60,0)/1440 -> 0.083333333 | E36: =ROUND('Recurring Budgets'!F32*IF(H36="CFO",Assumptions!$B$5,Assumptions!$B$4),0) -> 190 | F36: =ROUND('Recurring Budgets'!G32*60,0)/1440 -> 0 | G36: =ROUND('Recurring Budgets'!G32*Assumptions!$B$5,0) -> 0 | H36: ='Recurring Budgets'!L32 -> Staff
B37: Month End Close | C37: Monthly | D37: =ROUND('Recurring Budgets'!F33*60,0)/1440 -> 0.11458333 | E37: =ROUND('Recurring Budgets'!F33*IF(H37="CFO",Assumptions!$B$5,Assumptions!$B$4),0) -> 688 | F37: =ROUND('Recurring Budgets'!G33*60,0)/1440 -> 0.020833333 | G37: =ROUND('Recurring Budgets'!G33*Assumptions!$B$5,0) -> 125 | H37: ='Recurring Budgets'!L33 -> CFO
A38: Capital Financial LLC | B38: 1099 Quarterly Review (ongoing, after Oct 30) | C38: Quarterly | D38: =ROUND('Recurring Budgets'!F34*60,0)/1440 -> 0.03125 | E38: =ROUND('Recurring Budgets'!F34*IF(H38="CFO",Assumptions!$B$5,Assumptions!$B$4),0) -> 71 | F38: =ROUND('Recurring Budgets'!G34*60,0)/1440 -> 0 | G38: =ROUND('Recurring Budgets'!G34*Assumptions!$B$5,0) -> 0 | H38: ='Recurring Budgets'!L34 -> Staff
B39: Month End Close | C39: Monthly | D39: =ROUND('Recurring Budgets'!F35*60,0)/1440 -> 0.31944444 | E39: =ROUND('Recurring Budgets'!F35*IF(H39="CFO",Assumptions!$B$5,Assumptions!$B$4),0) -> 728 | F39: =ROUND('Recurring Budgets'!G35*60,0)/1440 -> 0.05 | G39: =ROUND('Recurring Budgets'!G35*Assumptions!$B$5,0) -> 300 | H39: ='Recurring Budgets'!L35 -> Staff
A40: Catalpa Industrial Park Inc | B40: 1099 Quarterly Review (ongoing, after Oct 30) | C40: Quarterly | D40: =ROUND('Recurring Budgets'!F36*60,0)/1440 -> 0.083333333 | E40: =ROUND('Recurring Budgets'!F36*IF(H40="CFO",Assumptions!$B$5,Assumptions!$B$4),0) -> 190 | F40: =ROUND('Recurring Budgets'!G36*60,0)/1440 -> 0 | G40: =ROUND('Recurring Budgets'!G36*Assumptions!$B$5,0) -> 0 | H40: ='Recurring Budgets'!L36 -> Staff
B41: Month End Close | C41: Monthly | D41: =ROUND('Recurring Budgets'!F37*60,0)/1440 -> 0.18402778 | E41: =ROUND('Recurring Budgets'!F37*IF(H41="CFO",Assumptions!$B$5,Assumptions!$B$4),0) -> 420 | F41: =ROUND('Recurring Budgets'!G37*60,0)/1440 -> 0.029166667 | G41: =ROUND('Recurring Budgets'!G37*Assumptions!$B$5,0) -> 175 | H41: ='Recurring Budgets'!L37 -> Staff
A42: Desert Quail Creative Classroom LLC | B42: 1099 Quarterly Review (ongoing, after Oct 30) | C42: Quarterly | D42: =ROUND('Recurring Budgets'!F38*60,0)/1440 -> 0.015972222 | E42: =ROUND('Recurring Budgets'!F38*IF(H42="CFO",Assumptions!$B$5,Assumptions!$B$4),0) -> 36 | F42: =ROUND('Recurring Budgets'!G38*60,0)/1440 -> 0 | G42: =ROUND('Recurring Budgets'!G38*Assumptions!$B$5,0) -> 0 | H42: ='Recurring Budgets'!L38 -> Staff
B43: Month End Close | C43: Monthly | D43: =ROUND('Recurring Budgets'!F39*60,0)/1440 -> 0.03125 | E43: =ROUND('Recurring Budgets'!F39*IF(H43="CFO",Assumptions!$B$5,Assumptions!$B$4),0) -> 71 | F43: =ROUND('Recurring Budgets'!G39*60,0)/1440 -> 0.020833333 | G43: =ROUND('Recurring Budgets'!G39*Assumptions!$B$5,0) -> 125 | H43: ='Recurring Budgets'!L39 -> Staff
A44: Educational Services Holdings LLC | B44: 1099 Quarterly Review (ongoing, after Oct 30) | C44: Quarterly | D44: =ROUND('Recurring Budgets'!F40*60,0)/1440 -> 0.03125 | E44: =ROUND('Recurring Budgets'!F40*IF(H44="CFO",Assumptions!$B$5,Assumptions!$B$4),0) -> 71 | F44: =ROUND('Recurring Budgets'!G40*60,0)/1440 -> 0 | G44: =ROUND('Recurring Budgets'!G40*Assumptions!$B$5,0) -> 0 | H44: ='Recurring Budgets'!L40 -> Staff
B45: Month End Close | C45: Monthly | D45: =ROUND('Recurring Budgets'!F41*60,0)/1440 -> 0.23958333 | E45: =ROUND('Recurring Budgets'!F41*IF(H45="CFO",Assumptions!$B$5,Assumptions!$B$4),0) -> 1438 | F45: =ROUND('Recurring Budgets'!G41*60,0)/1440 -> 0.020138889 | G45: =ROUND('Recurring Budgets'!G41*Assumptions!$B$5,0) -> 121 | H45: ='Recurring Budgets'!L41 -> CFO
A46: Educational Services LLC (dba ESI) | B46: Annual Audit Support | C46: Annual | D46: =ROUND('Recurring Budgets'!F43*60,0)/1440 -> 0.125 | E46: =ROUND('Recurring Budgets'!F43*IF(H46="CFO",Assumptions!$B$5,Assumptions!$B$4),0) -> 750 | F46: =ROUND('Recurring Budgets'!G43*60,0)/1440 -> 0 | G46: =ROUND('Recurring Budgets'!G43*Assumptions!$B$5,0) -> 0 | H46: ='Recurring Budgets'!L43 -> CFO
B47: Month End Close | C47: Monthly | D47: =ROUND('Recurring Budgets'!F44*60,0)/1440 -> 0.22916667 | E47: =ROUND('Recurring Budgets'!F44*IF(H47="CFO",Assumptions!$B$5,Assumptions!$B$4),0) -> 1375 | F47: =ROUND('Recurring Budgets'!G44*60,0)/1440 -> 0.072916667 | G47: =ROUND('Recurring Budgets'!G44*Assumptions!$B$5,0) -> 438 | H47: ='Recurring Budgets'!L44 -> CFO
A48: Eight Eleven LLC | B48: 1099 Quarterly Review (ongoing, after Oct 30) | C48: Quarterly | D48: =ROUND('Recurring Budgets'!F45*60,0)/1440 -> 0.083333333 | E48: =ROUND('Recurring Budgets'!F45*IF(H48="CFO",Assumptions!$B$5,Assumptions!$B$4),0) -> 190 | F48: =ROUND('Recurring Budgets'!G45*60,0)/1440 -> 0 | G48: =ROUND('Recurring Budgets'!G45*Assumptions!$B$5,0) -> 0 | H48: ='Recurring Budgets'!L45 -> Staff
B49: Month End Close | C49: Monthly | D49: =ROUND('Recurring Budgets'!F46*60,0)/1440 -> 0.92361111 | E49: =ROUND('Recurring Budgets'!F46*IF(H49="CFO",Assumptions!$B$5,Assumptions!$B$4),0) -> 2106 | F49: =ROUND('Recurring Budgets'!G46*60,0)/1440 -> 0.0625 | G49: =ROUND('Recurring Budgets'!G46*Assumptions!$B$5,0) -> 375 | H49: ='Recurring Budgets'!L46 -> Staff
B50: Weekly Accounting Work | C50: Weekly | D50: =ROUND('Recurring Budgets'!F47*60,0)/1440 -> 0.10763889 | E50: =ROUND('Recurring Budgets'!F47*IF(H50="CFO",Assumptions!$B$5,Assumptions!$B$4),0) -> 245 | F50: =ROUND('Recurring Budgets'!G47*60,0)/1440 -> 0 | G50: =ROUND('Recurring Budgets'!G47*Assumptions!$B$5,0) -> 0 | H50: ='Recurring Budgets'!L47 -> Staff
A51: FiveOliver LLC | B51: 1099 Quarterly Review (ongoing, after Oct 30) | C51: Quarterly | D51: =ROUND('Recurring Budgets'!F48*60,0)/1440 -> 0.083333333 | E51: =ROUND('Recurring Budgets'!F48*IF(H51="CFO",Assumptions!$B$5,Assumptions!$B$4),0) -> 190 | F51: =ROUND('Recurring Budgets'!G48*60,0)/1440 -> 0 | G51: =ROUND('Recurring Budgets'!G48*Assumptions!$B$5,0) -> 0 | H51: ='Recurring Budgets'!L48 -> Staff
A52: GAV Enterprises Inc | B52: 1099 Quarterly Review (ongoing, after Oct 30) | C52: Quarterly | D52: =ROUND('Recurring Budgets'!F49*60,0)/1440 -> 0.03125 | E52: =ROUND('Recurring Budgets'!F49*IF(H52="CFO",Assumptions!$B$5,Assumptions!$B$4),0) -> 71 | F52: =ROUND('Recurring Budgets'!G49*60,0)/1440 -> 0 | G52: =ROUND('Recurring Budgets'!G49*Assumptions!$B$5,0) -> 0 | H52: ='Recurring Budgets'!L49 -> Staff
B53: Adjusting Journal Entry Request | C53: Annual | D53: =ROUND('Recurring Budgets'!F50*60,0)/1440 -> 0.013888889 | E53: =ROUND('Recurring Budgets'!F50*IF(H53="CFO",Assumptions!$B$5,Assumptions!$B$4),0) -> 32 | F53: =ROUND('Recurring Budgets'!G50*60,0)/1440 -> 0 | G53: =ROUND('Recurring Budgets'!G50*Assumptions!$B$5,0) -> 0 | H53: ='Recurring Budgets'!L50 -> Staff
B54: Year-End Tax Coordination | C54: Annual | D54: =ROUND('Recurring Budgets'!F51*60,0)/1440 -> 0.013888889 | E54: =ROUND('Recurring Budgets'!F51*IF(H54="CFO",Assumptions!$B$5,Assumptions!$B$4),0) -> 32 | F54: =ROUND('Recurring Budgets'!G51*60,0)/1440 -> 0 | G54: =ROUND('Recurring Budgets'!G51*Assumptions!$B$5,0) -> 0 | H54: ='Recurring Budgets'!L51 -> Staff
B55: Quarter End Close | C55: Quarterly | D55: =ROUND('Recurring Budgets'!F52*60,0)/1440 -> 0.77430556 | E55: =ROUND('Recurring Budgets'!F52*IF(H55="CFO",Assumptions!$B$5,Assumptions!$B$4),0) -> 1765 | F55: =ROUND('Recurring Budgets'!G52*60,0)/1440 -> 0.0625 | G55: =ROUND('Recurring Budgets'!G52*Assumptions!$B$5,0) -> 375 | H55: ='Recurring Budgets'!L52 -> Staff
A56: KAMM ADGT LLC | B56: 1099 Quarterly Review (ongoing, after Oct 30) | C56: Quarterly | D56: =ROUND('Recurring Budgets'!F62*60,0)/1440 -> 0.015972222 | E56: =ROUND('Recurring Budgets'!F62*IF(H56="CFO",Assumptions!$B$5,Assumptions!$B$4),0) -> 36 | F56: =ROUND('Recurring Budgets'!G62*60,0)/1440 -> 0 | G56: =ROUND('Recurring Budgets'!G62*Assumptions!$B$5,0) -> 0 | H56: ='Recurring Budgets'!L62 -> Staff
B57: Month End Close | C57: Monthly | D57: =ROUND('Recurring Budgets'!F63*60,0)/1440 -> 0.020833333 | E57: =ROUND('Recurring Budgets'!F63*IF(H57="CFO",Assumptions!$B$5,Assumptions!$B$4),0) -> 48 | F57: =ROUND('Recurring Budgets'!G63*60,0)/1440 -> 0.015972222 | G57: =ROUND('Recurring Budgets'!G63*Assumptions!$B$5,0) -> 96 | H57: ='Recurring Budgets'!L63 -> Staff
A58: Little Moo's LLC | B58: 1099 Quarterly Review (ongoing, after Oct 30) | C58: Quarterly | D58: =ROUND('Recurring Budgets'!F64*60,0)/1440 -> 0.015972222 | E58: =ROUND('Recurring Budgets'!F64*IF(H58="CFO",Assumptions!$B$5,Assumptions!$B$4),0) -> 36 | F58: =ROUND('Recurring Budgets'!G64*60,0)/1440 -> 0 | G58: =ROUND('Recurring Budgets'!G64*Assumptions!$B$5,0) -> 0 | H58: ='Recurring Budgets'!L64 -> Staff
B59: Month End Close | C59: Monthly | D59: =ROUND('Recurring Budgets'!F65*60,0)/1440 -> 0.069444444 | E59: =ROUND('Recurring Budgets'!F65*IF(H59="CFO",Assumptions!$B$5,Assumptions!$B$4),0) -> 158 | F59: =ROUND('Recurring Budgets'!G65*60,0)/1440 -> 0.015972222 | G59: =ROUND('Recurring Budgets'!G65*Assumptions!$B$5,0) -> 96 | H59: ='Recurring Budgets'!L65 -> Staff
B60: Sales Tax Filing - Onyx Prepares the Returns for Client | C60: Monthly | D60: =ROUND('Recurring Budgets'!F66*60,0)/1440 -> 0.038194444 | E60: =ROUND('Recurring Budgets'!F66*IF(H60="CFO",Assumptions!$B$5,Assumptions!$B$4),0) -> 87 | F60: =ROUND('Recurring Budgets'!G66*60,0)/1440 -> 0 | G60: =ROUND('Recurring Budgets'!G66*Assumptions!$B$5,0) -> 0 | H60: ='Recurring Budgets'!L66 -> Staff
A61: Midwest Contracting Inc | B61: 1099 Quarterly Review (ongoing, after Oct 30) | C61: Quarterly | D61: =ROUND('Recurring Budgets'!F67*60,0)/1440 -> 0.083333333 | E61: =ROUND('Recurring Budgets'!F67*IF(H61="CFO",Assumptions!$B$5,Assumptions!$B$4),0) -> 190 | F61: =ROUND('Recurring Budgets'!G67*60,0)/1440 -> 0 | G61: =ROUND('Recurring Budgets'!G67*Assumptions!$B$5,0) -> 0 | H61: ='Recurring Budgets'!L67 -> Staff
B62: Month End Close | C62: Monthly | D62: =ROUND('Recurring Budgets'!F68*60,0)/1440 -> 1.4722222 | E62: =ROUND('Recurring Budgets'!F68*IF(H62="CFO",Assumptions!$B$5,Assumptions!$B$4),0) -> 3357 | F62: =ROUND('Recurring Budgets'!G68*60,0)/1440 -> 0.0625 | G62: =ROUND('Recurring Budgets'!G68*Assumptions!$B$5,0) -> 375 | H62: ='Recurring Budgets'!L68 -> Staff
B63: Weekly Accounting | C63: Weekly | D63: =ROUND('Recurring Budgets'!F69*60,0)/1440 -> 0.09375 | E63: =ROUND('Recurring Budgets'!F69*IF(H63="CFO",Assumptions!$B$5,Assumptions!$B$4),0) -> 214 | F63: =ROUND('Recurring Budgets'!G69*60,0)/1440 -> 0 | G63: =ROUND('Recurring Budgets'!G69*Assumptions!$B$5,0) -> 0 | H63: ='Recurring Budgets'!L69 -> Staff
A64: Mohrschladt Capital LP | B64: 1099 Quarterly Review (ongoing, after Oct 30) | C64: Quarterly | D64: =ROUND('Recurring Budgets'!F70*60,0)/1440 -> 0.03125 | E64: =ROUND('Recurring Budgets'!F70*IF(H64="CFO",Assumptions!$B$5,Assumptions!$B$4),0) -> 71 | F64: =ROUND('Recurring Budgets'!G70*60,0)/1440 -> 0 | G64: =ROUND('Recurring Budgets'!G70*Assumptions!$B$5,0) -> 0 | H64: ='Recurring Budgets'!L70 -> Staff
B65: Month End Close | C65: Monthly | D65: =ROUND('Recurring Budgets'!F71*60,0)/1440 -> 0.13541667 | E65: =ROUND('Recurring Budgets'!F71*IF(H65="CFO",Assumptions!$B$5,Assumptions!$B$4),0) -> 309 | F65: =ROUND('Recurring Budgets'!G71*60,0)/1440 -> 0.029166667 | G65: =ROUND('Recurring Budgets'!G71*Assumptions!$B$5,0) -> 175 | H65: ='Recurring Budgets'!L71 -> Staff
A66: Mohrschladt Howarth Associates Inc | B66: 1099 Quarterly Review (ongoing, after Oct 30) | C66: Quarterly | D66: =ROUND('Recurring Budgets'!F72*60,0)/1440 -> 0.083333333 | E66: =ROUND('Recurring Budgets'!F72*IF(H66="CFO",Assumptions!$B$5,Assumptions!$B$4),0) -> 190 | F66: =ROUND('Recurring Budgets'!G72*60,0)/1440 -> 0 | G66: =ROUND('Recurring Budgets'!G72*Assumptions!$B$5,0) -> 0 | H66: ='Recurring Budgets'!L72 -> Staff
B67: Month End Close | C67: Monthly | D67: =ROUND('Recurring Budgets'!F73*60,0)/1440 -> 0.072916667 | E67: =ROUND('Recurring Budgets'!F73*IF(H67="CFO",Assumptions!$B$5,Assumptions!$B$4),0) -> 166 | F67: =ROUND('Recurring Budgets'!G73*60,0)/1440 -> 0.029166667 | G67: =ROUND('Recurring Budgets'!G73*Assumptions!$B$5,0) -> 175 | H67: ='Recurring Budgets'!L73 -> Staff
A68: Mountain Trade Supply Inc | B68: 1099 Quarterly Review (ongoing, after Oct 30) | C68: Quarterly | D68: =ROUND('Recurring Budgets'!F74*60,0)/1440 -> 0.083333333 | E68: =ROUND('Recurring Budgets'!F74*IF(H68="CFO",Assumptions!$B$5,Assumptions!$B$4),0) -> 190 | F68: =ROUND('Recurring Budgets'!G74*60,0)/1440 -> 0 | G68: =ROUND('Recurring Budgets'!G74*Assumptions!$B$5,0) -> 0 | H68: ='Recurring Budgets'!L74 -> Staff
B69: Payroll Bi-Weekly 401K Payment | C69: Bi-weekly | D69: =ROUND('Recurring Budgets'!F75*60,0)/1440 -> 0.013888889 | E69: =ROUND('Recurring Budgets'!F75*IF(H69="CFO",Assumptions!$B$5,Assumptions!$B$4),0) -> 32 | F69: =ROUND('Recurring Budgets'!G75*60,0)/1440 -> 0.0069444444 | G69: =ROUND('Recurring Budgets'!G75*Assumptions!$B$5,0) -> 42 | H69: ='Recurring Budgets'!L75 -> Staff
B70: Run Payroll in Paychex | C70: Bi-weekly | D70: =ROUND('Recurring Budgets'!F76*60,0)/1440 -> 0.038194444 | E70: =ROUND('Recurring Budgets'!F76*IF(H70="CFO",Assumptions!$B$5,Assumptions!$B$4),0) -> 87 | F70: =ROUND('Recurring Budgets'!G76*60,0)/1440 -> 0.010416667 | G70: =ROUND('Recurring Budgets'!G76*Assumptions!$B$5,0) -> 63 | H70: ='Recurring Budgets'!L76 -> Staff
B71: Month End Close | C71: Monthly | D71: =ROUND('Recurring Budgets'!F77*60,0)/1440 -> 0.19444444 | E71: =ROUND('Recurring Budgets'!F77*IF(H71="CFO",Assumptions!$B$5,Assumptions!$B$4),0) -> 443 | F71: =ROUND('Recurring Budgets'!G77*60,0)/1440 -> 0.034722222 | G71: =ROUND('Recurring Budgets'!G77*Assumptions!$B$5,0) -> 208 | H71: ='Recurring Budgets'!L77 -> Staff
A72: Newport Classic Cars LLC | B72: 1099 Quarterly Review (ongoing, after Oct 30) | C72: Quarterly | D72: =ROUND('Recurring Budgets'!F78*60,0)/1440 -> 0.03125 | E72: =ROUND('Recurring Budgets'!F78*IF(H72="CFO",Assumptions!$B$5,Assumptions!$B$4),0) -> 71 | F72: =ROUND('Recurring Budgets'!G78*60,0)/1440 -> 0 | G72: =ROUND('Recurring Budgets'!G78*Assumptions!$B$5,0) -> 0 | H72: ='Recurring Budgets'!L78 -> Staff
B73: Quarterly Month End Close | C73: Quarterly | D73: =ROUND('Recurring Budgets'!F79*60,0)/1440 -> 0.059027778 | E73: =ROUND('Recurring Budgets'!F79*IF(H73="CFO",Assumptions!$B$5,Assumptions!$B$4),0) -> 135 | F73: =ROUND('Recurring Budgets'!G79*60,0)/1440 -> 0.029166667 | G73: =ROUND('Recurring Budgets'!G79*Assumptions!$B$5,0) -> 175 | H73: ='Recurring Budgets'!L79 -> Staff
B74: Quarterly Sales Tax Returns - Onyx Prepares the Returns for Client | C74: Quarterly | D74: =ROUND('Recurring Budgets'!F80*60,0)/1440 -> 0.020833333 | E74: =ROUND('Recurring Budgets'!F80*IF(H74="CFO",Assumptions!$B$5,Assumptions!$B$4),0) -> 48 | F74: =ROUND('Recurring Budgets'!G80*60,0)/1440 -> 0 | G74: =ROUND('Recurring Budgets'!G80*Assumptions!$B$5,0) -> 0 | H74: ='Recurring Budgets'!L80 -> Staff
A75: Obsidian Real Estate LLC | B75: 1099 Quarterly Review (ongoing, after Oct 30) | C75: Quarterly | D75: =ROUND('Recurring Budgets'!F81*60,0)/1440 -> 0.083333333 | E75: =ROUND('Recurring Budgets'!F81*IF(H75="CFO",Assumptions!$B$5,Assumptions!$B$4),0) -> 190 | F75: =ROUND('Recurring Budgets'!G81*60,0)/1440 -> 0 | G75: =ROUND('Recurring Budgets'!G81*Assumptions!$B$5,0) -> 0 | H75: ='Recurring Budgets'!L81 -> Staff
B76: Adjusting Journal Entry Request | C76: Annual | D76: =ROUND('Recurring Budgets'!F82*60,0)/1440 -> 0.024305556 | E76: =ROUND('Recurring Budgets'!F82*IF(H76="CFO",Assumptions!$B$5,Assumptions!$B$4),0) -> 55 | F76: =ROUND('Recurring Budgets'!G82*60,0)/1440 -> 0 | G76: =ROUND('Recurring Budgets'!G82*Assumptions!$B$5,0) -> 0 | H76: ='Recurring Budgets'!L82 -> Staff
B77: Month End Close | C77: Monthly | D77: =ROUND('Recurring Budgets'!F83*60,0)/1440 -> 0.23958333 | E77: =ROUND('Recurring Budgets'!F83*IF(H77="CFO",Assumptions!$B$5,Assumptions!$B$4),0) -> 546 | F77: =ROUND('Recurring Budgets'!G83*60,0)/1440 -> 0.029166667 | G77: =ROUND('Recurring Budgets'!G83*Assumptions!$B$5,0) -> 175 | H77: ='Recurring Budgets'!L83 -> Staff
B78: Monthly Reports and Bank Statements | C78: Monthly | D78: =ROUND('Recurring Budgets'!F84*60,0)/1440 -> 0.020833333 | E78: =ROUND('Recurring Budgets'!F84*IF(H78="CFO",Assumptions!$B$5,Assumptions!$B$4),0) -> 48 | F78: =ROUND('Recurring Budgets'!G84*60,0)/1440 -> 0 | G78: =ROUND('Recurring Budgets'!G84*Assumptions!$B$5,0) -> 0 | H78: ='Recurring Budgets'!L84 -> Staff
A79: Paradise Village LLC | B79: Adjusting Journal Entry Request | C79: Annual | D79: =ROUND('Recurring Budgets'!F85*60,0)/1440 -> 0.0069444444 | E79: =ROUND('Recurring Budgets'!F85*IF(H79="CFO",Assumptions!$B$5,Assumptions!$B$4),0) -> 16 | F79: =ROUND('Recurring Budgets'!G85*60,0)/1440 -> 0 | G79: =ROUND('Recurring Budgets'!G85*Assumptions!$B$5,0) -> 0 | H79: ='Recurring Budgets'!L85 -> Staff
B80: Quarter End Close | C80: Quarterly | D80: =ROUND('Recurring Budgets'!F86*60,0)/1440 -> 0.041666667 | E80: =ROUND('Recurring Budgets'!F86*IF(H80="CFO",Assumptions!$B$5,Assumptions!$B$4),0) -> 95 | F80: =ROUND('Recurring Budgets'!G86*60,0)/1440 -> 0.041666667 | G80: =ROUND('Recurring Budgets'!G86*Assumptions!$B$5,0) -> 250 | H80: ='Recurring Budgets'!L86 -> Staff
A81: Phil Tavasci Companies | B81: Daily Chase Fraud Review | C81: Daily | D81: =ROUND('Recurring Budgets'!F87*60,0)/1440 -> 0.0034722222 | E81: =ROUND('Recurring Budgets'!F87*IF(H81="CFO",Assumptions!$B$5,Assumptions!$B$4),0) -> 8 | F81: =ROUND('Recurring Budgets'!G87*60,0)/1440 -> 0 | G81: =ROUND('Recurring Budgets'!G87*Assumptions!$B$5,0) -> 0 | H81: ='Recurring Budgets'!L87 -> Staff
B82: Bookkeeping & Bill Pay | C82: Weekly | D82: =ROUND('Recurring Budgets'!F88*60,0)/1440 -> 0.0069444444 | E82: =ROUND('Recurring Budgets'!F88*IF(H82="CFO",Assumptions!$B$5,Assumptions!$B$4),0) -> 16 | F82: =ROUND('Recurring Budgets'!G88*60,0)/1440 -> 0 | G82: =ROUND('Recurring Budgets'!G88*Assumptions!$B$5,0) -> 0 | H82: ='Recurring Budgets'!L88 -> Staff
B83: Weekly Cash Review | C83: Weekly | D83: =ROUND('Recurring Budgets'!F89*60,0)/1440 -> 0.048611111 | E83: =ROUND('Recurring Budgets'!F89*IF(H83="CFO",Assumptions!$B$5,Assumptions!$B$4),0) -> 111 | F83: =ROUND('Recurring Budgets'!G89*60,0)/1440 -> 0 | G83: =ROUND('Recurring Budgets'!G89*Assumptions!$B$5,0) -> 0 | H83: ='Recurring Budgets'!L89 -> Staff
A84: Preferred Renovations LLC | B84: 1099 Quarterly Review (ongoing, after Oct 30) | C84: Quarterly | D84: =ROUND('Recurring Budgets'!F90*60,0)/1440 -> 0.083333333 | E84: =ROUND('Recurring Budgets'!F90*IF(H84="CFO",Assumptions!$B$5,Assumptions!$B$4),0) -> 190 | F84: =ROUND('Recurring Budgets'!G90*60,0)/1440 -> 0 | G84: =ROUND('Recurring Budgets'!G90*Assumptions!$B$5,0) -> 0 | H84: ='Recurring Budgets'!L90 -> Staff
B85: Month End Close | C85: Monthly | D85: =ROUND('Recurring Budgets'!F91*60,0)/1440 -> 0.076388889 | E85: =ROUND('Recurring Budgets'!F91*IF(H85="CFO",Assumptions!$B$5,Assumptions!$B$4),0) -> 174 | F85: =ROUND('Recurring Budgets'!G91*60,0)/1440 -> 0.041666667 | G85: =ROUND('Recurring Budgets'!G91*Assumptions!$B$5,0) -> 250 | H85: ='Recurring Budgets'!L91 -> Staff
A86: Prestige Arms Worldwide | B86: 1099 Quarterly Review (ongoing, after Oct 30) | C86: Quarterly | D86: =ROUND('Recurring Budgets'!F92*60,0)/1440 -> 0.015972222 | E86: =ROUND('Recurring Budgets'!F92*IF(H86="CFO",Assumptions!$B$5,Assumptions!$B$4),0) -> 36 | F86: =ROUND('Recurring Budgets'!G92*60,0)/1440 -> 0 | G86: =ROUND('Recurring Budgets'!G92*Assumptions!$B$5,0) -> 0 | H86: ='Recurring Budgets'!L92 -> Staff
B87: Year-End Tax Coordination | C87: Annual | D87: =ROUND('Recurring Budgets'!F93*60,0)/1440 -> 0.013888889 | E87: =ROUND('Recurring Budgets'!F93*IF(H87="CFO",Assumptions!$B$5,Assumptions!$B$4),0) -> 32 | F87: =ROUND('Recurring Budgets'!G93*60,0)/1440 -> 0 | G87: =ROUND('Recurring Budgets'!G93*Assumptions!$B$5,0) -> 0 | H87: ='Recurring Budgets'!L93 -> Staff
B88: Month End Close | C88: Monthly | D88: =ROUND('Recurring Budgets'!F94*60,0)/1440 -> 0.041666667 | E88: =ROUND('Recurring Budgets'!F94*IF(H88="CFO",Assumptions!$B$5,Assumptions!$B$4),0) -> 95 | F88: =ROUND('Recurring Budgets'!G94*60,0)/1440 -> 0.020833333 | G88: =ROUND('Recurring Budgets'!G94*Assumptions!$B$5,0) -> 125 | H88: ='Recurring Budgets'!L94 -> Staff
B89: Sales Tax Filing - Onyx Prepares the Returns for Client | C89: Monthly | D89: =ROUND('Recurring Budgets'!F95*60,0)/1440 -> 0.010416667 | E89: =ROUND('Recurring Budgets'!F95*IF(H89="CFO",Assumptions!$B$5,Assumptions!$B$4),0) -> 24 | F89: =ROUND('Recurring Budgets'!G95*60,0)/1440 -> 0 | G89: =ROUND('Recurring Budgets'!G95*Assumptions!$B$5,0) -> 0 | H89: ='Recurring Budgets'!L95 -> Staff
A90: Prime Solar USA LLC | B90: 1099 Quarterly Review (ongoing, after Oct 30) | C90: Quarterly | D90: =ROUND('Recurring Budgets'!F96*60,0)/1440 -> 0.03125 | E90: =ROUND('Recurring Budgets'!F96*IF(H90="CFO",Assumptions!$B$5,Assumptions!$B$4),0) -> 71 | F90: =ROUND('Recurring Budgets'!G96*60,0)/1440 -> 0 | G90: =ROUND('Recurring Budgets'!G96*Assumptions!$B$5,0) -> 0 | H90: ='Recurring Budgets'!L96 -> Staff
B91: Adjusting Journal Entry Request | C91: Annual | D91: =ROUND('Recurring Budgets'!F97*60,0)/1440 -> 0.03125 | E91: =ROUND('Recurring Budgets'!F97*IF(H91="CFO",Assumptions!$B$5,Assumptions!$B$4),0) -> 188 | F91: =ROUND('Recurring Budgets'!G97*60,0)/1440 -> 0 | G91: =ROUND('Recurring Budgets'!G97*Assumptions!$B$5,0) -> 0 | H91: ='Recurring Budgets'!L97 -> CFO
B92: Month End Close | C92: Monthly | D92: =ROUND('Recurring Budgets'!F98*60,0)/1440 -> 0.29166667 | E92: =ROUND('Recurring Budgets'!F98*IF(H92="CFO",Assumptions!$B$5,Assumptions!$B$4),0) -> 1750 | F92: =ROUND('Recurring Budgets'!G98*60,0)/1440 -> 0.041666667 | G92: =ROUND('Recurring Budgets'!G98*Assumptions!$B$5,0) -> 250 | H92: ='Recurring Budgets'!L98 -> CFO
A93: Rancho Industrial Park Inc | B93: 1099 Quarterly Review (ongoing, after Oct 30) | C93: Quarterly | D93: =ROUND('Recurring Budgets'!F99*60,0)/1440 -> 0.083333333 | E93: =ROUND('Recurring Budgets'!F99*IF(H93="CFO",Assumptions!$B$5,Assumptions!$B$4),0) -> 190 | F93: =ROUND('Recurring Budgets'!G99*60,0)/1440 -> 0 | G93: =ROUND('Recurring Budgets'!G99*Assumptions!$B$5,0) -> 0 | H93: ='Recurring Budgets'!L99 -> Staff
B94: Month End Close | C94: Monthly | D94: =ROUND('Recurring Budgets'!F100*60,0)/1440 -> 0.22916667 | E94: =ROUND('Recurring Budgets'!F100*IF(H94="CFO",Assumptions!$B$5,Assumptions!$B$4),0) -> 523 | F94: =ROUND('Recurring Budgets'!G100*60,0)/1440 -> 0.041666667 | G94: =ROUND('Recurring Budgets'!G100*Assumptions!$B$5,0) -> 250 | H94: ='Recurring Budgets'!L100 -> Staff
A95: SW Art Glass Inc | B95: Quarter End Close | C95: Quarterly | D95: =ROUND('Recurring Budgets'!F102*60,0)/1440 -> 0.041666667 | E95: =ROUND('Recurring Budgets'!F102*IF(H95="CFO",Assumptions!$B$5,Assumptions!$B$4),0) -> 250 | F95: =ROUND('Recurring Budgets'!G102*60,0)/1440 -> 0.0625 | G95: =ROUND('Recurring Budgets'!G102*Assumptions!$B$5,0) -> 375 | H95: ='Recurring Budgets'!L102 -> CFO
A96: Southwest Rents Inc | B96: 1099 Quarterly Review (ongoing, after Oct 30) | C96: Quarterly | D96: =ROUND('Recurring Budgets'!F103*60,0)/1440 -> 0.083333333 | E96: =ROUND('Recurring Budgets'!F103*IF(H96="CFO",Assumptions!$B$5,Assumptions!$B$4),0) -> 190 | F96: =ROUND('Recurring Budgets'!G103*60,0)/1440 -> 0 | G96: =ROUND('Recurring Budgets'!G103*Assumptions!$B$5,0) -> 0 | H96: ='Recurring Budgets'!L103 -> Staff
B97: Adjusting Journal Entry Request | C97: Annual | D97: =ROUND('Recurring Budgets'!F104*60,0)/1440 -> 0.1875 | E97: =ROUND('Recurring Budgets'!F104*IF(H97="CFO",Assumptions!$B$5,Assumptions!$B$4),0) -> 1125 | F97: =ROUND('Recurring Budgets'!G104*60,0)/1440 -> 0 | G97: =ROUND('Recurring Budgets'!G104*Assumptions!$B$5,0) -> 0 | H97: ='Recurring Budgets'!L104 -> CFO
B98: Month End Close | C98: Monthly | D98: =ROUND('Recurring Budgets'!F105*60,0)/1440 -> 0.041666667 | E98: =ROUND('Recurring Budgets'!F105*IF(H98="CFO",Assumptions!$B$5,Assumptions!$B$4),0) -> 95 | F98: =ROUND('Recurring Budgets'!G105*60,0)/1440 -> 0.020833333 | G98: =ROUND('Recurring Budgets'!G105*Assumptions!$B$5,0) -> 125 | H98: ='Recurring Budgets'!L105 -> Staff
A99: T5 Family Holdings LLC | B99: 1099 Quarterly Review (ongoing, after Oct 30) | C99: Quarterly | D99: =ROUND('Recurring Budgets'!F106*60,0)/1440 -> 0.015972222 | E99: =ROUND('Recurring Budgets'!F106*IF(H99="CFO",Assumptions!$B$5,Assumptions!$B$4),0) -> 36 | F99: =ROUND('Recurring Budgets'!G106*60,0)/1440 -> 0 | G99: =ROUND('Recurring Budgets'!G106*Assumptions!$B$5,0) -> 0 | H99: ='Recurring Budgets'!L106 -> Staff
B100: Month End Close | C100: Monthly | D100: =ROUND('Recurring Budgets'!F107*60,0)/1440 -> 0.065972222 | E100: =ROUND('Recurring Budgets'!F107*IF(H100="CFO",Assumptions!$B$5,Assumptions!$B$4),0) -> 150 | F100: =ROUND('Recurring Budgets'!G107*60,0)/1440 -> 0.020138889 | G100: =ROUND('Recurring Budgets'!G107*Assumptions!$B$5,0) -> 121 | H100: ='Recurring Budgets'!L107 -> Staff
A101: Tavasci Brothers Motorsports LLC | B101: 1099 Quarterly Review (ongoing, after Oct 30) | C101: Quarterly | D101: =ROUND('Recurring Budgets'!F108*60,0)/1440 -> 0.015972222 | E101: =ROUND('Recurring Budgets'!F108*IF(H101="CFO",Assumptions!$B$5,Assumptions!$B$4),0) -> 36 | F101: =ROUND('Recurring Budgets'!G108*60,0)/1440 -> 0 | G101: =ROUND('Recurring Budgets'!G108*Assumptions!$B$5,0) -> 0 | H101: ='Recurring Budgets'!L108 -> Staff
...

Sheet Read Me
A1: Karbon Budget Hours – Onyx Accounting Group
A2: Built Oct 1, 2026 from the 44 client billing sheets (history to Mar 2026) and the Harvest export (Dec 29, 2025 – Oct 2, 2026).
A3: Budgets are per WORK ITEM, not per person. CFO review is part of month-end but carried as its own number.
A5: HOW TO LOAD INTO KARBON – use the Karbon Entry tab (first tab). Everything else is supporting detail.
A6: 1. Recurring work: open each recurring series in Karbon and enter "Budget (Minutes)" from the Recurring Budgets tab. Future instances inherit it.
A7: 2. Open work already created: use the Open Items (Karbon) tab – one row per open item, matching Karbon Client Name and Work Title exactly.
A8: 3. If Karbon lets you split a budget by role/task, enter Work minutes and CFO Review minutes separately; otherwise enter Budget (Minutes) (the total).
A10: TABS
A11: Assumptions – billing rates, occurrences per month, 1099 sizes and factors, ad hoc reserve. Change a blue cell and every tab updates.
A12: Recurring Budgets – one row per client × recurring work series: budget per occurrence.
A13: Open Items (Karbon) – every open item from the Oct 1 Karbon list with its budget (pulled from the other tabs by formula).
A14: 1099 Oct 30 – the Q3 1099 review cycle, sized by client complexity and Q2 status.
... A39: • Where a client has no separate Payroll / Sales tax / Weekly item, that time is included in its Month End Close budget (the Basis column lists the parts).

Sheet Assumptions
A1: Assumptions (blue cells are inputs)
A3: Billing rates
A4: Staff work rate ($/hr) | B4: 95 | C4: Harvest: Staff Accountant standard rate (Christine/Valentina/Josephine $95).
A5: CFO rate ($/hr) | B5: 250 | C5: Harvest: CFO standard rate (Steven/Lisa Danforth $250).
A7: Occurrences per month
A8: Monthly | B8: 1
A9: Quarterly | B9: 0.33333333 | C9: One quarter-end per 3 months
A10: Weekly | B10: 4.3333333 | C10: 52 weeks ÷ 12
A11: Bi-weekly | B11: 2.1666667 | C11: 26 pay periods ÷ 12
A12: Daily | B12: 30.416667 | C12: Every day incl. weekends (Daily Chase Fraud Review)
A13: Annual | B13: 0.083333333
A14: 1099 | B14: 0.33333333 | C14: Quarterly 1099 review
A16: 1099 full review size (hrs, steps 1–7, Jan–Sep catch-up)
A17: Simple | B17: 0.75 | C17: Valentina's Q2 entries: 0.75h for steps 1–3 on small clients.
A18: Standard | B18: 1.5 | C18: Q2 entries 1.0–1.5h (vendor list prep).
A19: Complex | B19: 4 | C19: 2024 cycle for property/contractor clients ran ~2–6h/yr (billing sheets).
A20: Small property | B20: 2.5 | C20: Josephine: 2h quarterly was overstated by 30–60 min for the small property LLCs (1402 W Victory, 15650 Northsight, 3540 E Boot Track, 7327 Tierra Buena; 4530 W Flint added as same type). Ongoing = 1:15.
A22: 1099 Q2-status factor (Oct 30 cycle)
A23: Completed | B23: 0.5 | C23: Only the Q3 increment is needed.
A24: Partly done (3 of 7) | B24: 0.5 | C24: Josephine: heavy lifting (steps 1–3) was done in Q2 – Q3 only adds new vendors, same as Completed.
A25: Not started | B25: 1 | C25: Full Jan–Sep review.
A26: Not applicable | B26: 0
A27: Excluded (in-house) | B27: 0 | C27: IAG
A29: Ongoing quarterly 1099 (after Oct 30) | B29: 0.5 | C29: Share of a full review needed each later quarter (3 months of new vendors).
A31: Ad hoc reserve (capacity planning, hrs/month)
A32: CFO | B32: 25 | C32: Floor of CFO ad hoc time Feb–Sep 2026 (excl. IAG/ESI). Spikes come from known clients and are budgeted as Large items.
A33: Staff / controller | B33: 10 | C33: Typical staff ad hoc time Feb–Sep 2026; quiet months 3–7h.

Sheet 1099 Oct 30
A1: 1099 Quarterly Review – Oct 30, 2026 cycle
A2: Tier and Q2 status are inputs (blue). Budget = full review size for the tier × Q2-status factor (Assumptions tab).
A4: Client Name | B4: Complexity tier | C4: Q2 status (Karbon) | D4: Full review size (hrs) | E4: Q2-status factor | F4: Oct 30 budget (hrs) | G4: Oct 30 budget (Minutes) | H4: Ongoing quarterly (hrs) | I4: 1099 hrs logged Jul–Sep 2026 (info) | J4: Notes
A5: 1402 W Victory LLC | B5: Small property | C5: Not started | D5: =INDEX(Assumptions!$B$17:$B$20,MATCH(B5,Assumptions!$A$17:$A$20,0)) -> 2.5 | E5: =INDEX(Assumptions!$B$23:$B$27,MATCH(C5,Assumptions!$A$23:$A$27,0)) -> 1 | F5: =D5*E5 -> 2.5 | G5: =ROUND(F5*60,0) -> 150 | H5: =IF(OR(C5="Excluded (in-house)",C5="Not applicable"),0,D5*Assumptions!$B$29) -> 1.25 | I5: 0
A6: 15650 Northsight LLC | B6: Small property | C6: Not started | D6: =INDEX(Assumptions!$B$17:$B$20,MATCH(B6,Assumptions!$A$17:$A$20,0)) -> 2.5 | E6: =INDEX(Assumptions!$B$23:$B$27,MATCH(C6,Assumptions!$A$23:$A$27,0)) -> 1 | F6: =D6*E6 -> 2.5 | G6: =ROUND(F6*60,0) -> 150 | H6: =IF(OR(C6="Excluded (in-house)",C6="Not applicable"),0,D6*Assumptions!$B$29) -> 1.25 | I6: 0
A7: 3540 E Boot Track LLC | B7: Small property | C7: Not started | D7: =INDEX(Assumptions!$B$17:$B$20,MATCH(B7,Assumptions!$A$17:$A$20,0)) -> 2.5 | E7: =INDEX(Assumptions!$B$23:$B$27,MATCH(C7,Assumptions!$A$23:$A$27,0)) -> 1 | F7: =D7*E7 -> 2.5 | G7: =ROUND(F7*60,0) -> 150 | H7: =IF(OR(C7="Excluded (in-house)",C7="Not applicable"),0,D7*Assumptions!$B$29) -> 1.25 | I7: 0
A8: 4530 W Flint LLC | B8: Small property | C8: Not started | D8: =INDEX(Assumptions!$B$17:$B$20,MATCH(B8,Assumptions!$A$17:$A$20,0)) -> 2.5 | E8: =INDEX(Assumptions!$B$23:$B$27,MATCH(C8,Assumptions!$A$23:$A$27,0)) -> 1 | F8: =D8*E8 -> 2.5 | G8: =ROUND(F8*60,0) -> 150 | H8: =IF(OR(C8="Excluded (in-house)",C8="Not applicable"),0,D8*Assumptions!$B$29) -> 1.25 | I8: 0
A9: 7327 Tierra Buena LLC | B9: Standard | C9: Not started | D9: =INDEX(Assumptions!$B$17:$B$20,MATCH(B9,Assumptions!$A$17:$A$20,0)) -> 1.5 | E9: =INDEX(Assumptions!$B$23:$B$27,MATCH(C9,Assumptions!$A$23:$A$27,0)) -> 1 | F9: =D9*E9 -> 1.5 | G9: =ROUND(F9*60,0) -> 90 | H9: =IF(OR(C9="Excluded (in-house)",C9="Not applicable"),0,D9*Assumptions!$B$29) -> 0.75 | I9: 0
A10: 7730 Evans LLC | B10: Simple | C10: Partly done (3 of 7) | D10: =INDEX(Assumptions!$B$17:$B$20,MATCH(B10,Assumptions!$A$17:$A$20,0)) -> 0.75 | E10: =INDEX(Assumptions!$B$23:$B$27,MATCH(C10,Assumptions!$A$23:$A$27,0)) -> 0.5 | F10: =D10*E10 -> 0.375 | G10: =ROUND(F10*60,0) -> 23 | H10: =IF(OR(C10="Excluded (in-house)",C10="Not applicable"),0,D10*Assumptions!$B$29) -> 0.375 | I10: 0.75
A11: 909 MAIN LLC | B11: Simple | C11: Partly done (3 of 7) | D11: =INDEX(Assumptions!$B$17:$B$20,MATCH(B11,Assumptions!$A$17:$A$20,0)) -> 0.75 | E11: =INDEX(Assumptions!$B$23:$B$27,MATCH(C11,Assumptions!$A$23:$A$27,0)) -> 0.5 | F11: =D11*E11 -> 0.375 | G11: =ROUND(F11*60,0) -> 23 | H11: =IF(OR(C11="Excluded (in-house)",C11="Not applicable"),0,D11*Assumptions!$B$29) -> 0.375 | I11: 0.75
A12: Amerisource HR Consulting Group LLC | B12: Standard | C12: Completed | D12: =INDEX(Assumptions!$B$17:$B$20,MATCH(B12,Assumptions!$A$17:$A$20,0)) -> 1.5 | E12: =INDEX(Assumptions!$B$23:$B$27,MATCH(C12,Assumptions!$A$23:$A$27,0)) -> 0.5 | F12: =D12*E12 -> 0.75 | G12: =ROUND(F12*60,0) -> 45 | H12: =IF(OR(C12="Excluded (in-house)",C12="Not applicable"),0,D12*Assumptions!$B$29) -> 0.75 | I12: 4.5 | J12: Q2 completed Jul 21 (dropped off queue after 60 days).
A13: BSD Contracting LLC | B13: Complex | C13: Completed | D13: =INDEX(Assumptions!$B$17:$B$20,MATCH(B13,Assumptions!$A$17:$A$20,0)) -> 4 | E13: =INDEX(Assumptions!$B$23:$B$27,MATCH(C13,Assumptions!$A$23:$A$27,0)) -> 0.5 | F13: =D13*E13 -> 2 | G13: =ROUND(F13*60,0) -> 120 | H13: =IF(OR(C13="Excluded (in-house)",C13="Not applicable"),0,D13*Assumptions!$B$29) -> 2 | I13: 3.8
A14: BeckShar Development LLC | B14: Standard | C14: Completed | D14: =INDEX(Assumptions!$B$17:$B$20,MATCH(B14,Assumptions!$A$17:$A$20,0)) -> 1.5 | E14: =INDEX(Assumptions!$B$23:$B$27,MATCH(C14,Assumptions!$A$23:$A$27,0)) -> 0.5 | F14: =D14*E14 -> 0.75 | G14: =ROUND(F14*60,0) -> 45 | H14: =IF(OR(C14="Excluded (in-house)",C14="Not applicable"),0,D14*Assumptions!$B$29) -> 0.75 | I14: 0.9
A15: BeckShar Diamond Commercial LLC | B15: Standard | C15: Completed | D15: =INDEX(Assumptions!$B$17:$B$20,MATCH(B15,Assumptions!$A$17:$A$20,0)) -> 1.5 | E15: =INDEX(Assumptions!$B$23:$B$27,MATCH(C15,Assumptions!$A$23:$A$27,0)) -> 0.5 | F15: =D15*E15 -> 0.75 | G15: =ROUND(F15*60,0) -> 45 | H15: =IF(OR(C15="Excluded (in-house)",C15="Not applicable"),0,D15*Assumptions!$B$29) -> 0.75 | I15: 1.1
A16: BeckShar LLC | B16: Complex | C16: Completed | D16: =INDEX(Assumptions!$B$17:$B$20,MATCH(B16,Assumptions!$A$17:$A$20,0)) -> 4 | E16: =INDEX(Assumptions!$B$23:$B$27,MATCH(C16,Assumptions!$A$23:$A$27,0)) -> 0.5 | F16: =D16*E16 -> 2 | G16: =ROUND(F16*60,0) -> 120 | H16: =IF(OR(C16="Excluded (in-house)",C16="Not applicable"),0,D16*Assumptions!$B$29) -> 2 | I16: 5.35
A17: Building and Development Professionals LLC | B17: Complex | C17: Not started | D17: =INDEX(Assumptions!$B$17:$B$20,MATCH(B17,Assumptions!$A$17:$A$20,0)) -> 4 | E17: =INDEX(Assumptions!$B$23:$B$27,MATCH(C17,Assumptions!$A$23:$A$27,0)) -> 1 | F17: =D17*E17 -> 4 | G17: =ROUND(F17*60,0) -> 240 | H17: =IF(OR(C17="Excluded (in-house)",C17="Not applicable"),0,D17*Assumptions!$B$29) -> 2 | I17: 0
A18: Capital Financial LLC | B18: Standard | C18: Completed | D18: =INDEX(Assumptions!$B$17:$B$20,MATCH(B18,Assumptions!$A$17:$A$20,0)) -> 1.5 | E18: =INDEX(Assumptions!$B$23:$B$27,MATCH(C18,Assumptions!$A$23:$A$27,0)) -> 0.5 | F18: =D18*E18 -> 0.75 | G18: =ROUND(F18*60,0) -> 45 | H18: =IF(OR(C18="Excluded (in-house)",C18="Not applicable"),0,D18*Assumptions!$B$29) -> 0.75 | I18: 3 | J18: Q2 showed 8 of 8 but marked Cancelled – treated as completed (confirm).
A19: Catalpa Industrial Park Inc | B19: Complex | C19: Not started | D19: =INDEX(Assumptions!$B$17:$B$20,MATCH(B19,Assumptions!$A$17:$A$20,0)) -> 4 | E19: =INDEX(Assumptions!$B$23:$B$27,MATCH(C19,Assumptions!$A$23:$A$27,0)) -> 1 | F19: =D19*E19 -> 4 | G19: =ROUND(F19*60,0) -> 240 | H19: =IF(OR(C19="Excluded (in-house)",C19="Not applicable"),0,D19*Assumptions!$B$29) -> 2 | I19: 0
A20: Desert Quail Creative Classroom LLC | B20: Simple | C20: Not started | D20: =INDEX(Assumptions!$B$17:$B$20,MATCH(B20,Assumptions!$A$17:$A$20,0)) -> 0.75 | E20: =INDEX(Assumptions!$B$23:$B$27,MATCH(C20,Assumptions!$A$23:$A$27,0)) -> 1 | F20: =D20*E20 -> 0.75 | G20: =ROUND(F20*60,0) -> 45 | H20: =IF(OR(C20="Excluded (in-house)",C20="Not applicable"),0,D20*Assumptions!$B$29) -> 0.375 | I20: 0
A21: Educational Services Holdings LLC | B21: Standard | C21: Partly done (3 of 7) | D21: =INDEX(Assumptions!$B$17:$B$20,MATCH(B21,Assumptions!$A$17:$A$20,0)) -> 1.5 | E21: =INDEX(Assumptions!$B$23:$B$27,MATCH(C21,Assumptions!$A$23:$A$27,0)) -> 0.5 | F21: =D21*E21 -> 0.75 | G21: =ROUND(F21*60,0) -> 45 | H21: =IF(OR(C21="Excluded (in-house)",C21="Not applicable"),0,D21*Assumptions!$B$29) -> 0.75 | I21: 1.25
A22: Eight Eleven LLC | B22: Complex | C22: Partly done (3 of 7) | D22: =INDEX(Assumptions!$B$17:$B$20,MATCH(B22,Assumptions!$A$17:$A$20,0)) -> 4 | E22: =INDEX(Assumptions!$B$23:$B$27,MATCH(C22,Assumptions!$A$23:$A$27,0)) -> 0.5 | F22: =D22*E22 -> 2 | G22: =ROUND(F22*60,0) -> 120 | H22: =IF(OR(C22="Excluded (in-house)",C22="Not applicable"),0,D22*Assumptions!$B$29) -> 2 | I22: 7 | J22: Q2 waiting for client (steps 4–6) – may carry over.
A23: FiveOliver LLC | B23: Complex | C23: Not started | D23: =INDEX(Assumptions!$B$17:$B$20,MATCH(B23,Assumptions!$A$17:$A$20,0)) -> 4 | E23: =INDEX(Assumptions!$B$23:$B$27,MATCH(C23,Assumptions!$A$23:$A$27,0)) -> 1 | F23: =D23*E23 -> 4 | G23: =ROUND(F23*60,0) -> 240 | H23: =IF(OR(C23="Excluded (in-house)",C23="Not applicable"),0,D23*Assumptions!$B$29) -> 2 | I23: 0
A24: GAV Enterprises Inc | B24: Standard | C24: Not started | D24: =INDEX(Assumptions!$B$17:$B$20,MATCH(B24,Assumptions!$A$17:$A$20,0)) -> 1.5 | E24: =INDEX(Assumptions!$B$23:$B$27,MATCH(C24,Assumptions!$A$23:$A$27,0)) -> 1 | F24: =D24*E24 -> 1.5 | G24: =ROUND(F24*60,0) -> 90 | H24: =IF(OR(C24="Excluded (in-house)",C24="Not applicable"),0,D24*Assumptions!$B$29) -> 0.75 | I24: 1 | J24: Karbon 0 of 7, but 1.0h logged Sept 25.
A25: International Alliance Group LLC | B25: Standard | C25: Excluded (in-house) | D25: =INDEX(Assumptions!$B$17:$B$20,MATCH(B25,Assumptions!$A$17:$A$20,0)) -> 1.5 | E25: =INDEX(Assumptions!$B$23:$B$27,MATCH(C25,Assumptions!$A$23:$A$27,0)) -> 0 | F25: =D25*E25 -> 0 | G25: =ROUND(F25*60,0) -> 0 | H25: =IF(OR(C25="Excluded (in-house)",C25="Not applicable"),0,D25*Assumptions!$B$29) -> 0 | I25: 10 | J25: In-house – excluded.
A26: KAMM ADGT LLC | B26: Simple | C26: Completed | D26: =INDEX(Assumptions!$B$17:$B$20,MATCH(B26,Assumptions!$A$17:$A$20,0)) -> 0.75 | E26: =INDEX(Assumptions!$B$23:$B$27,MATCH(C26,Assumptions!$A$23:$A$27,0)) -> 0.5 | F26: =D26*E26 -> 0.375 | G26: =ROUND(F26*60,0) -> 23 | H26: =IF(OR(C26="Excluded (in-house)",C26="Not applicable"),0,D26*Assumptions!$B$29) -> 0.375 | I26: 1
A27: Little Moo's LLC | B27: Simple | C27: Partly done (3 of 7) | D27: =INDEX(Assumptions!$B$17:$B$20,MATCH(B27,Assumptions!$A$17:$A$20,0)) -> 0.75 | E27: =INDEX(Assumptions!$B$23:$B$27,MATCH(C27,Assumptions!$A$23:$A$27,0)) -> 0.5 | F27: =D27*E27 -> 0.375 | G27: =ROUND(F27*60,0) -> 23 | H27: =IF(OR(C27="Excluded (in-house)",C27="Not applicable"),0,D27*Assumptions!$B$29) -> 0.375 | I27: 0.75
A28: Midwest Contracting Inc | B28: Complex | C28: Partly done (3 of 7) | D28: =INDEX(Assumptions!$B$17:$B$20,MATCH(B28,Assumptions!$A$17:$A$20,0)) -> 4 | E28: =INDEX(Assumptions!$B$23:$B$27,MATCH(C28,Assumptions!$A$23:$A$27,0)) -> 0.5 | F28: =D28*E28 -> 2 | G28: =ROUND(F28*60,0) -> 120 | H28: =IF(OR(C28="Excluded (in-house)",C28="Not applicable"),0,D28*Assumptions!$B$29) -> 2 | I28: 8 | J28: Q2 waiting for client (steps 4–6) – may carry over.
A29: Mohrschladt Capital LP | B29: Standard | C29: Not started | D29: =INDEX(Assumptions!$B$17:$B$20,MATCH(B29,Assumptions!$A$17:$A$20,0)) -> 1.5 | E29: =INDEX(Assumptions!$B$23:$B$27,MATCH(C29,Assumptions!$A$23:$A$27,0)) -> 1 | F29: =D29*E29 -> 1.5 | G29: =ROUND(F29*60,0) -> 90 | H29: =IF(OR(C29="Excluded (in-house)",C29="Not applicable"),0,D29*Assumptions!$B$29) -> 0.75 | I29: 0
A30: Mohrschladt Howarth Associates Inc | B30: Complex | C30: Not started | D30: =INDEX(Assumptions!$B$17:$B$20,MATCH(B30,Assumptions!$A$17:$A$20,0)) -> 4 | E30: =INDEX(Assumptions!$B$23:$B$27,MATCH(C30,Assumptions!$A$23:$A$27,0)) -> 1 | F30: =D30*E30 -> 4 | G30: =ROUND(F30*60,0) -> 240 | H30: =IF(OR(C30="Excluded (in-house)",C30="Not applicable"),0,D30*Assumptions!$B$29) -> 2 | I30: 0
A31: Mountain Trade Supply Inc | B31: Complex | C31: Not started | D31: =INDEX(Assumptions!$B$17:$B$20,MATCH(B31,Assumptions!$A$17:$A$20,0)) -> 4 | E31: =INDEX(Assumptions!$B$23:$B$27,MATCH(C31,Assumptions!$A$23:$A$27,0)) -> 1 | F31: =D31*E31 -> 4 | G31: =ROUND(F31*60,0) -> 240 | H31: =IF(OR(C31="Excluded (in-house)",C31="Not applicable"),0,D31*Assumptions!$B$29) -> 2 | I31: 0 | J31: No Q2 item – new for Q3.
A32: Newport Classic Cars LLC | B32: Standard | C32: Not started | D32: =INDEX(Assumptions!$B$17:$B$20,MATCH(B32,Assumptions!$A$17:$A$20,0)) -> 1.5 | E32: =INDEX(Assumptions!$B$23:$B$27,MATCH(C32,Assumptions!$A$23:$A$27,0)) -> 1 | F32: =D32*E32 -> 1.5 | G32: =ROUND(F32*60,0) -> 90 | H32: =IF(OR(C32="Excluded (in-house)",C32="Not applicable"),0,D32*Assumptions!$B$29) -> 0.75 | I32: 0
A33: Obsidian Real Estate LLC | B33: Complex | C33: Not started | D33: =INDEX(Assumptions!$B$17:$B$20,MATCH(B33,Assumptions!$A$17:$A$20,0)) -> 4 | E33: =INDEX(Assumptions!$B$23:$B$27,MATCH(C33,Assumptions!$A$23:$A$27,0)) -> 1 | F33: =D33*E33 -> 4 | G33: =ROUND(F33*60,0) -> 240 | H33: =IF(OR(C33="Excluded (in-house)",C33="Not applicable"),0,D33*Assumptions!$B$29) -> 2 | I33: 0
A34: Preferred Renovations LLC | B34: Complex | C34: Completed | D34: =INDEX(Assumptions!$B$17:$B$20,MATCH(B34,Assumptions!$A$17:$A$20,0)) -> 4 | E34: =INDEX(Assumptions!$B$23:$B$27,MATCH(C34,Assumptions!$A$23:$A$27,0)) -> 0.5 | F34: =D34*E34 -> 2 | G34: =ROUND(F34*60,0) -> 120 | H34: =IF(OR(C34="Excluded (in-house)",C34="Not applicable"),0,D34*Assumptions!$B$29) -> 2 | I34: 0 | J34: Q2 completed Jul 22 (dropped off queue after 60 days).
A35: Prestige Arms Worldwide | B35: Simple | C35: Not started | D35: =INDEX(Assumptions!$B$17:$B$20,MATCH(B35,Assumptions!$A$17:$A$20,0)) -> 0.75 | E35: =INDEX(Assumptions!$B$23:$B$27,MATCH(C35,Assumptions!$A$23:$A$27,0)) -> 1 | F35: =D35*E35 -> 0.75 | G35: =ROUND(F35*60,0) -> 45 | H35: =IF(OR(C35="Excluded (in-house)",C35="Not applicable"),0,D35*Assumptions!$B$29) -> 0.375 | I35: 0
A36: Prime Solar USA LLC | B36: Standard | C36: Not started | D36: =INDEX(Assumptions!$B$17:$B$20,MATCH(B36,Assumptions!$A$17:$A$20,0)) -> 1.5 | E36: =INDEX(Assumptions!$B$23:$B$27,MATCH(C36,Assumptions!$A$23:$A$27,0)) -> 1 | F36: =D36*E36 -> 1.5 | G36: =ROUND(F36*60,0) -> 90 | H36: =IF(OR(C36="Excluded (in-house)",C36="Not applicable"),0,D36*Assumptions!$B$29) -> 0.75 | I36: 2.5 | J36: Karbon 0 of 7, but 2.5h logged Aug 27–28 (vendor list prepared).
A37: Rancho Industrial Park Inc | B37: Complex | C37: Not started | D37: =INDEX(Assumptions!$B$17:$B$20,MATCH(B37,Assumptions!$A$17:$A$20,0)) -> 4 | E37: =INDEX(Assumptions!$B$23:$B$27,MATCH(C37,Assumptions!$A$23:$A$27,0)) -> 1 | F37: =D37*E37 -> 4 | G37: =ROUND(F37*60,0) -> 240 | H37: =IF(OR(C37="Excluded (in-house)",C37="Not applicable"),0,D37*Assumptions!$B$29) -> 2 | I37: 0
A38: SW Art Glass Inc | B38: Simple | C38: Not applicable | D38: =INDEX(Assumptions!$B$17:$B$20,MATCH(B38,Assumptions!$A$17:$A$20,0)) -> 0.75 | E38: =INDEX(Assumptions!$B$23:$B$27,MATCH(C38,Assumptions!$A$23:$A$27,0)) -> 0 | F38: =D38*E38 -> 0 | G38: =ROUND(F38*60,0) -> 0 | H38: =IF(OR(C38="Excluded (in-house)",C38="Not applicable"),0,D38*Assumptions!$B$29) -> 0 | I38: 0
A39: Southwest Rents Inc | B39: Complex | C39: Not started | D39: =INDEX(Assumptions!$B$17:$B$20,MATCH(B39,Assumptions!$A$17:$A$20,0)) -> 4 | E39: =INDEX(Assumptions!$B$23:$B$27,MATCH(C39,Assumptions!$A$23:$A$27,0)) -> 1 | F39: =D39*E39 -> 4 | G39: =ROUND(F39*60,0) -> 240 | H39: =IF(OR(C39="Excluded (in-house)",C39="Not applicable"),0,D39*Assumptions!$B$29) -> 2 | I39: 0
A40: T5 Family Holdings LLC | B40: Simple | C40: Partly done (3 of 7) | D40: =INDEX(Assumptions!$B$17:$B$20,MATCH(B40,Assumptions!$A$17:$A$20,0)) -> 0.75 | E40: =INDEX(Assumptions!$B$23:$B$27,MATCH(C40,Assumptions!$A$23:$A$27,0)) -> 0.5 | F40: =D40*E40 -> 0.375 | G40: =ROUND(F40*60,0) -> 23 | H40: =IF(OR(C40="Excluded (in-house)",C40="Not applicable"),0,D40*Assumptions!$B$29) -> 0.375 | I40: 0.75
A41: Tavasci Brothers Motorsports LLC | B41: Simple | C41: Partly done (3 of 7) | D41: =INDEX(Assumptions!$B$17:$B$20,MATCH(B41,Assumptions!$A$17:$A$20,0)) -> 0.75 | E41: =INDEX(Assumptions!$B$23:$B$27,MATCH(C41,Assumptions!$A$23:$A$27,0)) -> 0.5 | F41: =D41*E41 -> 0.375 | G41: =ROUND(F41*60,0) -> 23 | H41: =IF(OR(C41="Excluded (in-house)",C41="Not applicable"),0,D41*Assumptions!$B$29) -> 0.375 | I41: 0.75
A42: VV1012 LLC | B42: Standard | C42: Partly done (3 of 7) | D42: =INDEX(Assumptions!$B$17:$B$20,MATCH(B42,Assumptions!$A$17:$A$20,0)) -> 1.5 | E42: =INDEX(Assumptions!$B$23:$B$27,MATCH(C42,Assumptions!$A$23:$A$27,0)) -> 0.5 | F42: =D42*E42 -> 0.75 | G42: =ROUND(F42*60,0) -> 45 | H42: =IF(OR(C42="Excluded (in-house)",C42="Not applicable"),0,D42*Assumptions!$B$29) -> 0.75 | I42: 1.5
A43: VVI 1017 LLC | B43: Standard | C43: Partly done (3 of 7) | D43: =INDEX(Assumptions!$B$17:$B$20,MATCH(B43,Assumptions!$A$17:$A$20,0)) -> 1.5 | E43: =INDEX(Assumptions!$B$23:$B$27,MATCH(C43,Assumptions!$A$23:$A$27,0)) -> 0.5 | F43: =D43*E43 -> 0.75 | G43: =ROUND(F43*60,0) -> 45 | H43: =IF(OR(C43="Excluded (in-house)",C43="Not applicable"),0,D43*Assumptions!$B$29) -> 0.75 | I43: 1.5
A44: VVNS LLC | B44: Standard | C44: Partly done (3 of 7) | D44: =INDEX(Assumptions!$B$17:$B$20,MATCH(B44,Assumptions!$A$17:$A$20,0)) -> 1.5 | E44: =INDEX(Assumptions!$B$23:$B$27,MATCH(C44,Assumptions!$A$23:$A$27,0)) -> 0.5 | F44: =D44*E44 -> 0.75 | G44: =ROUND(F44*60,0) -> 45 | H44: =IF(OR(C44="Excluded (in-house)",C44="Not applicable"),0,D44*Assumptions!$B$29) -> 0.75 | I44: 0.75
A45: Young Wealth Management PLLC | B45: Standard | C45: Partly done (3 of 7) | D45: =INDEX(Assumptions!$B$17:$B$20,MATCH(B45,Assumptions!$A$17:$A$20,0)) -> 1.5 | E45: =INDEX(Assumptions!$B$23:$B$27,MATCH(C45,Assumptions!$A$23:$A$27,0)) -> 0.5 | F45: =D45*E45 -> 0.75 | G45: =ROUND(F45*60,0) -> 45 | H45: =IF(OR(C45="Excluded (in-house)",C45="Not applicable"),0,D45*Assumptions!$B$29) -> 0.75 | I45: 3
A46: TOTAL | F46: =SUM(F5:F45) -> 70 | G46: =SUM(G5:G45) -> 4203 | H46: =SUM(H5:H45) -> 44.5 | I46: =SUM(I5:I45) -> 59.9
A48: Not included: the January filing step (finalize, e-file, send forms) – historically ~0.2–0.5h per client; budget it as its own item in January.

Sheet Recurring Budgets
A1: Lookup key | B1: Client Name | C1: Work Type | D1: Work Item (recurring series) | E1: Repeats | F1: Work (hrs / occurrence) | G1: CFO Review (hrs / occurrence) | H1: Total (hrs / occurrence) | I1: Budget (Minutes) | J1: Work (Minutes) | K1: CFO Review (Minutes) | L1: Work rate | M1: Budget (USD) | N1: Monthly equivalent – Work (hrs) | O1: Monthly equivalent – CFO Review (hrs) | P1: Confidence | Q1: Basis / notes | R1: Baseline months used
A2: 1402 W Victory LLC|1099|1099 Quarterly Review|1099 | B2: 1402 W Victory LLC | C2: 1099 | D2: 1099 Quarterly Review | E2: 1099 | F2: =IFERROR(INDEX('1099 Oct 30'!$H$5:$H$45,MATCH(B2,'1099 Oct 30'!$A$5:$A$45,0)),0) -> 1.25 | G2: 0 | H2: =F2+G2 -> 1.25 | I2: =ROUND(H2*60,0) -> 75 | J2: =ROUND(F2*60,0) -> 75 | K2: =ROUND(G2*60,0) -> 0 | L2: Staff | M2: =F2*IF(L2="CFO",Assumptions!$B$5,Assumptions!$B$4)+G2*Assumptions!$B$5 -> 118.75 | N2: =F2*INDEX(Assumptions!$B$8:$B$14,MATCH(E2,Assumptions!$A$8:$A$14,0)) -> 0.41666667 | O2: =G2*INDEX(Assumptions!$B$8:$B$14,MATCH(E2,Assumptions!$A$8:$A$14,0)) -> 0 | P2: Estimate | Q2: 1099 tier Small property: ongoing quarterly review (half a full review). See 1099 tab for the Oct 30 cycle. | R2: Settled from 2026-06 (2026-06 – 2026-09)
A3: 1402 W Victory LLC|Monthly Financials|Month End Close|Monthly | B3: 1402 W Victory LLC | C3: Monthly Financials | D3: Month End Close | E3: Monthly | F3: 0.5 | G3: 0.7 | H3: =F3+G3 -> 1.2 | I3: =ROUND(H3*60,0) -> 72 | J3: =ROUND(F3*60,0) -> 30 | K3: =ROUND(G3*60,0) -> 42 | L3: Staff | M3: =F3*IF(L3="CFO",Assumptions!$B$5,Assumptions!$B$4)+G3*Assumptions!$B$5 -> 222.5 | N3: =F3*INDEX(Assumptions!$B$8:$B$14,MATCH(E3,Assumptions!$A$8:$A$14,0)) -> 0.5 | O3: =G3*INDEX(Assumptions!$B$8:$B$14,MATCH(E3,Assumptions!$A$8:$A$14,0)) -> 0.7 | P3: High | Q3: Includes Month-end 0.7. Review = median of 7 closes reviewed in Harvest (0.70h). | R3: Settled from 2026-06 (2026-06 – 2026-09)
A4: 15650 Northsight LLC|1099|1099 Quarterly Review|1099 | B4: 15650 Northsight LLC | C4: 1099 | D4: 1099 Quarterly Review | E4: 1099 | F4: =IFERROR(INDEX('1099 Oct 30'!$H$5:$H$45,MATCH(B4,'1099 Oct 30'!$A$5:$A$45,0)),0) -> 1.25 | G4: 0 | H4: =F4+G4 -> 1.25 | I4: =ROUND(H4*60,0) -> 75 | J4: =ROUND(F4*60,0) -> 75 | K4: =ROUND(G4*60,0) -> 0 | L4: Staff | M4: =F4*IF(L4="CFO",Assumptions!$B$5,Assumptions!$B$4)+G4*Assumptions!$B$5 -> 118.75 | N4: =F4*INDEX(Assumptions!$B$8:$B$14,MATCH(E4,Assumptions!$A$8:$A$14,0)) -> 0.41666667 | O4: =G4*INDEX(Assumptions!$B$8:$B$14,MATCH(E4,Assumptions!$A$8:$A$14,0)) -> 0 | P4: Estimate | Q4: 1099 tier Small property: ongoing quarterly review (half a full review). See 1099 tab for the Oct 30 cycle. | R4: Quarterly client – average of Apr–Sep 2026 (2026-04 – 2026-09)
A5: 15650 Northsight LLC|Accounting|Quarter End Close|Quarterly | B5: 15650 Northsight LLC | C5: Accounting | D5: Quarter End Close | E5: Quarterly | F5: 0.5 | G5: 1.25 | H5: =F5+G5 -> 1.75 | I5: =ROUND(H5*60,0) -> 105 | J5: =ROUND(F5*60,0) -> 30 | K5: =ROUND(G5*60,0) -> 75 | L5: Staff | M5: =F5*IF(L5="CFO",Assumptions!$B$5,Assumptions!$B$4)+G5*Assumptions!$B$5 -> 360 | N5: =F5*INDEX(Assumptions!$B$8:$B$14,MATCH(E5,Assumptions!$A$8:$A$14,0)) -> 0.16666667 | O5: =G5*INDEX(Assumptions!$B$8:$B$14,MATCH(E5,Assumptions!$A$8:$A$14,0)) -> 0.41666667 | P5: High | Q5: Includes Month-end 0.5. Review = 1.25h as logged (only 2 reviewed close(s) in Harvest – check). | R5: Quarterly client – average of Apr–Sep 2026 (2026-04 – 2026-09)
A6: 15650 Northsight LLC|Sales tax|Quarterly Sales Tax Filing - Onyx Prepares the Returns for Client|Quarterly | B6: 15650 Northsight LLC | C6: Sales tax | D6: Quarterly Sales Tax Filing - Onyx Prepares the Returns for Client | E6: Quarterly | F6: 0.5 | G6: 0 | H6: =F6+G6 -> 0.5 | I6: =ROUND(H6*60,0) -> 30 | J6: =ROUND(F6*60,0) -> 30 | K6: =ROUND(G6*60,0) -> 0 | L6: Staff | M6: =F6*IF(L6="CFO",Assumptions!$B$5,Assumptions!$B$4)+G6*Assumptions!$B$5 -> 47.5 | N6: =F6*INDEX(Assumptions!$B$8:$B$14,MATCH(E6,Assumptions!$A$8:$A$14,0)) -> 0.16666667 | O6: =G6*INDEX(Assumptions!$B$8:$B$14,MATCH(E6,Assumptions!$A$8:$A$14,0)) -> 0 | P6: Estimate | Q6: Sales tax time × 3 (quarterly filing). Little logged time – minimum applied. | R6: Quarterly client – average of Apr–Sep 2026 (2026-04 – 2026-09)
A7: 1915 NORTH 16TH STREET LLC|Default|Year-End Tax Coordination|Annual | B7: 1915 NORTH 16TH STREET LLC | C7: Default | D7: Year-End Tax Coordination | E7: Annual | F7: 1 | G7: 0 | H7: =F7+G7 -> 1 | I7: =ROUND(H7*60,0) -> 60 | J7: =ROUND(F7*60,0) -> 60 | K7: =ROUND(G7*60,0) -> 0 | L7: Staff | M7: =F7*IF(L7="CFO",Assumptions!$B$5,Assumptions!$B$4)+G7*Assumptions!$B$5 -> 95 | N7: =F7*INDEX(Assumptions!$B$8:$B$14,MATCH(E7,Assumptions!$A$8:$A$14,0)) -> 0.083333333 | O7: =G7*INDEX(Assumptions!$B$8:$B$14,MATCH(E7,Assumptions!$A$8:$A$14,0)) -> 0 | P7: Estimate | Q7: No year-end hours logged in the last 12 months – placeholder 1.0h. | R7: No recent recurring hours
A8: 3540 E Boot Track LLC|1099|1099 Quarterly Review|1099 | B8: 3540 E Boot Track LLC | C8: 1099 | D8: 1099 Quarterly Review | E8: 1099 | F8: =IFERROR(INDEX('1099 Oct 30'!$H$5:$H$45,MATCH(B8,'1099 Oct 30'!$A$5:$A$45,0)),0) -> 1.25 | G8: 0 | H8: =F8+G8 -> 1.25 | I8: =ROUND(H8*60,0) -> 75 | J8: =ROUND(F8*60,0) -> 75 | K8: =ROUND(G8*60,0) -> 0 | L8: Staff | M8: =F8*IF(L8="CFO",Assumptions!$B$5,Assumptions!$B$4)+G8*Assumptions!$B$5 -> 118.75 | N8: =F8*INDEX(Assumptions!$B$8:$B$14,MATCH(E8,Assumptions!$A$8:$A$14,0)) -> 0.41666667 | O8: =G8*INDEX(Assumptions!$B$8:$B$14,MATCH(E8,Assumptions!$A$8:$A$14,0)) -> 0 | P8: Estimate | Q8: 1099 tier Small property: ongoing quarterly review (half a full review). See 1099 tab for the Oct 30 cycle. | R8: Settled from 2026-07 (2026-07 – 2026-09)
A9: 3540 E Boot Track LLC|Monthly Financials|Month End Close|Monthly | B9: 3540 E Boot Track LLC | C9: Monthly Financials | D9: Month End Close | E9: Monthly | F9: 2.25 | G9: 0.7 | H9: =F9+G9 -> 2.95 | I9: =ROUND(H9*60,0) -> 177 | J9: =ROUND(F9*60,0) -> 135 | K9: =ROUND(G9*60,0) -> 42 | L9: Staff | M9: =F9*IF(L9="CFO",Assumptions!$B$5,Assumptions!$B$4)+G9*Assumptions!$B$5 -> 388.75 | N9: =F9*INDEX(Assumptions!$B$8:$B$14,MATCH(E9,Assumptions!$A$8:$A$14,0)) -> 2.25 | O9: =G9*INDEX(Assumptions!$B$8:$B$14,MATCH(E9,Assumptions!$A$8:$A$14,0)) -> 0.7 | P9: High | Q9: Includes Month-end 2.4. Review = median of 7 closes reviewed in Harvest (0.70h). | R9: Settled from 2026-07 (2026-07 – 2026-09)
A10: 4530 W Flint LLC|1099|1099 Quarterly Review|1099 | B10: 4530 W Flint LLC | C10: 1099 | D10: 1099 Quarterly Review | E10: 1099 | F10: =IFERROR(INDEX('1099 Oct 30'!$H$5:$H$45,MATCH(B10,'1099 Oct 30'!$A$5:$A$45,0)),0) -> 1.25 | G10: 0 | H10: =F10+G10 -> 1.25 | I10: =ROUND(H10*60,0) -> 75 | J10: =ROUND(F10*60,0) -> 75 | K10: =ROUND(G10*60,0) -> 0 | L10: Staff | M10: =F10*IF(L10="CFO",Assumptions!$B$5,Assumptions!$B$4)+G10*Assumptions!$B$5 -> 118.75 | N10: =F10*INDEX(Assumptions!$B$8:$B$14,MATCH(E10,Assumptions!$A$8:$A$14,0)) -> 0.41666667 | O10: =G10*INDEX(Assumptions!$B$8:$B$14,MATCH(E10,Assumptions!$A$8:$A$14,0)) -> 0 | P10: Estimate | Q10: 1099 tier Small property: ongoing quarterly review (half a full review). See 1099 tab for the Oct 30 cycle. | R10: Settled from 2026-02 (2026-02 – 2026-09)
A11: 4530 W Flint LLC|Monthly Financials|Month End Close|Monthly | B11: 4530 W Flint LLC | C11: Monthly Financials | D11: Month End Close | E11: Monthly | F11: 0.8333 | G11: 0.7 | H11: =F11+G11 -> 1.5333 | I11: =ROUND(H11*60,0) -> 92 | J11: =ROUND(F11*60,0) -> 50 | K11: =ROUND(G11*60,0) -> 42 | L11: Staff | M11: =F11*IF(L11="CFO",Assumptions!$B$5,Assumptions!$B$4)+G11*Assumptions!$B$5 -> 254.1635 | N11: =F11*INDEX(Assumptions!$B$8:$B$14,MATCH(E11,Assumptions!$A$8:$A$14,0)) -> 0.8333 | O11: =G11*INDEX(Assumptions!$B$8:$B$14,MATCH(E11,Assumptions!$A$8:$A$14,0)) -> 0.7 | P11: High | Q11: Includes Month-end 0.8. Review = median of 7 closes reviewed in Harvest (0.70h). | R11: Settled from 2026-02 (2026-02 – 2026-09)
A12: 7327 Tierra Buena LLC|1099|1099 Quarterly Review|1099 | B12: 7327 Tierra Buena LLC | C12: 1099 | D12: 1099 Quarterly Review | E12: 1099 | F12: =IFERROR(INDEX('1099 Oct 30'!$H$5:$H$45,MATCH(B12,'1099 Oct 30'!$A$5:$A$45,0)),0) -> 0.75 | G12: 0 | H12: =F12+G12 -> 0.75 | I12: =ROUND(H12*60,0) -> 45 | J12: =ROUND(F12*60,0) -> 45 | K12: =ROUND(G12*60,0) -> 0 | L12: Staff | M12: =F12*IF(L12="CFO",Assumptions!$B$5,Assumptions!$B$4)+G12*Assumptions!$B$5 -> 71.25 | N12: =F12*INDEX(Assumptions!$B$8:$B$14,MATCH(E12,Assumptions!$A$8:$A$14,0)) -> 0.25 | O12: =G12*INDEX(Assumptions!$B$8:$B$14,MATCH(E12,Assumptions!$A$8:$A$14,0)) -> 0 | P12: Estimate | Q12: 1099 tier Standard: ongoing quarterly review (half a full review). See 1099 tab for the Oct 30 cycle. | R12: Settled from 2026-02 (2026-02 – 2026-09)
A13: 7327 Tierra Buena LLC|Monthly Financials|Month End Close|Monthly | B13: 7327 Tierra Buena LLC | C13: Monthly Financials | D13: Month End Close | E13: Monthly | F13: 1.1667 | G13: 0.7 | H13: =F13+G13 -> 1.8667 | I13: =ROUND(H13*60,0) -> 112 | J13: =ROUND(F13*60,0) -> 70 | K13: =ROUND(G13*60,0) -> 42 | L13: Staff | M13: =F13*IF(L13="CFO",Assumptions!$B$5,Assumptions!$B$4)+G13*Assumptions!$B$5 -> 285.8365 | N13: =F13*INDEX(Assumptions!$B$8:$B$14,MATCH(E13,Assumptions!$A$8:$A$14,0)) -> 1.1667 | O13: =G13*INDEX(Assumptions!$B$8:$B$14,MATCH(E13,Assumptions!$A$8:$A$14,0)) -> 0.7 | P13: High | Q13: Includes Month-end 1.3. Review = median of 7 closes reviewed in Harvest (0.70h). | R13: Settled from 2026-02 (2026-02 – 2026-09)
A14: 7730 Evans LLC|1099|1099 Quarterly Review|1099 | B14: 7730 Evans LLC | C14: 1099 | D14: 1099 Quarterly Review | E14: 1099 | F14: =IFERROR(INDEX('1099 Oct 30'!$H$5:$H$45,MATCH(B14,'1099 Oct 30'!$A$5:$A$45,0)),0) -> 0.375 | G14: 0 | H14: =F14+G14 -> 0.375 | I14: =ROUND(H14*60,0) -> 23 | J14: =ROUND(F14*60,0) -> 23 | K14: =ROUND(G14*60,0) -> 0 | L14: Staff | M14: =F14*IF(L14="CFO",Assumptions!$B$5,Assumptions!$B$4)+G14*Assumptions!$B$5 -> 35.625 | N14: =F14*INDEX(Assumptions!$B$8:$B$14,MATCH(E14,Assumptions!$A$8:$A$14,0)) -> 0.125 | O14: =G14*INDEX(Assumptions!$B$8:$B$14,MATCH(E14,Assumptions!$A$8:$A$14,0)) -> 0 | P14: Estimate | Q14: 1099 tier Simple: ongoing quarterly review (half a full review). See 1099 tab for the Oct 30 cycle. | R14: Settled from 2026-04 (2026-04 – 2026-09)
A15: 7730 Evans LLC|Monthly Financials|Month End Close|Monthly | B15: 7730 Evans LLC | C15: Monthly Financials | D15: Month End Close | E15: Monthly | F15: 0.75 | G15: 0.3833 | H15: =F15+G15 -> 1.1333 | I15: =ROUND(H15*60,0) -> 68 | J15: =ROUND(F15*60,0) -> 45 | K15: =ROUND(G15*60,0) -> 23 | L15: Staff | M15: =F15*IF(L15="CFO",Assumptions!$B$5,Assumptions!$B$4)+G15*Assumptions!$B$5 -> 167.075 | N15: =F15*INDEX(Assumptions!$B$8:$B$14,MATCH(E15,Assumptions!$A$8:$A$14,0)) -> 0.75 | O15: =G15*INDEX(Assumptions!$B$8:$B$14,MATCH(E15,Assumptions!$A$8:$A$14,0)) -> 0.3833 | P15: Medium | Q15: Josephine's Apr–May 2026 closes + allowance for a new person (Valentina's hours not used). Review = median of 8 closes reviewed in Harvest (0.38h). | R15: Settled from 2026-04 (2026-04 – 2026-09)
A16: 909 MAIN LLC|1099|1099 Quarterly Review|1099 | B16: 909 MAIN LLC | C16: 1099 | D16: 1099 Quarterly Review | E16: 1099 | F16: =IFERROR(INDEX('1099 Oct 30'!$H$5:$H$45,MATCH(B16,'1099 Oct 30'!$A$5:$A$45,0)),0) -> 0.375 | G16: 0 | H16: =F16+G16 -> 0.375 | I16: =ROUND(H16*60,0) -> 23 | J16: =ROUND(F16*60,0) -> 23 | K16: =ROUND(G16*60,0) -> 0 | L16: Staff | M16: =F16*IF(L16="CFO",Assumptions!$B$5,Assumptions!$B$4)+G16*Assumptions!$B$5 -> 35.625 | N16: =F16*INDEX(Assumptions!$B$8:$B$14,MATCH(E16,Assumptions!$A$8:$A$14,0)) -> 0.125 | O16: =G16*INDEX(Assumptions!$B$8:$B$14,MATCH(E16,Assumptions!$A$8:$A$14,0)) -> 0 | P16: Provisional | Q16: 1099 tier Simple: ongoing quarterly review (half a full review). See 1099 tab for the Oct 30 cycle. Will become an Airbnb – provisional. Revisit once it converts. | R16: Settled from 2026-06 (2026-06 – 2026-09)
A17: 909 MAIN LLC|Monthly Financials|Month End Close|Monthly | B17: 909 MAIN LLC | C17: Monthly Financials | D17: Month End Close | E17: Monthly | F17: 1.25 | G17: 0.4833 | H17: =F17+G17 -> 1.7333 | I17: =ROUND(H17*60,0) -> 104 | J17: =ROUND(F17*60,0) -> 75 | K17: =ROUND(G17*60,0) -> 29 | L17: Staff | M17: =F17*IF(L17="CFO",Assumptions!$B$5,Assumptions!$B$4)+G17*Assumptions!$B$5 -> 239.575 | N17: =F17*INDEX(Assumptions!$B$8:$B$14,MATCH(E17,Assumptions!$A$8:$A$14,0)) -> 1.25 | O17: =G17*INDEX(Assumptions!$B$8:$B$14,MATCH(E17,Assumptions!$A$8:$A$14,0)) -> 0.4833 | P17: Provisional | Q17: Josephine's Apr–May 2026 closes + allowance for a new person (Valentina's hours not used). Will become an Airbnb – provisional. Revisit once it converts. Review = median of 8 closes reviewed in Harvest (0.48h). | R17: Settled from 2026-06 (2026-06 – 2026-09)
A18: Amerisource HR Consulting Group LLC|1099|1099 Quarterly Review|1099 | B18: Amerisource HR Consulting Group LLC | C18: 1099 | D18: 1099 Quarterly Review | E18: 1099 | F18: =IFERROR(INDEX('1099 Oct 30'!$H$5:$H$45,MATCH(B18,'1099 Oct 30'!$A$5:$A$45,0)),0) -> 0.75 | G18: 0 | H18: =F18+G18 -> 0.75 | I18: =ROUND(H18*60,0) -> 45 | J18: =ROUND(F18*60,0) -> 45 | K18: =ROUND(G18*60,0) -> 0 | L18: Staff | M18: =F18*IF(L18="CFO",Assumptions!$B$5,Assumptions!$B$4)+G18*Assumptions!$B$5 -> 71.25 | N18: =F18*INDEX(Assumptions!$B$8:$B$14,MATCH(E18,Assumptions!$A$8:$A$14,0)) -> 0.25 | O18: =G18*INDEX(Assumptions!$B$8:$B$14,MATCH(E18,Assumptions!$A$8:$A$14,0)) -> 0 | P18: Estimate | Q18: 1099 tier Standard: ongoing quarterly review (half a full review). See 1099 tab for the Oct 30 cycle. | R18: Settled from 2026-07 (2026-07 – 2026-09)
A19: Amerisource HR Consulting Group LLC|Year-end review|Adjusting Journal Entry Request|Annual | B19: Amerisource HR Consulting Group LLC | C19: Year-end review | D19: Adjusting Journal Entry Request | E19: Annual | F19: 5.6667 | G19: 0 | H19: =F19+G19 -> 5.6667 | I19: =ROUND(H19*60,0) -> 340 | J19: =ROUND(F19*60,0) -> 340 | K19: =ROUND(G19*60,0) -> 0 | L19: Staff | M19: =F19*IF(L19="CFO",Assumptions!$B$5,Assumptions!$B$4)+G19*Assumptions!$B$5 -> 538.3365 | N19: =F19*INDEX(Assumptions!$B$8:$B$14,MATCH(E19,Assumptions!$A$8:$A$14,0)) -> 0.472225 | O19: =G19*INDEX(Assumptions!$B$8:$B$14,MATCH(E19,Assumptions!$A$8:$A$14,0)) -> 0 | P19: High | Q19: Year-end/tax hours Oct 2025–Sep 2026 (5.6h). | R19: Settled from 2026-07 (2026-07 – 2026-09)
A20: Amerisource HR Consulting Group LLC|Monthly Financials|Month End Close|Monthly | B20: Amerisource HR Consulting Group LLC | C20: Monthly Financials | D20: Month End Close | E20: Monthly | F20: 16.1667 | G20: 1 | H20: =F20+G20 -> 17.1667 | I20: =ROUND(H20*60,0) -> 1030 | J20: =ROUND(F20*60,0) -> 970 | K20: =ROUND(G20*60,0) -> 60 | L20: Staff | M20: =F20*IF(L20="CFO",Assumptions!$B$5,Assumptions!$B$4)+G20*Assumptions!$B$5 -> 1785.8365 | N20: =F20*INDEX(Assumptions!$B$8:$B$14,MATCH(E20,Assumptions!$A$8:$A$14,0)) -> 16.1667 | O20: =G20*INDEX(Assumptions!$B$8:$B$14,MATCH(E20,Assumptions!$A$8:$A$14,0)) -> 1 | P20: High | Q20: Includes Month-end 5.0, Payroll 11.7, CFO advisory 0.2. Review = median of 4 closes reviewed in Harvest (1.00h). | R20: Settled from 2026-07 (2026-07 – 2026-09)
A21: Amerisource HR Consulting Group LLC|Bookkeeping|Bookkeeping & Bill Pay|Weekly | B21: Amerisource HR Consulting Group LLC | C21: Bookkeeping | D21: Bookkeeping & Bill Pay | E21: Weekly | F21: 1.8333 | G21: 0 | H21: =F21+G21 -> 1.8333 | I21: =ROUND(H21*60,0) -> 110 | J21: =ROUND(F21*60,0) -> 110 | K21: =ROUND(G21*60,0) -> 0 | L21: Staff | M21: =F21*IF(L21="CFO",Assumptions!$B$5,Assumptions!$B$4)+G21*Assumptions!$B$5 -> 174.1635 | N21: =F21*INDEX(Assumptions!$B$8:$B$14,MATCH(E21,Assumptions!$A$8:$A$14,0)) -> 7.9443 | O21: =G21*INDEX(Assumptions!$B$8:$B$14,MATCH(E21,Assumptions!$A$8:$A$14,0)) -> 0 | P21: High | Q21: Weekly bookkeeping/settlement time ÷ weeks per month. | R21: Settled from 2026-07 (2026-07 – 2026-09)
A22: BSD Contracting LLC|1099|1099 Quarterly Review|1099 | B22: BSD Contracting LLC | C22: 1099 | D22: 1099 Quarterly Review | E22: 1099 | F22: =IFERROR(INDEX('1099 Oct 30'!$H$5:$H$45,MATCH(B22,'1099 Oct 30'!$A$5:$A$45,0)),0) -> 2 | G22: 0 | H22: =F22+G22 -> 2 | I22: =ROUND(H22*60,0) -> 120 | J22: =ROUND(F22*60,0) -> 120 | K22: =ROUND(G22*60,0) -> 0 | L22: Staff | M22: =F22*IF(L22="CFO",Assumptions!$B$5,Assumptions!$B$4)+G22*Assumptions!$B$5 -> 190 | N22: =F22*INDEX(Assumptions!$B$8:$B$14,MATCH(E22,Assumptions!$A$8:$A$14,0)) -> 0.66666667 | O22: =G22*INDEX(Assumptions!$B$8:$B$14,MATCH(E22,Assumptions!$A$8:$A$14,0)) -> 0 | P22: Estimate | Q22: 1099 tier Complex: ongoing quarterly review (half a full review). See 1099 tab for the Oct 30 cycle. | R22: Settled from 2026-04 (2026-04 – 2026-09)
A23: BSD Contracting LLC|Monthly Financials|Month End Close|Monthly | B23: BSD Contracting LLC | C23: Monthly Financials | D23: Month End Close | E23: Monthly | F23: 0.75 | G23: 0.5 | H23: =F23+G23 -> 1.25 | I23: =ROUND(H23*60,0) -> 75 | J23: =ROUND(F23*60,0) -> 45 | K23: =ROUND(G23*60,0) -> 30 | L23: Staff | M23: =F23*IF(L23="CFO",Assumptions!$B$5,Assumptions!$B$4)+G23*Assumptions!$B$5 -> 196.25 | N23: =F23*INDEX(Assumptions!$B$8:$B$14,MATCH(E23,Assumptions!$A$8:$A$14,0)) -> 0.75 | O23: =G23*INDEX(Assumptions!$B$8:$B$14,MATCH(E23,Assumptions!$A$8:$A$14,0)) -> 0.5 | P23: High | Q23: Includes Month-end 0.7, Payroll 0.4. Review = median of 4 closes reviewed in Harvest (0.50h). | R23: Settled from 2026-04 (2026-04 – 2026-09)
A24: Barrett Living Trust|Year-end review|Adjusting Journal Entry Request|Annual | B24: Barrett Living Trust | C24: Year-end review | D24: Adjusting Journal Entry Request | E24: Annual | F24: 0.5 | G24: 0 | H24: =F24+G24 -> 0.5 | I24: =ROUND(H24*60,0) -> 30 | J24: =ROUND(F24*60,0) -> 30 | K24: =ROUND(G24*60,0) -> 0 | L24: Staff | M24: =F24*IF(L24="CFO",Assumptions!$B$5,Assumptions!$B$4)+G24*Assumptions!$B$5 -> 47.5 | N24: =F24*INDEX(Assumptions!$B$8:$B$14,MATCH(E24,Assumptions!$A$8:$A$14,0)) -> 0.041666667 | O24: =G24*INDEX(Assumptions!$B$8:$B$14,MATCH(E24,Assumptions!$A$8:$A$14,0)) -> 0 | P24: High | Q24: Year-end/tax hours Oct 2025–Sep 2026 (0.5h). | R24: Not settled by rule – median of last 6 months (2026-04 – 2026-09)
A25: Barrett Living Trust|Accounting|Month End Close|Monthly | B25: Barrett Living Trust | C25: Accounting | D25: Month End Close | E25: Monthly | F25: 2.8333 | G25: 1.1 | H25: =F25+G25 -> 3.9333 | I25: =ROUND(H25*60,0) -> 236 | J25: =ROUND(F25*60,0) -> 170 | K25: =ROUND(G25*60,0) -> 66 | L25: Staff | M25: =F25*IF(L25="CFO",Assumptions!$B$5,Assumptions!$B$4)+G25*Assumptions!$B$5 -> 544.1635 | N25: =F25*INDEX(Assumptions!$B$8:$B$14,MATCH(E25,Assumptions!$A$8:$A$14,0)) -> 2.8333 | O25: =G25*INDEX(Assumptions!$B$8:$B$14,MATCH(E25,Assumptions!$A$8:$A$14,0)) -> 1.1 | P25: High | Q25: Includes Month-end 2.6, Bookkeeping 0.9. Review = 1.10h as logged (only 2 reviewed close(s) in Harvest – check). | R25: Not settled by rule – median of last 6 months (2026-04 – 2026-09)
A26: BeckShar Development LLC|1099|1099 Quarterly Review|1099 | B26: BeckShar Development LLC | C26: 1099 | D26: 1099 Quarterly Review | E26: 1099 | F26: =IFERROR(INDEX('1099 Oct 30'!$H$5:$H$45,MATCH(B26,'1099 Oct 30'!$A$5:$A$45,0)),0) -> 0.75 | G26: 0 | H26: =F26+G26 -> 0.75 | I26: =ROUND(H26*60,0) -> 45 | J26: =ROUND(F26*60,0) -> 45 | K26: =ROUND(G26*60,0) -> 0 | L26: Staff | M26: =F26*IF(L26="CFO",Assumptions!$B$5,Assumptions!$B$4)+G26*Assumptions!$B$5 -> 71.25 | N26: =F26*INDEX(Assumptions!$B$8:$B$14,MATCH(E26,Assumptions!$A$8:$A$14,0)) -> 0.25 | O26: =G26*INDEX(Assumptions!$B$8:$B$14,MATCH(E26,Assumptions!$A$8:$A$14,0)) -> 0 | P26: Estimate | Q26: 1099 tier Standard: ongoing quarterly review (half a full review). See 1099 tab for the Oct 30 cycle. | R26: Settled from 2026-06 (2026-06 – 2026-09)
A27: BeckShar Development LLC|Monthly Financials|Month End Close|Monthly | B27: BeckShar Development LLC | C27: Monthly Financials | D27: Month End Close | E27: Monthly | F27: 6.9167 | G27: 0.8 | H27: =F27+G27 -> 7.7167 | I27: =ROUND(H27*60,0) -> 463 | J27: =ROUND(F27*60,0) -> 415 | K27: =ROUND(G27*60,0) -> 48 | L27: Staff | M27: =F27*IF(L27="CFO",Assumptions!$B$5,Assumptions!$B$4)+G27*Assumptions!$B$5 -> 857.0865 | N27: =F27*INDEX(Assumptions!$B$8:$B$14,MATCH(E27,Assumptions!$A$8:$A$14,0)) -> 6.9167 | O27: =G27*INDEX(Assumptions!$B$8:$B$14,MATCH(E27,Assumptions!$A$8:$A$14,0)) -> 0.8 | P27: High | Q27: Includes Month-end 2.5, Bookkeeping 0.2, Payroll 1.6, CFO advisory 2.1. Review = median of 6 closes reviewed in Harvest (0.80h). | R27: Settled from 2026-06 (2026-06 – 2026-09)
A28: BeckShar Diamond Commercial LLC|1099|1099 Quarterly Review|1099 | B28: BeckShar Diamond Commercial LLC | C28: 1099 | D28: 1099 Quarterly Review | E28: 1099 | F28: =IFERROR(INDEX('1099 Oct 30'!$H$5:$H$45,MATCH(B28,'1099 Oct 30'!$A$5:$A$45,0)),0) -> 0.75 | G28: 0 | H28: =F28+G28 -> 0.75 | I28: =ROUND(H28*60,0) -> 45 | J28: =ROUND(F28*60,0) -> 45 | K28: =ROUND(G28*60,0) -> 0 | L28: Staff | M28: =F28*IF(L28="CFO",Assumptions!$B$5,Assumptions!$B$4)+G28*Assumptions!$B$5 -> 71.25 | N28: =F28*INDEX(Assumptions!$B$8:$B$14,MATCH(E28,Assumptions!$A$8:$A$14,0)) -> 0.25 | O28: =G28*INDEX(Assumptions!$B$8:$B$14,MATCH(E28,Assumptions!$A$8:$A$14,0)) -> 0 | P28: Estimate | Q28: 1099 tier Standard: ongoing quarterly review (half a full review). See 1099 tab for the Oct 30 cycle. | R28: Settled from 2026-06 (2026-06 – 2026-09)
A29: BeckShar Diamond Commercial LLC|Monthly Financials|Month End Close|Monthly | B29: BeckShar Diamond Commercial LLC | C29: Monthly Financials | D29: Month End Close | E29: Monthly | F29: 0.4167 | G29: 0.5 | H29: =F29+G29 -> 0.9167 | I29: =ROUND(H29*60,0) -> 55 | J29: =ROUND(F29*60,0) -> 25 | K29: =ROUND(G29*60,0) -> 30 | L29: Staff | M29: =F29*IF(L29="CFO",Assumptions!$B$5,Assumptions!$B$4)+G29*Assumptions!$B$5 -> 164.5865 | N29: =F29*INDEX(Assumptions!$B$8:$B$14,MATCH(E29,Assumptions!$A$8:$A$14,0)) -> 0.4167 | O29: =G29*INDEX(Assumptions!$B$8:$B$14,MATCH(E29,Assumptions!$A$8:$A$14,0)) -> 0.5 | P29: High | Q29: Includes Month-end 0.7. Review = median of 4 closes reviewed in Harvest (0.50h). | R29: Settled from 2026-06 (2026-06 – 2026-09)
A30: BeckShar LLC|1099|1099 Quarterly Review|1099 | B30: BeckShar LLC | C30: 1099 | D30: 1099 Quarterly Review | E30: 1099 | F30: =IFERROR(INDEX('1099 Oct 30'!$H$5:$H$45,MATCH(B30,'1099 Oct 30'!$A$5:$A$45,0)),0) -> 2 | G30: 0 | H30: =F30+G30 -> 2 | I30: =ROUND(H30*60,0) -> 120 | J30: =ROUND(F30*60,0) -> 120 | K30: =ROUND(G30*60,0) -> 0 | L30: Staff | M30: =F30*IF(L30="CFO",Assumptions!$B$5,Assumptions!$B$4)+G30*Assumptions!$B$5 -> 190 | N30: =F30*INDEX(Assumptions!$B$8:$B$14,MATCH(E30,Assumptions!$A$8:$A$14,0)) -> 0.66666667 | O30: =G30*INDEX(Assumptions!$B$8:$B$14,MATCH(E30,Assumptions!$A$8:$A$14,0)) -> 0 | P30: Estimate | Q30: 1099 tier Complex: ongoing quarterly review (half a full review). See 1099 tab for the Oct 30 cycle. | R30: Settled from 2026-05 (2026-05 – 2026-09)
A31: BeckShar LLC|Monthly Financials|Month End Close|Monthly | B31: BeckShar LLC | C31: Monthly Financials | D31: Month End Close | E31: Monthly | F31: 2.9167 | G31: 1.25 | H31: =F31+G31 -> 4.1667 | I31: =ROUND(H31*60,0) -> 250 | J31: =ROUND(F31*60,0) -> 175 | K31: =ROUND(G31*60,0) -> 75 | L31: Staff | M31: =F31*IF(L31="CFO",Assumptions!$B$5,Assumptions!$B$4)+G31*Assumptions!$B$5 -> 589.5865 | N31: =F31*INDEX(Assumptions!$B$8:$B$14,MATCH(E31,Assumptions!$A$8:$A$14,0)) -> 2.9167 | O31: =G31*INDEX(Assumptions!$B$8:$B$14,MATCH(E31,Assumptions!$A$8:$A$14,0)) -> 1.25 | P31: High | Q31: Includes Month-end 1.2, Bookkeeping 0.5, Payroll 1.3, Sales tax 0.8. Review = 1.25h as logged (only 2 reviewed close(s) in Harvest – check). | R31: Settled from 2026-05 (2026-05 – 2026-09)
A32: Building and Development Professionals LLC|1099|1099 Quarterly Review|1099 | B32: Building and Development Professionals LLC | C32: 1099 | D32: 1099 Quarterly Review | E32: 1099 | F32: =IFERROR(INDEX('1099 Oct 30'!$H$5:$H$45,MATCH(B32,'1099 Oct 30'!$A$5:$A$45,0)),0) -> 2 | G32: 0 | H32: =F32+G32 -> 2 | I32: =ROUND(H32*60,0) -> 120 | J32: =ROUND(F32*60,0) -> 120 | K32: =ROUND(G32*60,0) -> 0 | L32: Staff | M32: =F32*IF(L32="CFO",Assumptions!$B$5,Assumptions!$B$4)+G32*Assumptions!$B$5 -> 190 | N32: =F32*INDEX(Assumptions!$B$8:$B$14,MATCH(E32,Assumptions!$A$8:$A$14,0)) -> 0.66666667 | O32: =G32*INDEX(Assumptions!$B$8:$B$14,MATCH(E32,Assumptions!$A$8:$A$14,0)) -> 0 | P32: Estimate | Q32: 1099 tier Complex: ongoing quarterly review (half a full review). See 1099 tab for the Oct 30 cycle. | R32: Not settled by rule – median of last 6 months (2026-04 – 2026-09)
A33: Building and Development Professionals LLC|Monthly Financials|Month End Close|Monthly | B33: Building and Development Professionals LLC | C33: Monthly Financials | D33: Month End Close | E33: Monthly | F33: 2.75 | G33: 0.5 | H33: =F33+G33 -> 3.25 | I33: =ROUND(H33*60,0) -> 195 | J33: =ROUND(F33*60,0) -> 165 | K33: =ROUND(G33*60,0) -> 30 | L33: CFO | M33: =F33*IF(L33="CFO",Assumptions!$B$5,Assumptions!$B$4)+G33*Assumptions!$B$5 -> 812.5 | N33: =F33*INDEX(Assumptions!$B$8:$B$14,MATCH(E33,Assumptions!$A$8:$A$14,0)) -> 2.75 | O33: =G33*INDEX(Assumptions!$B$8:$B$14,MATCH(E33,Assumptions!$A$8:$A$14,0)) -> 0.5 | P33: High | Q33: Includes Month-end 0.5, CFO advisory 1.9. Review = 0.5h placeholder (no close reviews found in Harvest) – check. | R33: Not settled by rule – median of last 6 months (2026-04 – 2026-09)
A34: Capital Financial LLC|1099|1099 Quarterly Review|1099 | B34: Capital Financial LLC | C34: 1099 | D34: 1099 Quarterly Review | E34: 1099 | F34: =IFERROR(INDEX('1099 Oct 30'!$H$5:$H$45,MATCH(B34,'1099 Oct 30'!$A$5:$A$45,0)),0) -> 0.75 | G34: 0 | H34: =F34+G34 -> 0.75 | I34: =ROUND(H34*60,0) -> 45 | J34: =ROUND(F34*60,0) -> 45 | K34: =ROUND(G34*60,0) -> 0 | L34: Staff | M34: =F34*IF(L34="CFO",Assumptions!$B$5,Assumptions!$B$4)+G34*Assumptions!$B$5 -> 71.25 | N34: =F34*INDEX(Assumptions!$B$8:$B$14,MATCH(E34,Assumptions!$A$8:$A$14,0)) -> 0.25 | O34: =G34*INDEX(Assumptions!$B$8:$B$14,MATCH(E34,Assumptions!$A$8:$A$14,0)) -> 0 | P34: Estimate | Q34: 1099 tier Standard: ongoing quarterly review (half a full review). See 1099 tab for the Oct 30 cycle. Aug–Sep 2026 excluded (one-time payroll JE re-entry, resolved). | R34: Settled from 2026-03 (2026-03 – 2026-07)
A35: Capital Financial LLC|Monthly Financials|Month End Close|Monthly | B35: Capital Financial LLC | C35: Monthly Financials | D35: Month End Close | E35: Monthly | F35: 7.6667 | G35: 1.2 | H35: =F35+G35 -> 8.8667 | I35: =ROUND(H35*60,0) -> 532 | J35: =ROUND(F35*60,0) -> 460 | K35: =ROUND(G35*60,0) -> 72 | L35: Staff | M35: =F35*IF(L35="CFO",Assumptions!$B$5,Assumptions!$B$4)+G35*Assumptions!$B$5 -> 1028.3365 | N35: =F35*INDEX(Assumptions!$B$8:$B$14,MATCH(E35,Assumptions!$A$8:$A$14,0)) -> 7.6667 | O35: =G35*INDEX(Assumptions!$B$8:$B$14,MATCH(E35,Assumptions!$A$8:$A$14,0)) -> 1.2 | P35: High | Q35: Includes Month-end 3.4, Bookkeeping 0.7, Payroll 2.7, CFO advisory 0.3. Aug–Sep 2026 excluded (one-time payroll JE re-entry, resolved). Review = median of 3 closes reviewed in Harvest (1.20h). | R35: Settled from 2026-03 (2026-03 – 2026-07)
A36: Catalpa Industrial Park Inc|1099|1099 Quarterly Review|1099 | B36: Catalpa Industrial Park Inc | C36: 1099 | D36: 1099 Quarterly Review | E36: 1099 | F36: =IFERROR(INDEX('1099 Oct 30'!$H$5:$H$45,MATCH(B36,'1099 Oct 30'!$A$5:$A$45,0)),0) -> 2 | G36: 0 | H36: =F36+G36 -> 2 | I36: =ROUND(H36*60,0) -> 120 | J36: =ROUND(F36*60,0) -> 120 | K36: =ROUND(G36*60,0) -> 0 | L36: Staff | M36: =F36*IF(L36="CFO",Assumptions!$B$5,Assumptions!$B$4)+G36*Assumptions!$B$5 -> 190 | N36: =F36*INDEX(Assumptions!$B$8:$B$14,MATCH(E36,Assumptions!$A$8:$A$14,0)) -> 0.66666667 | O36: =G36*INDEX(Assumptions!$B$8:$B$14,MATCH(E36,Assumptions!$A$8:$A$14,0)) -> 0 | P36: Estimate | Q36: 1099 tier Complex: ongoing quarterly review (half a full review). See 1099 tab for the Oct 30 cycle. | R36: Not settled by rule – median of last 6 months (2026-04 – 2026-09)
A37: Catalpa Industrial Park Inc|Monthly Financials|Month End Close|Monthly | B37: Catalpa Industrial Park Inc | C37: Monthly Financials | D37: Month End Close | E37: Monthly | F37: 4.4167 | G37: 0.7 | H37: =F37+G37 -> 5.1167 | I37: =ROUND(H37*60,0) -> 307 | J37: =ROUND(F37*60,0) -> 265 | K37: =ROUND(G37*60,0) -> 42 | L37: Staff | M37: =F37*IF(L37="CFO",Assumptions!$B$5,Assumptions!$B$4)+G37*Assumptions!$B$5 -> 594.5865 | N37: =F37*INDEX(Assumptions!$B$8:$B$14,MATCH(E37,Assumptions!$A$8:$A$14,0)) -> 4.4167 | O37: =G37*INDEX(Assumptions!$B$8:$B$14,MATCH(E37,Assumptions!$A$8:$A$14,0)) -> 0.7 | P37: High | Q37: Includes Month-end 4.7. Review = median of 6 closes reviewed in Harvest (0.70h). | R37: Not settled by rule – median of last 6 months (2026-04 – 2026-09)
A38: Desert Quail Creative Classroom LLC|1099|1099 Quarterly Review|1099 | B38: Desert Quail Creative Classroom LLC | C38: 1099 | D38: 1099 Quarterly Review | E38: 1099 | F38: =IFERROR(INDEX('1099 Oct 30'!$H$5:$H$45,MATCH(B38,'1099 Oct 30'!$A$5:$A$45,0)),0) -> 0.375 | G38: 0 | H38: =F38+G38 -> 0.375 | I38: =ROUND(H38*60,0) -> 23 | J38: =ROUND(F38*60,0) -> 23 | K38: =ROUND(G38*60,0) -> 0 | L38: Staff | M38: =F38*IF(L38="CFO",Assumptions!$B$5,Assumptions!$B$4)+G38*Assumptions!$B$5 -> 35.625 | N38: =F38*INDEX(Assumptions!$B$8:$B$14,MATCH(E38,Assumptions!$A$8:$A$14,0)) -> 0.125 | O38: =G38*INDEX(Assumptions!$B$8:$B$14,MATCH(E38,Assumptions!$A$8:$A$14,0)) -> 0 | P38: Estimate | Q38: 1099 tier Simple: ongoing quarterly review (half a full review). See 1099 tab for the Oct 30 cycle. | R38: Settled from 2026-04 (2026-04 – 2026-09)
A39: Desert Quail Creative Classroom LLC|Monthly Financials|Month End Close|Monthly | B39: Desert Quail Creative Classroom LLC | C39: Monthly Financials | D39: Month End Close | E39: Monthly | F39: 0.75 | G39: 0.5 | H39: =F39+G39 -> 1.25 | I39: =ROUND(H39*60,0) -> 75 | J39: =ROUND(F39*60,0) -> 45 | K39: =ROUND(G39*60,0) -> 30 | L39: Staff | M39: =F39*IF(L39="CFO",Assumptions!$B$5,Assumptions!$B$4)+G39*Assumptions!$B$5 -> 196.25 | N39: =F39*INDEX(Assumptions!$B$8:$B$14,MATCH(E39,Assumptions!$A$8:$A$14,0)) -> 0.75 | O39: =G39*INDEX(Assumptions!$B$8:$B$14,MATCH(E39,Assumptions!$A$8:$A$14,0)) -> 0.5 | P39: Medium | Q39: Josephine's Apr–May 2026 closes + allowance for a new person (Valentina's hours not used). Review = median of 7 closes reviewed in Harvest (0.50h). | R39: Settled from 2026-04 (2026-04 – 2026-09)
A40: Educational Services Holdings LLC|1099|1099 Quarterly Review|1099 | B40: Educational Services Holdings LLC | C40: 1099 | D40: 1099 Quarterly Review | E40: 1099 | F40: =IFERROR(INDEX('1099 Oct 30'!$H$5:$H$45,MATCH(B40,'1099 Oct 30'!$A$5:$A$45,0)),0) -> 0.75 | G40: 0 | H40: =F40+G40 -> 0.75 | I40: =ROUND(H40*60,0) -> 45 | J40: =ROUND(F40*60,0) -> 45 | K40: =ROUND(G40*60,0) -> 0 | L40: Staff | M40: =F40*IF(L40="CFO",Assumptions!$B$5,Assumptions!$B$4)+G40*Assumptions!$B$5 -> 71.25 | N40: =F40*INDEX(Assumptions!$B$8:$B$14,MATCH(E40,Assumptions!$A$8:$A$14,0)) -> 0.25 | O40: =G40*INDEX(Assumptions!$B$8:$B$14,MATCH(E40,Assumptions!$A$8:$A$14,0)) -> 0 | P40: Estimate | Q40: 1099 tier Standard: ongoing quarterly review (half a full review). See 1099 tab for the Oct 30 cycle. | R40: Settled from 2026-03 (2026-03 – 2026-09)
A41: Educational Services Holdings LLC|Monthly Financials|Month End Close|Monthly | B41: Educational Services Holdings LLC | C41: Monthly Financials | D41: Month End Close | E41: Monthly | F41: 5.75 | G41: 0.4833 | H41: =F41+G41 -> 6.2333 | I41: =ROUND(H41*60,0) -> 374 | J41: =ROUND(F41*60,0) -> 345 | K41: =ROUND(G41*60,0) -> 29 | L41: CFO | M41: =F41*IF(L41="CFO",Assumptions!$B$5,Assumptions!$B$4)+G41*Assumptions!$B$5 -> 1558.325 | N41: =F41*INDEX(Assumptions!$B$8:$B$14,MATCH(E41,Assumptions!$A$8:$A$14,0)) -> 5.75 | O41: =G41*INDEX(Assumptions!$B$8:$B$14,MATCH(E41,Assumptions!$A$8:$A$14,0)) -> 0.4833 | P41: Low – based on Valentina's hours | Q41: Includes Month-end 1.8, CFO advisory 3.8. Review = median of 4 closes reviewed in Harvest (0.48h). | R41: Settled from 2026-03 (2026-03 – 2026-09)
A42: Educational Services Intermediate LLC|Default|1099 Quarterly Review|1099 | B42: Educational Services Intermediate LLC | C42: Default | D42: 1099 Quarterly Review | E42: 1099 | P42: Excluded | Q42: No work for this entity (per Josephine). No budget set – consider closing the Karbon item.
A43: Educational Services LLC (dba ESI)|Year-end review|Annual Audit Support|Annual | B43: Educational Services LLC (dba ESI) | C43: Year-end review | D43: Annual Audit Support | E43: Annual | F43: 3 | G43: 0 | H43: =F43+G43 -> 3 | I43: =ROUND(H43*60,0) -> 180 | J43: =ROUND(F43*60,0) -> 180 | K43: =ROUND(G43*60,0) -> 0 | L43: CFO | M43: =F43*IF(L43="CFO",Assumptions!$B$5,Assumptions!$B$4)+G43*Assumptions!$B$5 -> 750 | N43: =F43*INDEX(Assumptions!$B$8:$B$14,MATCH(E43,Assumptions!$A$8:$A$14,0)) -> 0.25 | O43: =G43*INDEX(Assumptions!$B$8:$B$14,MATCH(E43,Assumptions!$A$8:$A$14,0)) -> 0 | P43: Medium | Q43: SUGGESTED – no item in Karbon. Steven's annual audit review/sign-off (Aug–Sep). Steven's CFO client; in-house controller does the books. Forecast/budget meetings treated as recurring CFO work. Jul light because client's controller was out. | R43: Oct 2025 – Sep 2026
A44: Educational Services LLC (dba ESI)|Monthly Financials|Month End Close|Monthly | B44: Educational Services LLC (dba ESI) | C44: Monthly Financials | D44: Month End Close | E44: Monthly | F44: 5.5 | G44: 1.75 | H44: =F44+G44 -> 7.25 | I44: =ROUND(H44*60,0) -> 435 | J44: =ROUND(F44*60,0) -> 330 | K44: =ROUND(G44*60,0) -> 105 | L44: CFO | M44: =F44*IF(L44="CFO",Assumptions!$B$5,Assumptions!$B$4)+G44*Assumptions!$B$5 -> 1812.5 | N44: =F44*INDEX(Assumptions!$B$8:$B$14,MATCH(E44,Assumptions!$A$8:$A$14,0)) -> 5.5 | O44: =G44*INDEX(Assumptions!$B$8:$B$14,MATCH(E44,Assumptions!$A$8:$A$14,0)) -> 1.75 | P44: High | Q44: Includes Month-end 0.1, CFO advisory 6.2. Steven's CFO client; in-house controller does the books. Forecast/budget meetings treated as recurring CFO work. Jul light because client's controller was out. Review = median of 7 closes reviewed in Harvest (1.75h). | R44: Not settled by rule – median of last 6 months (2026-04 – 2026-09)
A45: Eight Eleven LLC|1099|1099 Quarterly Review|1099 | B45: Eight Eleven LLC | C45: 1099 | D45: 1099 Quarterly Review | E45: 1099 | F45: =IFERROR(INDEX('1099 Oct 30'!$H$5:$H$45,MATCH(B45,'1099 Oct 30'!$A$5:$A$45,0)),0) -> 2 | G45: 0 | H45: =F45+G45 -> 2 | I45: =ROUND(H45*60,0) -> 120 | J45: =ROUND(F45*60,0) -> 120 | K45: =ROUND(G45*60,0) -> 0 | L45: Staff | M45: =F45*IF(L45="CFO",Assumptions!$B$5,Assumptions!$B$4)+G45*Assumptions!$B$5 -> 190 | N45: =F45*INDEX(Assumptions!$B$8:$B$14,MATCH(E45,Assumptions!$A$8:$A$14,0)) -> 0.66666667 | O45: =G45*INDEX(Assumptions!$B$8:$B$14,MATCH(E45,Assumptions!$A$8:$A$14,0)) -> 0 | P45: Estimate | Q45: 1099 tier Complex: ongoing quarterly review (half a full review). See 1099 tab for the Oct 30 cycle. Sep 2026 excluded (Christine out of time, not less work). | R45: Settled from 2026-06 (2026-06 – 2026-08)
A46: Eight Eleven LLC|Monthly Financials|Month End Close|Monthly | B46: Eight Eleven LLC | C46: Monthly Financials | D46: Month End Close | E46: Monthly | F46: 22.1667 | G46: 1.5 | H46: =F46+G46 -> 23.6667 | I46: =ROUND(H46*60,0) -> 1420 | J46: =ROUND(F46*60,0) -> 1330 | K46: =ROUND(G46*60,0) -> 90 | L46: Staff | M46: =F46*IF(L46="CFO",Assumptions!$B$5,Assumptions!$B$4)+G46*Assumptions!$B$5 -> 2480.8365 | N46: =F46*INDEX(Assumptions!$B$8:$B$14,MATCH(E46,Assumptions!$A$8:$A$14,0)) -> 22.1667 | O46: =G46*INDEX(Assumptions!$B$8:$B$14,MATCH(E46,Assumptions!$A$8:$A$14,0)) -> 1.5 | P46: High | Q46: Includes Month-end 8.3, Payroll 9.4, CFO advisory 1.1. Sep 2026 excluded (Christine out of time, not less work). Review = median of 10 closes reviewed in Harvest (1.50h). | R46: Settled from 2026-06 (2026-06 – 2026-08)
A47: Eight Eleven LLC|Accounting|Weekly Accounting Work|Weekly | B47: Eight Eleven LLC | C47: Accounting | D47: Weekly Accounting Work | E47: Weekly | F47: 2.5833 | G47: 0 | H47: =F47+G47 -> 2.5833 | I47: =ROUND(H47*60,0) -> 155 | J47: =ROUND(F47*60,0) -> 155 | K47: =ROUND(G47*60,0) -> 0 | L47: Staff | M47: =F47*IF(L47="CFO",Assumptions!$B$5,Assumptions!$B$4)+G47*Assumptions!$B$5 -> 245.4135 | N47: =F47*INDEX(Assumptions!$B$8:$B$14,MATCH(E47,Assumptions!$A$8:$A$14,0)) -> 11.1943 | O47: =G47*INDEX(Assumptions!$B$8:$B$14,MATCH(E47,Assumptions!$A$8:$A$14,0)) -> 0 | P47: High | Q47: Weekly bookkeeping/settlement time ÷ weeks per month. Sep 2026 excluded (Christine out of time, not less work). | R47: Settled from 2026-06 (2026-06 – 2026-08)
A48: FiveOliver LLC|1099|1099 Quarterly Review|1099 | B48: FiveOliver LLC | C48: 1099 | D48: 1099 Quarterly Review | E48: 1099 | F48: =IFERROR(INDEX('1099 Oct 30'!$H$5:$H$45,MATCH(B48,'1099 Oct 30'!$A$5:$A$45,0)),0) -> 2 | G48: 0 | H48: =F48+G48 -> 2 | I48: =ROUND(H48*60,0) -> 120 | J48: =ROUND(F48*60,0) -> 120 | K48: =ROUND(G48*60,0) -> 0 | L48: Staff | M48: =F48*IF(L48="CFO",Assumptions!$B$5,Assumptions!$B$4)+G48*Assumptions!$B$5 -> 190 | N48: =F48*INDEX(Assumptions!$B$8:$B$14,MATCH(E48,Assumptions!$A$8:$A$14,0)) -> 0.66666667 | O48: =G48*INDEX(Assumptions!$B$8:$B$14,MATCH(E48,Assumptions!$A$8:$A$14,0)) -> 0 | P48: Estimate | Q48: 1099 tier Complex: ongoing quarterly review (half a full review). See 1099 tab for the Oct 30 cycle. | R48: Settled from 2026-05 (2026-05 – 2026-09)
A49: GAV Enterprises Inc|1099|1099 Quarterly Review|1099 | B49: GAV Enterprises Inc | C49: 1099 | D49: 1099 Quarterly Review | E49: 1099 | F49: =IFERROR(INDEX('1099 Oct 30'!$H$5:$H$45,MATCH(B49,'1099 Oct 30'!$A$5:$A$45,0)),0) -> 0.75 | G49: 0 | H49: =F49+G49 -> 0.75 | I49: =ROUND(H49*60,0) -> 45 | J49: =ROUND(F49*60,0) -> 45 | K49: =ROUND(G49*60,0) -> 0 | L49: Staff | M49: =F49*IF(L49="CFO",Assumptions!$B$5,Assumptions!$B$4)+G49*Assumptions!$B$5 -> 71.25 | N49: =F49*INDEX(Assumptions!$B$8:$B$14,MATCH(E49,Assumptions!$A$8:$A$14,0)) -> 0.25 | O49: =G49*INDEX(Assumptions!$B$8:$B$14,MATCH(E49,Assumptions!$A$8:$A$14,0)) -> 0 | P49: Estimate | Q49: 1099 tier Standard: ongoing quarterly review (half a full review). See 1099 tab for the Oct 30 cycle. | R49: Quarterly client – average of Apr–Sep 2026 (2026-04 – 2026-09)
A50: GAV Enterprises Inc|Year-end review|Adjusting Journal Entry Request|Annual | B50: GAV Enterprises Inc | C50: Year-end review | D50: Adjusting Journal Entry Request | E50: Annual | F50: 0.3333 | G50: 0 | H50: =F50+G50 -> 0.3333 | I50: =ROUND(H50*60,0) -> 20 | J50: =ROUND(F50*60,0) -> 20 | K50: =ROUND(G50*60,0) -> 0 | L50: Staff | M50: =F50*IF(L50="CFO",Assumptions!$B$5,Assumptions!$B$4)+G50*Assumptions!$B$5 -> 31.6635 | N50: =F50*INDEX(Assumptions!$B$8:$B$14,MATCH(E50,Assumptions!$A$8:$A$14,0)) -> 0.027775 | O50: =G50*INDEX(Assumptions!$B$8:$B$14,MATCH(E50,Assumptions!$A$8:$A$14,0)) -> 0 | P50: High | Q50: Year-end/tax hours Oct 2025–Sep 2026 (0.8h) split across 2 year-end items. | R50: Quarterly client – average of Apr–Sep 2026 (2026-04 – 2026-09)
A51: GAV Enterprises Inc|Default|Year-End Tax Coordination|Annual | B51: GAV Enterprises Inc | C51: Default | D51: Year-End Tax Coordination | E51: Annual | F51: 0.3333 | G51: 0 | H51: =F51+G51 -> 0.3333 | I51: =ROUND(H51*60,0) -> 20 | J51: =ROUND(F51*60,0) -> 20 | K51: =ROUND(G51*60,0) -> 0 | L51: Staff | M51: =F51*IF(L51="CFO",Assumptions!$B$5,Assumptions!$B$4)+G51*Assumptions!$B$5 -> 31.6635 | N51: =F51*INDEX(Assumptions!$B$8:$B$14,MATCH(E51,Assumptions!$A$8:$A$14,0)) -> 0.027775 | O51: =G51*INDEX(Assumptions!$B$8:$B$14,MATCH(E51,Assumptions!$A$8:$A$14,0)) -> 0 | P51: High | Q51: Year-end/tax hours Oct 2025–Sep 2026 (0.8h) split across 2 year-end items. | R51: Quarterly client – average of Apr–Sep 2026 (2026-04 – 2026-09)
A52: GAV Enterprises Inc|Accounting|Quarter End Close|Quarterly | B52: GAV Enterprises Inc | C52: Accounting | D52: Quarter End Close | E52: Quarterly | F52: 18.5833 | G52: 1.5 | H52: =F52+G52 -> 20.0833 | I52: =ROUND(H52*60,0) -> 1205 | J52: =ROUND(F52*60,0) -> 1115 | K52: =ROUND(G52*60,0) -> 90 | L52: Staff | M52: =F52*IF(L52="CFO",Assumptions!$B$5,Assumptions!$B$4)+G52*Assumptions!$B$5 -> 2140.4135 | N52: =F52*INDEX(Assumptions!$B$8:$B$14,MATCH(E52,Assumptions!$A$8:$A$14,0)) -> 6.1944333 | O52: =G52*INDEX(Assumptions!$B$8:$B$14,MATCH(E52,Assumptions!$A$8:$A$14,0)) -> 0.5 | P52: High | Q52: Includes Month-end 10.4, Bookkeeping 7.8, CFO advisory 0.7. Review = 0.25h as logged (only 1 reviewed close(s) in Harvest – check). Quarterly review from history: Q3 2025 Lisa 1.0 first pass + 0.5 complete = 1.5h; Jan–Jun 2024 review ~1.5h. | R52: Quarterly client – average of Apr–Sep 2026 (2026-04 – 2026-09)
A53: International Alliance Group LLC|1099|1099 Quarterly Review|1099 | B53: International Alliance Group LLC | C53: 1099 | D53: 1099 Quarterly Review | E53: 1099 | P53: Excluded | Q53: On hold – IAG brought in-house. No budget set.
A54: International Alliance Group LLC|Year-end review|Adjusting Journal Entry Request|Annual | B54: International Alliance Group LLC | C54: Year-end review | D54: Adjusting Journal Entry Request | E54: Annual | P54: Excluded | Q54: On hold – IAG brought in-house. No budget set.
A55: International Alliance Group LLC|Sales tax|Hawaii Monthly Tax Filing - Onyx Prepares & Files|Monthly | B55: International Alliance Group LLC | C55: Sales tax | D55: Hawaii Monthly Tax Filing - Onyx Prepares & Files | E55: Monthly | P55: Excluded | Q55: On hold – IAG brought in-house. No budget set.
A56: International Alliance Group LLC|Monthly Financials|Month End Close|Monthly | B56: International Alliance Group LLC | C56: Monthly Financials | D56: Month End Close | E56: Monthly | P56: Excluded | Q56: On hold – IAG brought in-house. No budget set.
A57: International Alliance Group LLC|Sales tax|Sales Tax Filing - Onyx Prepares the Returns for Client|Monthly | B57: International Alliance Group LLC | C57: Sales tax | D57: Sales Tax Filing - Onyx Prepares the Returns for Client | E57: Monthly | P57: Excluded | Q57: On hold – IAG brought in-house. No budget set.
A58: International Alliance Group LLC|Accounting|Quarterly 1GPA Filing|Quarterly | B58: International Alliance Group LLC | C58: Accounting | D58: Quarterly 1GPA Filing | E58: Quarterly | P58: Excluded | Q58: On hold – IAG brought in-house. No budget set.
A59: International Alliance Group LLC|Sales tax|Quarterly Financial Reports to MidFirst Bank|Quarterly | B59: International Alliance Group LLC | C59: Sales tax | D59: Quarterly Financial Reports to MidFirst Bank | E59: Quarterly | P59: Excluded | Q59: On hold – IAG brought in-house. No budget set.
A60: International Alliance Group LLC|Sales tax|Quarterly Sales Tax Returns - Onyx Prepares the Returns for Client|Quarterly | B60: International Alliance Group LLC | C60: Sales tax | D60: Quarterly Sales Tax Returns - Onyx Prepares the Returns for Client | E60: Quarterly | P60: Excluded | Q60: On hold – IAG brought in-house. No budget set.
A61: International Alliance Group LLC|Accounting|Bookkeeping & Bill Pay|Weekly | B61: International Alliance Group LLC | C61: Accounting | D61: Bookkeeping & Bill Pay | E61: Weekly | P61: Excluded | Q61: On hold – IAG brought in-house. No budget set.
A62: KAMM ADGT LLC|1099|1099 Quarterly Review|1099 | B62: KAMM ADGT LLC | C62: 1099 | D62: 1099 Quarterly Review | E62: 1099 | F62: =IFERROR(INDEX('1099 Oct 30'!$H$5:$H$45,MATCH(B62,'1099 Oct 30'!$A$5:$A$45,0)),0) -> 0.375 | G62: 0 | H62: =F62+G62 -> 0.375 | I62: =ROUND(H62*60,0) -> 23 | J62: =ROUND(F62*60,0) -> 23 | K62: =ROUND(G62*60,0) -> 0 | L62: Staff | M62: =F62*IF(L62="CFO",Assumptions!$B$5,Assumptions!$B$4)+G62*Assumptions!$B$5 -> 35.625 | N62: =F62*INDEX(Assumptions!$B$8:$B$14,MATCH(E62,Assumptions!$A$8:$A$14,0)) -> 0.125 | O62: =G62*INDEX(Assumptions!$B$8:$B$14,MATCH(E62,Assumptions!$A$8:$A$14,0)) -> 0 | P62: Estimate | Q62: 1099 tier Simple: ongoing quarterly review (half a full review). See 1099 tab for the Oct 30 cycle. | R62: Settled from 2026-04 (2026-04 – 2026-09)
A63: KAMM ADGT LLC|Monthly Financials|Month End Close|Monthly | B63: KAMM ADGT LLC | C63: Monthly Financials | D63: Month End Close | E63: Monthly | F63: 0.5 | G63: 0.3833 | H63: =F63+G63 -> 0.8833 | I63: =ROUND(H63*60,0) -> 53 | J63: =ROUND(F63*60,0) -> 30 | K63: =ROUND(G63*60,0) -> 23 | L63: Staff | M63: =F63*IF(L63="CFO",Assumptions!$B$5,Assumptions!$B$4)+G63*Assumptions!$B$5 -> 143.325 | N63: =F63*INDEX(Assumptions!$B$8:$B$14,MATCH(E63,Assumptions!$A$8:$A$14,0)) -> 0.5 | O63: =G63*INDEX(Assumptions!$B$8:$B$14,MATCH(E63,Assumptions!$A$8:$A$14,0)) -> 0.3833 | P63: Medium | Q63: Josephine's Apr–May 2026 closes + allowance for a new person (Valentina's hours not used). Review = median of 8 closes reviewed in Harvest (0.38h). | R63: Settled from 2026-04 (2026-04 – 2026-09)
A64: Little Moo's LLC|1099|1099 Quarterly Review|1099 | B64: Little Moo's LLC | C64: 1099 | D64: 1099 Quarterly Review | E64: 1099 | F64: =IFERROR(INDEX('1099 Oct 30'!$H$5:$H$45,MATCH(B64,'1099 Oct 30'!$A$5:$A$45,0)),0) -> 0.375 | G64: 0 | H64: =F64+G64 -> 0.375 | I64: =ROUND(H64*60,0) -> 23 | J64: =ROUND(F64*60,0) -> 23 | K64: =ROUND(G64*60,0) -> 0 | L64: Staff | M64: =F64*IF(L64="CFO",Assumptions!$B$5,Assumptions!$B$4)+G64*Assumptions!$B$5 -> 35.625 | N64: =F64*INDEX(Assumptions!$B$8:$B$14,MATCH(E64,Assumptions!$A$8:$A$14,0)) -> 0.125 | O64: =G64*INDEX(Assumptions!$B$8:$B$14,MATCH(E64,Assumptions!$A$8:$A$14,0)) -> 0 | P64: Provisional | Q64: 1099 tier Simple: ongoing quarterly review (half a full review). See 1099 tab for the Oct 30 cycle. Store opens Oct 2026 (Square POS, sales tax, inventory; payroll later) – provisional, pre-opening level. Revisit after 2–3 months open. | R64: Settled from 2026-05 (2026-05 – 2026-09)
A65: Little Moo's LLC|Monthly Financials|Month End Close|Monthly | B65: Little Moo's LLC | C65: Monthly Financials | D65: Month End Close | E65: Monthly | F65: 1.6667 | G65: 0.3833 | H65: =F65+G65 -> 2.05 | I65: =ROUND(H65*60,0) -> 123 | J65: =ROUND(F65*60,0) -> 100 | K65: =ROUND(G65*60,0) -> 23 | L65: Staff | M65: =F65*IF(L65="CFO",Assumptions!$B$5,Assumptions!$B$4)+G65*Assumptions!$B$5 -> 254.1615 | N65: =F65*INDEX(Assumptions!$B$8:$B$14,MATCH(E65,Assumptions!$A$8:$A$14,0)) -> 1.6667 | O65: =G65*INDEX(Assumptions!$B$8:$B$14,MATCH(E65,Assumptions!$A$8:$A$14,0)) -> 0.3833 | P65: Provisional | Q65: Includes Month-end 1.7, CFO advisory 0.1. Store opens Oct 2026 (Square POS, sales tax, inventory; payroll later) – provisional, pre-opening level. Revisit after 2–3 months open. Review = median of 8 closes reviewed in Harvest (0.38h). | R65: Settled from 2026-05 (2026-05 – 2026-09)
A66: Little Moo's LLC|Sales tax|Sales Tax Filing - Onyx Prepares the Returns for Client|Monthly | B66: Little Moo's LLC | C66: Sales tax | D66: Sales Tax Filing - Onyx Prepares the Returns for Client | E66: Monthly | F66: 0.9167 | G66: 0 | H66: =F66+G66 -> 0.9167 | I66: =ROUND(H66*60,0) -> 55 | J66: =ROUND(F66*60,0) -> 55 | K66: =ROUND(G66*60,0) -> 0 | L66: Staff | M66: =F66*IF(L66="CFO",Assumptions!$B$5,Assumptions!$B$4)+G66*Assumptions!$B$5 -> 87.0865 | N66: =F66*INDEX(Assumptions!$B$8:$B$14,MATCH(E66,Assumptions!$A$8:$A$14,0)) -> 0.9167 | O66: =G66*INDEX(Assumptions!$B$8:$B$14,MATCH(E66,Assumptions!$A$8:$A$14,0)) -> 0 | P66: Provisional | Q66: Sales tax time per month. Store opens Oct 2026 (Square POS, sales tax, inventory; payroll later) – provisional, pre-opening level. Revisit after 2–3 months open. | R66: Settled from 2026-05 (2026-05 – 2026-09)
A67: Midwest Contracting Inc|1099|1099 Quarterly Review|1099 | B67: Midwest Contracting Inc | C67: 1099 | D67: 1099 Quarterly Review | E67: 1099 | F67: =IFERROR(INDEX('1099 Oct 30'!$H$5:$H$45,MATCH(B67,'1099 Oct 30'!$A$5:$A$45,0)),0) -> 2 | G67: 0 | H67: =F67+G67 -> 2 | I67: =ROUND(H67*60,0) -> 120 | J67: =ROUND(F67*60,0) -> 120 | K67: =ROUND(G67*60,0) -> 0 | L67: Staff | M67: =F67*IF(L67="CFO",Assumptions!$B$5,Assumptions!$B$4)+G67*Assumptions!$B$5 -> 190 | N67: =F67*INDEX(Assumptions!$B$8:$B$14,MATCH(E67,Assumptions!$A$8:$A$14,0)) -> 0.66666667 | O67: =G67*INDEX(Assumptions!$B$8:$B$14,MATCH(E67,Assumptions!$A$8:$A$14,0)) -> 0 | P67: Estimate | Q67: 1099 tier Complex: ongoing quarterly review (half a full review). See 1099 tab for the Oct 30 cycle. | R67: Settled from 2026-07 (2026-07 – 2026-09)
A68: Midwest Contracting Inc|Monthly Financials|Month End Close|Monthly | B68: Midwest Contracting Inc | C68: Monthly Financials | D68: Month End Close | E68: Monthly | F68: 35.3333 | G68: 1.5 | H68: =F68+G68 -> 36.8333 | I68: =ROUND(H68*60,0) -> 2210 | J68: =ROUND(F68*60,0) -> 2120 | K68: =ROUND(G68*60,0) -> 90 | L68: Staff | M68: =F68*IF(L68="CFO",Assumptions!$B$5,Assumptions!$B$4)+G68*Assumptions!$B$5 -> 3731.6635 | N68: =F68*INDEX(Assumptions!$B$8:$B$14,MATCH(E68,Assumptions!$A$8:$A$14,0)) -> 35.3333 | O68: =G68*INDEX(Assumptions!$B$8:$B$14,MATCH(E68,Assumptions!$A$8:$A$14,0)) -> 1.5 | P68: High | Q68: Includes Month-end 13.9, Payroll 12.1, Sales tax 0.5, CFO advisory 7.4. Review = median of 5 closes reviewed in Harvest (1.50h). | R68: Settled from 2026-07 (2026-07 – 2026-09)
A69: Midwest Contracting Inc|Accounting|Weekly Accounting|Weekly | B69: Midwest Contracting Inc | C69: Accounting | D69: Weekly Accounting | E69: Weekly | F69: 2.25 | G69: 0 | H69: =F69+G69 -> 2.25 | I69: =ROUND(H69*60,0) -> 135 | J69: =ROUND(F69*60,0) -> 135 | K69: =ROUND(G69*60,0) -> 0 | L69: Staff | M69: =F69*IF(L69="CFO",Assumptions!$B$5,Assumptions!$B$4)+G69*Assumptions!$B$5 -> 213.75 | N69: =F69*INDEX(Assumptions!$B$8:$B$14,MATCH(E69,Assumptions!$A$8:$A$14,0)) -> 9.75 | O69: =G69*INDEX(Assumptions!$B$8:$B$14,MATCH(E69,Assumptions!$A$8:$A$14,0)) -> 0 | P69: High | Q69: Weekly bookkeeping/settlement time ÷ weeks per month. | R69: Settled from 2026-07 (2026-07 – 2026-09)
A70: Mohrschladt Capital LP|1099|1099 Quarterly Review|1099 | B70: Mohrschladt Capital LP | C70: 1099 | D70: 1099 Quarterly Review | E70: 1099 | F70: =IFERROR(INDEX('1099 Oct 30'!$H$5:$H$45,MATCH(B70,'1099 Oct 30'!$A$5:$A$45,0)),0) -> 0.75 | G70: 0 | H70: =F70+G70 -> 0.75 | I70: =ROUND(H70*60,0) -> 45 | J70: =ROUND(F70*60,0) -> 45 | K70: =ROUND(G70*60,0) -> 0 | L70: Staff | M70: =F70*IF(L70="CFO",Assumptions!$B$5,Assumptions!$B$4)+G70*Assumptions!$B$5 -> 71.25 | N70: =F70*INDEX(Assumptions!$B$8:$B$14,MATCH(E70,Assumptions!$A$8:$A$14,0)) -> 0.25 | O70: =G70*INDEX(Assumptions!$B$8:$B$14,MATCH(E70,Assumptions!$A$8:$A$14,0)) -> 0 | P70: Estimate | Q70: 1099 tier Standard: ongoing quarterly review (half a full review). See 1099 tab for the Oct 30 cycle. | R70: Not settled by rule – median of last 6 months (2026-04 – 2026-09)
A71: Mohrschladt Capital LP|Monthly Financials|Month End Close|Monthly | B71: Mohrschladt Capital LP | C71: Monthly Financials | D71: Month End Close | E71: Monthly | F71: 3.25 | G71: 0.7 | H71: =F71+G71 -> 3.95 | I71: =ROUND(H71*60,0) -> 237 | J71: =ROUND(F71*60,0) -> 195 | K71: =ROUND(G71*60,0) -> 42 | L71: Staff | M71: =F71*IF(L71="CFO",Assumptions!$B$5,Assumptions!$B$4)+G71*Assumptions!$B$5 -> 483.75 | N71: =F71*INDEX(Assumptions!$B$8:$B$14,MATCH(E71,Assumptions!$A$8:$A$14,0)) -> 3.25 | O71: =G71*INDEX(Assumptions!$B$8:$B$14,MATCH(E71,Assumptions!$A$8:$A$14,0)) -> 0.7 | P71: High | Q71: Includes Month-end 2.6, Bookkeeping 0.4, CFO advisory 0.1. Review = median of 5 closes reviewed in Harvest (0.70h). | R71: Not settled by rule – median of last 6 months (2026-04 – 2026-09)
A72: Mohrschladt Howarth Associates Inc|1099|1099 Quarterly Review|1099 | B72: Mohrschladt Howarth Associates Inc | C72: 1099 | D72: 1099 Quarterly Review | E72: 1099 | F72: =IFERROR(INDEX('1099 Oct 30'!$H$5:$H$45,MATCH(B72,'1099 Oct 30'!$A$5:$A$45,0)),0) -> 2 | G72: 0 | H72: =F72+G72 -> 2 | I72: =ROUND(H72*60,0) -> 120 | J72: =ROUND(F72*60,0) -> 120 | K72: =ROUND(G72*60,0) -> 0 | L72: Staff | M72: =F72*IF(L72="CFO",Assumptions!$B$5,Assumptions!$B$4)+G72*Assumptions!$B$5 -> 190 | N72: =F72*INDEX(Assumptions!$B$8:$B$14,MATCH(E72,Assumptions!$A$8:$A$14,0)) -> 0.66666667 | O72: =G72*INDEX(Assumptions!$B$8:$B$14,MATCH(E72,Assumptions!$A$8:$A$14,0)) -> 0 | P72: Estimate | Q72: 1099 tier Complex: ongoing quarterly review (half a full review). See 1099 tab for the Oct 30 cycle. | R72: Settled from 2026-06 (2026-06 – 2026-09)
A73: Mohrschladt Howarth Associates Inc|Monthly Financials|Month End Close|Monthly | B73: Mohrschladt Howarth Associates Inc | C73: Monthly Financials | D73: Month End Close | E73: Monthly | F73: 1.75 | G73: 0.7 | H73: =F73+G73 -> 2.45 | I73: =ROUND(H73*60,0) -> 147 | J73: =ROUND(F73*60,0) -> 105 | K73: =ROUND(G73*60,0) -> 42 | L73: Staff | M73: =F73*IF(L73="CFO",Assumptions!$B$5,Assumptions!$B$4)+G73*Assumptions!$B$5 -> 341.25 | N73: =F73*INDEX(Assumptions!$B$8:$B$14,MATCH(E73,Assumptions!$A$8:$A$14,0)) -> 1.75 | O73: =G73*INDEX(Assumptions!$B$8:$B$14,MATCH(E73,Assumptions!$A$8:$A$14,0)) -> 0.7 | P73: High | Q73: Includes Month-end 1.9. Review = median of 7 closes reviewed in Harvest (0.70h). | R73: Settled from 2026-06 (2026-06 – 2026-09)
A74: Mountain Trade Supply Inc|Default|1099 Quarterly Review|1099 | B74: Mountain Trade Supply Inc | C74: Default | D74: 1099 Quarterly Review | E74: 1099 | F74: =IFERROR(INDEX('1099 Oct 30'!$H$5:$H$45,MATCH(B74,'1099 Oct 30'!$A$5:$A$45,0)),0) -> 2 | G74: 0 | H74: =F74+G74 -> 2 | I74: =ROUND(H74*60,0) -> 120 | J74: =ROUND(F74*60,0) -> 120 | K74: =ROUND(G74*60,0) -> 0 | L74: Staff | M74: =F74*IF(L74="CFO",Assumptions!$B$5,Assumptions!$B$4)+G74*Assumptions!$B$5 -> 190 | N74: =F74*INDEX(Assumptions!$B$8:$B$14,MATCH(E74,Assumptions!$A$8:$A$14,0)) -> 0.66666667 | O74: =G74*INDEX(Assumptions!$B$8:$B$14,MATCH(E74,Assumptions!$A$8:$A$14,0)) -> 0 | P74: Estimate | Q74: 1099 tier Complex: ongoing quarterly review (half a full review). See 1099 tab for the Oct 30 cycle. Payroll takeover in progress (Paychex/401k/PFML); tax audit budgeted separately. Confirm payroll is ongoing. | R74: Not settled by rule – median of last 6 months (2026-04 – 2026-09)
A75: Mountain Trade Supply Inc|Payroll|Payroll Bi-Weekly 401K Payment|Bi-weekly | B75: Mountain Trade Supply Inc | C75: Payroll | D75: Payroll Bi-Weekly 401K Payment | E75: Bi-weekly | F75: 0.3333 | G75: 0.1667 | H75: =F75+G75 -> 0.5 | I75: =ROUND(H75*60,0) -> 30 | J75: =ROUND(F75*60,0) -> 20 | K75: =ROUND(G75*60,0) -> 10 | L75: Staff | M75: =F75*IF(L75="CFO",Assumptions!$B$5,Assumptions!$B$4)+G75*Assumptions!$B$5 -> 73.3385 | N75: =F75*INDEX(Assumptions!$B$8:$B$14,MATCH(E75,Assumptions!$A$8:$A$14,0)) -> 0.72215 | O75: =G75*INDEX(Assumptions!$B$8:$B$14,MATCH(E75,Assumptions!$A$8:$A$14,0)) -> 0.36118333 | P75: High | Q75: Payroll time ÷ pay periods per month (25% share). Payroll takeover in progress (Paychex/401k/PFML); tax audit budgeted separately. Confirm payroll is ongoing. Review = Lisa oversight, 15 min per occurrence (work moving to Jessica). | R75: Not settled by rule – median of last 6 months (2026-04 – 2026-09)
A76: Mountain Trade Supply Inc|Accounting|Run Payroll in Paychex|Bi-weekly | B76: Mountain Trade Supply Inc | C76: Accounting | D76: Run Payroll in Paychex | E76: Bi-weekly | F76: 0.9167 | G76: 0.25 | H76: =F76+G76 -> 1.1667 | I76: =ROUND(H76*60,0) -> 70 | J76: =ROUND(F76*60,0) -> 55 | K76: =ROUND(G76*60,0) -> 15 | L76: Staff | M76: =F76*IF(L76="CFO",Assumptions!$B$5,Assumptions!$B$4)+G76*Assumptions!$B$5 -> 149.5865 | N76: =F76*INDEX(Assumptions!$B$8:$B$14,MATCH(E76,Assumptions!$A$8:$A$14,0)) -> 1.9861833 | O76: =G76*INDEX(Assumptions!$B$8:$B$14,MATCH(E76,Assumptions!$A$8:$A$14,0)) -> 0.54166667 | P76: High | Q76: Payroll time ÷ pay periods per month (75% share). Payroll takeover in progress (Paychex/401k/PFML); tax audit budgeted separately. Confirm payroll is ongoing. Review = Lisa oversight, 15 min per occurrence (work moving to Jessica). | R76: Not settled by rule – median of last 6 months (2026-04 – 2026-09)
A77: Mountain Trade Supply Inc|Monthly Financials|Month End Close|Monthly | B77: Mountain Trade Supply Inc | C77: Monthly Financials | D77: Month End Close | E77: Monthly | F77: 4.6667 | G77: 0.8333 | H77: =F77+G77 -> 5.5 | I77: =ROUND(H77*60,0) -> 330 | J77: =ROUND(F77*60,0) -> 280 | K77: =ROUND(G77*60,0) -> 50 | L77: Staff | M77: =F77*IF(L77="CFO",Assumptions!$B$5,Assumptions!$B$4)+G77*Assumptions!$B$5 -> 651.6615 | N77: =F77*INDEX(Assumptions!$B$8:$B$14,MATCH(E77,Assumptions!$A$8:$A$14,0)) -> 4.6667 | O77: =G77*INDEX(Assumptions!$B$8:$B$14,MATCH(E77,Assumptions!$A$8:$A$14,0)) -> 0.8333 | P77: Low | Q77: SUGGESTED – no recurring month-end item in the Oct list (only the July clean-up). Payroll takeover in progress (Paychex/401k/PFML); tax audit budgeted separately. Confirm payroll is ongoing. Review = 0.25h as logged (only 1 reviewed close(s) in Harvest – check). Review set to 0:50 per Josephine (CYMA login 5–8 min, complex system; 0.7–1h). | R77: Not settled by rule – median of last 6 months (2026-04 – 2026-09)
A78: Newport Classic Cars LLC|1099|1099 Quarterly Review|1099 | B78: Newport Classic Cars LLC | C78: 1099 | D78: 1099 Quarterly Review | E78: 1099 | F78: =IFERROR(INDEX('1099 Oct 30'!$H$5:$H$45,MATCH(B78,'1099 Oct 30'!$A$5:$A$45,0)),0) -> 0.75 | G78: 0 | H78: =F78+G78 -> 0.75 | I78: =ROUND(H78*60,0) -> 45 | J78: =ROUND(F78*60,0) -> 45 | K78: =ROUND(G78*60,0) -> 0 | L78: Staff | M78: =F78*IF(L78="CFO",Assumptions!$B$5,Assumptions!$B$4)+G78*Assumptions!$B$5 -> 71.25 | N78: =F78*INDEX(Assumptions!$B$8:$B$14,MATCH(E78,Assumptions!$A$8:$A$14,0)) -> 0.25 | O78: =G78*INDEX(Assumptions!$B$8:$B$14,MATCH(E78,Assumptions!$A$8:$A$14,0)) -> 0 | P78: Estimate | Q78: 1099 tier Standard: ongoing quarterly review (half a full review). See 1099 tab for the Oct 30 cycle. | R78: Quarterly client – average of Apr–Sep 2026 (2026-04 – 2026-09)
A79: Newport Classic Cars LLC|Quarterly Financials|Quarterly Month End Close|Quarterly | B79: Newport Classic Cars LLC | C79: Quarterly Financials | D79: Quarterly Month End Close | E79: Quarterly | F79: 1.4167 | G79: 0.7 | H79: =F79+G79 -> 2.1167 | I79: =ROUND(H79*60,0) -> 127 | J79: =ROUND(F79*60,0) -> 85 | K79: =ROUND(G79*60,0) -> 42 | L79: Staff | M79: =F79*IF(L79="CFO",Assumptions!$B$5,Assumptions!$B$4)+G79*Assumptions!$B$5 -> 309.5865 | N79: =F79*INDEX(Assumptions!$B$8:$B$14,MATCH(E79,Assumptions!$A$8:$A$14,0)) -> 0.47223333 | O79: =G79*INDEX(Assumptions!$B$8:$B$14,MATCH(E79,Assumptions!$A$8:$A$14,0)) -> 0.23333333 | P79: High | Q79: Includes Month-end 0.8, Payroll 0.4. Review = median of 6 closes reviewed in Harvest (0.70h). | R79: Quarterly client – average of Apr–Sep 2026 (2026-04 – 2026-09)
A80: Newport Classic Cars LLC|Sales tax|Quarterly Sales Tax Returns - Onyx Prepares the Returns for Client|Quarterly | B80: Newport Classic Cars LLC | C80: Sales tax | D80: Quarterly Sales Tax Returns - Onyx Prepares the Returns for Client | E80: Quarterly | F80: 0.5 | G80: 0 | H80: =F80+G80 -> 0.5 | I80: =ROUND(H80*60,0) -> 30 | J80: =ROUND(F80*60,0) -> 30 | K80: =ROUND(G80*60,0) -> 0 | L80: Staff | M80: =F80*IF(L80="CFO",Assumptions!$B$5,Assumptions!$B$4)+G80*Assumptions!$B$5 -> 47.5 | N80: =F80*INDEX(Assumptions!$B$8:$B$14,MATCH(E80,Assumptions!$A$8:$A$14,0)) -> 0.16666667 | O80: =G80*INDEX(Assumptions!$B$8:$B$14,MATCH(E80,Assumptions!$A$8:$A$14,0)) -> 0 | P80: Estimate | Q80: Sales tax time × 3 (quarterly filing). Little logged time – minimum applied. | R80: Quarterly client – average of Apr–Sep 2026 (2026-04 – 2026-09)
A81: Obsidian Real Estate LLC|1099|1099 Quarterly Review|1099 | B81: Obsidian Real Estate LLC | C81: 1099 | D81: 1099 Quarterly Review | E81: 1099 | F81: =IFERROR(INDEX('1099 Oct 30'!$H$5:$H$45,MATCH(B81,'1099 Oct 30'!$A$5:$A$45,0)),0) -> 2 | G81: 0 | H81: =F81+G81 -> 2 | I81: =ROUND(H81*60,0) -> 120 | J81: =ROUND(F81*60,0) -> 120 | K81: =ROUND(G81*60,0) -> 0 | L81: Staff | M81: =F81*IF(L81="CFO",Assumptions!$B$5,Assumptions!$B$4)+G81*Assumptions!$B$5 -> 190 | N81: =F81*INDEX(Assumptions!$B$8:$B$14,MATCH(E81,Assumptions!$A$8:$A$14,0)) -> 0.66666667 | O81: =G81*INDEX(Assumptions!$B$8:$B$14,MATCH(E81,Assumptions!$A$8:$A$14,0)) -> 0 | P81: Estimate | Q81: 1099 tier Complex: ongoing quarterly review (half a full review). See 1099 tab for the Oct 30 cycle. | R81: Settled from 2026-05 (2026-05 – 2026-09)
A82: Obsidian Real Estate LLC|Year-end review|Adjusting Journal Entry Request|Annual | B82: Obsidian Real Estate LLC | C82: Year-end review | D82: Adjusting Journal Entry Request | E82: Annual | F82: 0.5833 | G82: 0 | H82: =F82+G82 -> 0.5833 | I82: =ROUND(H82*60,0) -> 35 | J82: =ROUND(F82*60,0) -> 35 | K82: =ROUND(G82*60,0) -> 0 | L82: Staff | M82: =F82*IF(L82="CFO",Assumptions!$B$5,Assumptions!$B$4)+G82*Assumptions!$B$5 -> 55.4135 | N82: =F82*INDEX(Assumptions!$B$8:$B$14,MATCH(E82,Assumptions!$A$8:$A$14,0)) -> 0.048608333 | O82: =G82*INDEX(Assumptions!$B$8:$B$14,MATCH(E82,Assumptions!$A$8:$A$14,0)) -> 0 | P82: High | Q82: Year-end/tax hours Oct 2025–Sep 2026 (0.6h). | R82: Settled from 2026-05 (2026-05 – 2026-09)
A83: Obsidian Real Estate LLC|Monthly Financials|Month End Close|Monthly | B83: Obsidian Real Estate LLC | C83: Monthly Financials | D83: Month End Close | E83: Monthly | F83: 5.75 | G83: 0.7 | H83: =F83+G83 -> 6.45 | I83: =ROUND(H83*60,0) -> 387 | J83: =ROUND(F83*60,0) -> 345 | K83: =ROUND(G83*60,0) -> 42 | L83: Staff | M83: =F83*IF(L83="CFO",Assumptions!$B$5,Assumptions!$B$4)+G83*Assumptions!$B$5 -> 721.25 | N83: =F83*INDEX(Assumptions!$B$8:$B$14,MATCH(E83,Assumptions!$A$8:$A$14,0)) -> 5.75 | O83: =G83*INDEX(Assumptions!$B$8:$B$14,MATCH(E83,Assumptions!$A$8:$A$14,0)) -> 0.7 | P83: High | Q83: Includes Month-end 5.4, Bookkeeping 0.1, Sales tax 0.4, CFO advisory 0.1. Less 0.5h budgeted on "Monthly Reports and Bank Statements". Review = median of 7 closes reviewed in Harvest (0.70h). | R83: Settled from 2026-05 (2026-05 – 2026-09)
A84: Obsidian Real Estate LLC|Monthly Financials|Monthly Reports and Bank Statements|Monthly | B84: Obsidian Real Estate LLC | C84: Monthly Financials | D84: Monthly Reports and Bank Statements | E84: Monthly | F84: 0.5 | G84: 0 | H84: =F84+G84 -> 0.5 | I84: =ROUND(H84*60,0) -> 30 | J84: =ROUND(F84*60,0) -> 30 | K84: =ROUND(G84*60,0) -> 0 | L84: Staff | M84: =F84*IF(L84="CFO",Assumptions!$B$5,Assumptions!$B$4)+G84*Assumptions!$B$5 -> 47.5 | N84: =F84*INDEX(Assumptions!$B$8:$B$14,MATCH(E84,Assumptions!$A$8:$A$14,0)) -> 0.5 | O84: =G84*INDEX(Assumptions!$B$8:$B$14,MATCH(E84,Assumptions!$A$8:$A$14,0)) -> 0 | P84: High | Q84: Collecting monthly reports/statements (close prep). Taken out of the month-end budget. | R84: Settled from 2026-05 (2026-05 – 2026-09)
A85: Paradise Village LLC|Year-end review|Adjusting Journal Entry Request|Annual | B85: Paradise Village LLC | C85: Year-end review | D85: Adjusting Journal Entry Request | E85: Annual | F85: 0.1667 | G85: 0 | H85: =F85+G85 -> 0.1667 | I85: =ROUND(H85*60,0) -> 10 | J85: =ROUND(F85*60,0) -> 10 | K85: =ROUND(G85*60,0) -> 0 | L85: Staff | M85: =F85*IF(L85="CFO",Assumptions!$B$5,Assumptions!$B$4)+G85*Assumptions!$B$5 -> 15.8365 | N85: =F85*INDEX(Assumptions!$B$8:$B$14,MATCH(E85,Assumptions!$A$8:$A$14,0)) -> 0.013891667 | O85: =G85*INDEX(Assumptions!$B$8:$B$14,MATCH(E85,Assumptions!$A$8:$A$14,0)) -> 0 | P85: High | Q85: Year-end/tax hours Oct 2025–Sep 2026 (0.1h). | R85: Quarterly client – average of Apr–Sep 2026 (2026-04 – 2026-09)
A86: Paradise Village LLC|Accounting|Quarter End Close|Quarterly | B86: Paradise Village LLC | C86: Accounting | D86: Quarter End Close | E86: Quarterly | F86: 1 | G86: 1 | H86: =F86+G86 -> 2 | I86: =ROUND(H86*60,0) -> 120 | J86: =ROUND(F86*60,0) -> 60 | K86: =ROUND(G86*60,0) -> 60 | L86: Staff | M86: =F86*IF(L86="CFO",Assumptions!$B$5,Assumptions!$B$4)+G86*Assumptions!$B$5 -> 345 | N86: =F86*INDEX(Assumptions!$B$8:$B$14,MATCH(E86,Assumptions!$A$8:$A$14,0)) -> 0.33333333 | O86: =G86*INDEX(Assumptions!$B$8:$B$14,MATCH(E86,Assumptions!$A$8:$A$14,0)) -> 0.33333333 | P86: High | Q86: Includes Month-end 1.0. Review = 1.00h as logged (only 2 reviewed close(s) in Harvest – check). | R86: Quarterly client – average of Apr–Sep 2026 (2026-04 – 2026-09)
A87: Phil Tavasci Companies|Bookkeeping|Daily Chase Fraud Review|Daily | B87: Phil Tavasci Companies | C87: Bookkeeping | D87: Daily Chase Fraud Review | E87: Daily | F87: 0.0833 | G87: 0 | H87: =F87+G87 -> 0.0833 | I87: =ROUND(H87*60,0) -> 5 | J87: =ROUND(F87*60,0) -> 5 | K87: =ROUND(G87*60,0) -> 0 | L87: Staff | M87: =F87*IF(L87="CFO",Assumptions!$B$5,Assumptions!$B$4)+G87*Assumptions!$B$5 -> 7.9135 | N87: =F87*INDEX(Assumptions!$B$8:$B$14,MATCH(E87,Assumptions!$A$8:$A$14,0)) -> 2.5337083 | O87: =G87*INDEX(Assumptions!$B$8:$B$14,MATCH(E87,Assumptions!$A$8:$A$14,0)) -> 0 | P87: Medium | Q87: T5 history (Jul–Sep 2026): daily account/fraud checks.
A88: Phil Tavasci Companies|Bookkeeping|Bookkeeping & Bill Pay|Weekly | B88: Phil Tavasci Companies | C88: Bookkeeping | D88: Bookkeeping & Bill Pay | E88: Weekly | F88: 0.1667 | G88: 0 | H88: =F88+G88 -> 0.1667 | I88: =ROUND(H88*60,0) -> 10 | J88: =ROUND(F88*60,0) -> 10 | K88: =ROUND(G88*60,0) -> 0 | L88: Staff | M88: =F88*IF(L88="CFO",Assumptions!$B$5,Assumptions!$B$4)+G88*Assumptions!$B$5 -> 15.8365 | N88: =F88*INDEX(Assumptions!$B$8:$B$14,MATCH(E88,Assumptions!$A$8:$A$14,0)) -> 0.72236667 | O88: =G88*INDEX(Assumptions!$B$8:$B$14,MATCH(E88,Assumptions!$A$8:$A$14,0)) -> 0 | P88: Medium | Q88: T5 history (Jul–Sep 2026): group bill pay/AP.
A89: Phil Tavasci Companies|Bookkeeping|Weekly Cash Review|Weekly | B89: Phil Tavasci Companies | C89: Bookkeeping | D89: Weekly Cash Review | E89: Weekly | F89: 1.1667 | G89: 0 | H89: =F89+G89 -> 1.1667 | I89: =ROUND(H89*60,0) -> 70 | J89: =ROUND(F89*60,0) -> 70 | K89: =ROUND(G89*60,0) -> 0 | L89: Staff | M89: =F89*IF(L89="CFO",Assumptions!$B$5,Assumptions!$B$4)+G89*Assumptions!$B$5 -> 110.8365 | N89: =F89*INDEX(Assumptions!$B$8:$B$14,MATCH(E89,Assumptions!$A$8:$A$14,0)) -> 5.0557 | O89: =G89*INDEX(Assumptions!$B$8:$B$14,MATCH(E89,Assumptions!$A$8:$A$14,0)) -> 0 | P89: Medium | Q89: T5 history (Jul–Sep 2026): weekly cash review.
A90: Preferred Renovations LLC|1099|1099 Quarterly Review|1099 | B90: Preferred Renovations LLC | C90: 1099 | D90: 1099 Quarterly Review | E90: 1099 | F90: =IFERROR(INDEX('1099 Oct 30'!$H$5:$H$45,MATCH(B90,'1099 Oct 30'!$A$5:$A$45,0)),0) -> 2 | G90: 0 | H90: =F90+G90 -> 2 | I90: =ROUND(H90*60,0) -> 120 | J90: =ROUND(F90*60,0) -> 120 | K90: =ROUND(G90*60,0) -> 0 | L90: Staff | M90: =F90*IF(L90="CFO",Assumptions!$B$5,Assumptions!$B$4)+G90*Assumptions!$B$5 -> 190 | N90: =F90*INDEX(Assumptions!$B$8:$B$14,MATCH(E90,Assumptions!$A$8:$A$14,0)) -> 0.66666667 | O90: =G90*INDEX(Assumptions!$B$8:$B$14,MATCH(E90,Assumptions!$A$8:$A$14,0)) -> 0 | P90: Estimate | Q90: 1099 tier Complex: ongoing quarterly review (half a full review). See 1099 tab for the Oct 30 cycle. | R90: Settled from 2026-06 (2026-06 – 2026-09)
A91: Preferred Renovations LLC|Monthly Financials|Month End Close|Monthly | B91: Preferred Renovations LLC | C91: Monthly Financials | D91: Month End Close | E91: Monthly | F91: 1.8333 | G91: 1 | H91: =F91+G91 -> 2.8333 | I91: =ROUND(H91*60,0) -> 170 | J91: =ROUND(F91*60,0) -> 110 | K91: =ROUND(G91*60,0) -> 60 | L91: Staff | M91: =F91*IF(L91="CFO",Assumptions!$B$5,Assumptions!$B$4)+G91*Assumptions!$B$5 -> 424.1635 | N91: =F91*INDEX(Assumptions!$B$8:$B$14,MATCH(E91,Assumptions!$A$8:$A$14,0)) -> 1.8333 | O91: =G91*INDEX(Assumptions!$B$8:$B$14,MATCH(E91,Assumptions!$A$8:$A$14,0)) -> 1 | P91: High | Q91: Includes Month-end 1.3, Payroll 1.1, CFO advisory 0.1. Review = median of 5 closes reviewed in Harvest (1.00h). | R91: Settled from 2026-06 (2026-06 – 2026-09)
A92: Prestige Arms Worldwide|1099|1099 Quarterly Review|1099 | B92: Prestige Arms Worldwide | C92: 1099 | D92: 1099 Quarterly Review | E92: 1099 | F92: =IFERROR(INDEX('1099 Oct 30'!$H$5:$H$45,MATCH(B92,'1099 Oct 30'!$A$5:$A$45,0)),0) -> 0.375 | G92: 0 | H92: =F92+G92 -> 0.375 | I92: =ROUND(H92*60,0) -> 23 | J92: =ROUND(F92*60,0) -> 23 | K92: =ROUND(G92*60,0) -> 0 | L92: Staff | M92: =F92*IF(L92="CFO",Assumptions!$B$5,Assumptions!$B$4)+G92*Assumptions!$B$5 -> 35.625 | N92: =F92*INDEX(Assumptions!$B$8:$B$14,MATCH(E92,Assumptions!$A$8:$A$14,0)) -> 0.125 | O92: =G92*INDEX(Assumptions!$B$8:$B$14,MATCH(E92,Assumptions!$A$8:$A$14,0)) -> 0 | P92: Estimate | Q92: 1099 tier Simple: ongoing quarterly review (half a full review). See 1099 tab for the Oct 30 cycle. Little recent history (backlog not yet worked). Close set at 1.0h from 2025 pattern, adjusted for contractor under-recording. | R92: Settled from 2026-04 (2026-04 – 2026-09)
A93: Prestige Arms Worldwide|Default|Year-End Tax Coordination|Annual | B93: Prestige Arms Worldwide | C93: Default | D93: Year-End Tax Coordination | E93: Annual | F93: 0.3333 | G93: 0 | H93: =F93+G93 -> 0.3333 | I93: =ROUND(H93*60,0) -> 20 | J93: =ROUND(F93*60,0) -> 20 | K93: =ROUND(G93*60,0) -> 0 | L93: Staff | M93: =F93*IF(L93="CFO",Assumptions!$B$5,Assumptions!$B$4)+G93*Assumptions!$B$5 -> 31.6635 | N93: =F93*INDEX(Assumptions!$B$8:$B$14,MATCH(E93,Assumptions!$A$8:$A$14,0)) -> 0.027775 | O93: =G93*INDEX(Assumptions!$B$8:$B$14,MATCH(E93,Assumptions!$A$8:$A$14,0)) -> 0 | P93: High | Q93: Year-end/tax hours Oct 2025–Sep 2026 (0.3h). Little recent history (backlog not yet worked). Close set at 1.0h from 2025 pattern, adjusted for contractor under-recording. | R93: Settled from 2026-04 (2026-04 – 2026-09)
A94: Prestige Arms Worldwide|Monthly Financials|Month End Close|Monthly | B94: Prestige Arms Worldwide | C94: Monthly Financials | D94: Month End Close | E94: Monthly | F94: 1 | G94: 0.5 | H94: =F94+G94 -> 1.5 | I94: =ROUND(H94*60,0) -> 90 | J94: =ROUND(F94*60,0) -> 60 | K94: =ROUND(G94*60,0) -> 30 | L94: Staff | M94: =F94*IF(L94="CFO",Assumptions!$B$5,Assumptions!$B$4)+G94*Assumptions!$B$5 -> 220 | N94: =F94*INDEX(Assumptions!$B$8:$B$14,MATCH(E94,Assumptions!$A$8:$A$14,0)) -> 1 | O94: =G94*INDEX(Assumptions!$B$8:$B$14,MATCH(E94,Assumptions!$A$8:$A$14,0)) -> 0.5 | P94: Estimate | Q94: Little recent history (backlog not yet worked). Close set at 1.0h from 2025 pattern, adjusted for contractor under-recording. Review = 0.5h placeholder (no close reviews found in Harvest) – check. | R94: Settled from 2026-04 (2026-04 – 2026-09)
A95: Prestige Arms Worldwide|Sales tax|Sales Tax Filing - Onyx Prepares the Returns for Client|Monthly | B95: Prestige Arms Worldwide | C95: Sales tax | D95: Sales Tax Filing - Onyx Prepares the Returns for Client | E95: Monthly | F95: 0.25 | G95: 0 | H95: =F95+G95 -> 0.25 | I95: =ROUND(H95*60,0) -> 15 | J95: =ROUND(F95*60,0) -> 15 | K95: =ROUND(G95*60,0) -> 0 | L95: Staff | M95: =F95*IF(L95="CFO",Assumptions!$B$5,Assumptions!$B$4)+G95*Assumptions!$B$5 -> 23.75 | N95: =F95*INDEX(Assumptions!$B$8:$B$14,MATCH(E95,Assumptions!$A$8:$A$14,0)) -> 0.25 | O95: =G95*INDEX(Assumptions!$B$8:$B$14,MATCH(E95,Assumptions!$A$8:$A$14,0)) -> 0 | P95: Estimate | Q95: Sales tax time per month. Little logged time – minimum applied. Little recent history (backlog not yet worked). Close set at 1.0h from 2025 pattern, adjusted for contractor under-recording. | R95: Settled from 2026-04 (2026-04 – 2026-09)
A96: Prime Solar USA LLC|1099|1099 Quarterly Review|1099 | B96: Prime Solar USA LLC | C96: 1099 | D96: 1099 Quarterly Review | E96: 1099 | F96: =IFERROR(INDEX('1099 Oct 30'!$H$5:$H$45,MATCH(B96,'1099 Oct 30'!$A$5:$A$45,0)),0) -> 0.75 | G96: 0 | H96: =F96+G96 -> 0.75 | I96: =ROUND(H96*60,0) -> 45 | J96: =ROUND(F96*60,0) -> 45 | K96: =ROUND(G96*60,0) -> 0 | L96: Staff | M96: =F96*IF(L96="CFO",Assumptions!$B$5,Assumptions!$B$4)+G96*Assumptions!$B$5 -> 71.25 | N96: =F96*INDEX(Assumptions!$B$8:$B$14,MATCH(E96,Assumptions!$A$8:$A$14,0)) -> 0.25 | O96: =G96*INDEX(Assumptions!$B$8:$B$14,MATCH(E96,Assumptions!$A$8:$A$14,0)) -> 0 | P96: Estimate | Q96: 1099 tier Standard: ongoing quarterly review (half a full review). See 1099 tab for the Oct 30 cycle. | R96: Settled from 2026-07 (2026-07 – 2026-09)
A97: Prime Solar USA LLC|Year-end review|Adjusting Journal Entry Request|Annual | B97: Prime Solar USA LLC | C97: Year-end review | D97: Adjusting Journal Entry Request | E97: Annual | F97: 0.75 | G97: 0 | H97: =F97+G97 -> 0.75 | I97: =ROUND(H97*60,0) -> 45 | J97: =ROUND(F97*60,0) -> 45 | K97: =ROUND(G97*60,0) -> 0 | L97: CFO | M97: =F97*IF(L97="CFO",Assumptions!$B$5,Assumptions!$B$4)+G97*Assumptions!$B$5 -> 187.5 | N97: =F97*INDEX(Assumptions!$B$8:$B$14,MATCH(E97,Assumptions!$A$8:$A$14,0)) -> 0.0625 | O97: =G97*INDEX(Assumptions!$B$8:$B$14,MATCH(E97,Assumptions!$A$8:$A$14,0)) -> 0 | P97: Low – based on Valentina's hours | Q97: Year-end/tax hours Oct 2025–Sep 2026 (0.8h). | R97: Settled from 2026-07 (2026-07 – 2026-09)
A98: Prime Solar USA LLC|Monthly Financials|Month End Close|Monthly | B98: Prime Solar USA LLC | C98: Monthly Financials | D98: Month End Close | E98: Monthly | F98: 7 | G98: 1 | H98: =F98+G98 -> 8 | I98: =ROUND(H98*60,0) -> 480 | J98: =ROUND(F98*60,0) -> 420 | K98: =ROUND(G98*60,0) -> 60 | L98: CFO | M98: =F98*IF(L98="CFO",Assumptions!$B$5,Assumptions!$B$4)+G98*Assumptions!$B$5 -> 2000 | N98: =F98*INDEX(Assumptions!$B$8:$B$14,MATCH(E98,Assumptions!$A$8:$A$14,0)) -> 7 | O98: =G98*INDEX(Assumptions!$B$8:$B$14,MATCH(E98,Assumptions!$A$8:$A$14,0)) -> 1 | P98: Low – based on Valentina's hours | Q98: Includes Month-end 3.9, CFO advisory 1.3. Review = median of 7 closes reviewed in Harvest (1.00h). | R98: Settled from 2026-07 (2026-07 – 2026-09)
A99: Rancho Industrial Park Inc|1099|1099 Quarterly Review|1099 | B99: Rancho Industrial Park Inc | C99: 1099 | D99: 1099 Quarterly Review | E99: 1099 | F99: =IFERROR(INDEX('1099 Oct 30'!$H$5:$H$45,MATCH(B99,'1099 Oct 30'!$A$5:$A$45,0)),0) -> 2 | G99: 0 | H99: =F99+G99 -> 2 | I99: =ROUND(H99*60,0) -> 120 | J99: =ROUND(F99*60,0) -> 120 | K99: =ROUND(G99*60,0) -> 0 | L99: Staff | M99: =F99*IF(L99="CFO",Assumptions!$B$5,Assumptions!$B$4)+G99*Assumptions!$B$5 -> 190 | N99: =F99*INDEX(Assumptions!$B$8:$B$14,MATCH(E99,Assumptions!$A$8:$A$14,0)) -> 0.66666667 | O99: =G99*INDEX(Assumptions!$B$8:$B$14,MATCH(E99,Assumptions!$A$8:$A$14,0)) -> 0 | P99: Estimate | Q99: 1099 tier Complex: ongoing quarterly review (half a full review). See 1099 tab for the Oct 30 cycle. | R99: Not settled by rule – median of last 6 months (2026-04 – 2026-09)
A100: Rancho Industrial Park Inc|Monthly Financials|Month End Close|Monthly | B100: Rancho Industrial Park Inc | C100: Monthly Financials | D100: Month End Close | E100: Monthly | F100: 5.5 | G100: 1 | H100: =F100+G100 -> 6.5 | I100: =ROUND(H100*60,0) -> 390 | J100: =ROUND(F100*60,0) -> 330 | K100: =ROUND(G100*60,0) -> 60 | L100: Staff | M100: =F100*IF(L100="CFO",Assumptions!$B$5,Assumptions!$B$4)+G100*Assumptions!$B$5 -> 772.5 | N100: =F100*INDEX(Assumptions!$B$8:$B$14,MATCH(E100,Assumptions!$A$8:$A$14,0)) -> 5.5 | O100: =G100*INDEX(Assumptions!$B$8:$B$14,MATCH(E100,Assumptions!$A$8:$A$14,0)) -> 1 | P100: High | Q100: Includes Month-end 5.8. Review = median of 7 closes reviewed in Harvest (1.00h). | R100: Not settled by rule – median of last 6 months (2026-04 – 2026-09)
...

Sheet Open Items (Karbon)
A1: Client Name | B1: Work Title | C1: Work Type | D1: Due Date | E1: Assignee (Oct 1) | F1: Status (Oct 1) | G1: Repeats | H1: Budget source | I1: Work (hrs) | J1: CFO Review (hrs) | K1: Total (hrs) | L1: Budget (Minutes) | M1: Budget (USD) | N1: Confidence | O1: Notes | P1: Lookup key
A2: 1402 W Victory LLC | B2: Aug 2026 Month End Close | C2: Monthly Financials | D2: 46295 | E2: Lisa Danforth | F2: In Progress - Review | G2: Monthly | H2: Recurring Budgets | I2: =INDEX('Recurring Budgets'!$F$2:$F$125,MATCH(P2,'Recurring Budgets'!$A$2:$A$125,0)) -> 0.5 | J2: =INDEX('Recurring Budgets'!$G$2:$G$125,MATCH(P2,'Recurring Budgets'!$A$2:$A$125,0)) -> 0.7 | K2: =I2+J2 -> 1.2 | L2: =ROUND(K2*60,0) -> 72 | M2: =INDEX('Recurring Budgets'!$M$2:$M$125,MATCH(P2,'Recurring Budgets'!$A$2:$A$125,0)) -> 222.5 | N2: =INDEX('Recurring Budgets'!$P$2:$P$125,MATCH(P2,'Recurring Budgets'!$A$2:$A$125,0)) -> High | O2: =INDEX('Recurring Budgets'!$Q$2:$Q$125,MATCH(P2,'Recurring Budgets'!$A$2:$A$125,0)) -> Includes Month-end 0.7. Review = median of 7 closes reviewed in Harvest (0.70h). | P2: 1402 W Victory LLC|Monthly Financials|Month End Close|Monthly
A3: 1402 W Victory LLC | B3: 1099 Quarterly Review | C3: 1099 | D3: 46325 | E3: Unassigned | F3: Planned | G3: 1099 | H3: 1099 tab | I3: =INDEX('1099 Oct 30'!$F$5:$F$45,MATCH(P3,'1099 Oct 30'!$A$5:$A$45,0)) -> 2.5 | J3: 0 | K3: =I3+J3 -> 2.5 | L3: =ROUND(K3*60,0) -> 150 | M3: =I3*Assumptions!$B$4 -> 237.5 | N3: Estimate | O3: Oct 30 cycle budget from 1099 tab (covers catch-up for clients not completed in Q2). | P3: 1402 W Victory LLC
A4: 1402 W Victory LLC | B4: Sep 2026 Month End Close | C4: Monthly Financials | D4: 46325 | E4: Christine Johnson | F4: Planned | G4: Monthly | H4: Recurring Budgets | I4: =INDEX('Recurring Budgets'!$F$2:$F$125,MATCH(P4,'Recurring Budgets'!$A$2:$A$125,0)) -> 0.5 | J4: =INDEX('Recurring Budgets'!$G$2:$G$125,MATCH(P4,'Recurring Budgets'!$A$2:$A$125,0)) -> 0.7 | K4: =I4+J4 -> 1.2 | L4: =ROUND(K4*60,0) -> 72 | M4: =INDEX('Recurring Budgets'!$M$2:$M$125,MATCH(P4,'Recurring Budgets'!$A$2:$A$125,0)) -> 222.5 | N4: =INDEX('Recurring Budgets'!$P$2:$P$125,MATCH(P4,'Recurring Budgets'!$A$2:$A$125,0)) -> High | O4: =INDEX('Recurring Budgets'!$Q$2:$Q$125,MATCH(P4,'Recurring Budgets'!$A$2:$A$125,0)) -> Includes Month-end 0.7. Review = median of 7 closes reviewed in Harvest (0.70h). | P4: 1402 W Victory LLC|Monthly Financials|Month End Close|Monthly
A5: 15650 Northsight LLC | B5: Jul-Sep 2026 Quarter End Close | C5: Accounting | D5: 46303 | E5: Christine Johnson | F5: In Progress | G5: Quarterly | H5: Recurring Budgets | I5: =INDEX('Recurring Budgets'!$F$2:$F$125,MATCH(P5,'Recurring Budgets'!$A$2:$A$125,0)) -> 0.5 | J5: =INDEX('Recurring Budgets'!$G$2:$G$125,MATCH(P5,'Recurring Budgets'!$A$2:$A$125,0)) -> 1.25 | K5: =I5+J5 -> 1.75 | L5: =ROUND(K5*60,0) -> 105 | M5: =INDEX('Recurring Budgets'!$M$2:$M$125,MATCH(P5,'Recurring Budgets'!$A$2:$A$125,0)) -> 360 | N5: =INDEX('Recurring Budgets'!$P$2:$P$125,MATCH(P5,'Recurring Budgets'!$A$2:$A$125,0)) -> High | O5: =INDEX('Recurring Budgets'!$Q$2:$Q$125,MATCH(P5,'Recurring Budgets'!$A$2:$A$125,0)) -> Includes Month-end 0.5. Review = 1.25h as logged (only 2 reviewed close(s) in Harvest – check). | P5: 15650 Northsight LLC|Accounting|Quarter End Close|Quarterly
A6: 15650 Northsight LLC | B6: Quarterly Sales Tax Filing - Onyx Prepares the Returns for Client Jul - Oct 2026 | C6: Sales tax | D6: 46314 | E6: Christine Johnson | F6: Planned | G6: Quarterly | H6: Recurring Budgets | I6: =INDEX('Recurring Budgets'!$F$2:$F$125,MATCH(P6,'Recurring Budgets'!$A$2:$A$125,0)) -> 0.5 | J6: =INDEX('Recurring Budgets'!$G$2:$G$125,MATCH(P6,'Recurring Budgets'!$A$2:$A$125,0)) -> 0 | K6: =I6+J6 -> 0.5 | L6: =ROUND(K6*60,0) -> 30 | M6: =INDEX('Recurring Budgets'!$M$2:$M$125,MATCH(P6,'Recurring Budgets'!$A$2:$A$125,0)) -> 47.5 | N6: =INDEX('Recurring Budgets'!$P$2:$P$125,MATCH(P6,'Recurring Budgets'!$A$2:$A$125,0)) -> Estimate | O6: =INDEX('Recurring Budgets'!$Q$2:$Q$125,MATCH(P6,'Recurring Budgets'!$A$2:$A$125,0)) -> Sales tax time × 3 (quarterly filing). Little logged time – minimum applied. | P6: 15650 Northsight LLC|Sales tax|Quarterly Sales Tax Filing - Onyx Prepares the Returns for Client|Quarterly
A7: 15650 Northsight LLC | B7: 1099 Quarterly Review | C7: 1099 | D7: 46325 | E7: Unassigned | F7: Planned | G7: 1099 | H7: 1099 tab | I7: =INDEX('1099 Oct 30'!$F$5:$F$45,MATCH(P7,'1099 Oct 30'!$A$5:$A$45,0)) -> 2.5 | J7: 0 | K7: =I7+J7 -> 2.5 | L7: =ROUND(K7*60,0) -> 150 | M7: =I7*Assumptions!$B$4 -> 237.5 | N7: Estimate | O7: Oct 30 cycle budget from 1099 tab (covers catch-up for clients not completed in Q2). | P7: 15650 Northsight LLC
A8: 1915 NORTH 16TH STREET LLC | B8: Year-End Tax Coordination 2025 | C8: Default | D8: 46265 | E8: Steven Nikolov | F8: In Progress | G8: Annual | H8: Recurring Budgets | I8: =INDEX('Recurring Budgets'!$F$2:$F$125,MATCH(P8,'Recurring Budgets'!$A$2:$A$125,0)) -> 1 | J8: =INDEX('Recurring Budgets'!$G$2:$G$125,MATCH(P8,'Recurring Budgets'!$A$2:$A$125,0)) -> 0 | K8: =I8+J8 -> 1 | L8: =ROUND(K8*60,0) -> 60 | M8: =INDEX('Recurring Budgets'!$M$2:$M$125,MATCH(P8,'Recurring Budgets'!$A$2:$A$125,0)) -> 95 | N8: =INDEX('Recurring Budgets'!$P$2:$P$125,MATCH(P8,'Recurring Budgets'!$A$2:$A$125,0)) -> Estimate | O8: =INDEX('Recurring Budgets'!$Q$2:$Q$125,MATCH(P8,'Recurring Budgets'!$A$2:$A$125,0)) -> No year-end hours logged in the last 12 months – placeholder 1.0h. | P8: 1915 NORTH 16TH STREET LLC|Default|Year-End Tax Coordination|Annual
A9: 3540 E Boot Track LLC | B9: Aug 2026 Month End Close | C9: Monthly Financials | D9: 46295 | E9: Lisa Danforth | F9: In Progress - Review | G9: Monthly | H9: Recurring Budgets | I9: =INDEX('Recurring Budgets'!$F$2:$F$125,MATCH(P9,'Recurring Budgets'!$A$2:$A$125,0)) -> 2.25 | J9: =INDEX('Recurring Budgets'!$G$2:$G$125,MATCH(P9,'Recurring Budgets'!$A$2:$A$125,0)) -> 0.7 | K9: =I9+J9 -> 2.95 | L9: =ROUND(K9*60,0) -> 177 | M9: =INDEX('Recurring Budgets'!$M$2:$M$125,MATCH(P9,'Recurring Budgets'!$A$2:$A$125,0)) -> 388.75 | N9: =INDEX('Recurring Budgets'!$P$2:$P$125,MATCH(P9,'Recurring Budgets'!$A$2:$A$125,0)) -> High | O9: =INDEX('Recurring Budgets'!$Q$2:$Q$125,MATCH(P9,'Recurring Budgets'!$A$2:$A$125,0)) -> Includes Month-end 2.4. Review = median of 7 closes reviewed in Harvest (0.70h). | P9: 3540 E Boot Track LLC|Monthly Financials|Month End Close|Monthly
A10: 3540 E Boot Track LLC | B10: 1099 Quarterly Review | C10: 1099 | D10: 46325 | E10: Unassigned | F10: Planned | G10: 1099 | H10: 1099 tab | I10: =INDEX('1099 Oct 30'!$F$5:$F$45,MATCH(P10,'1099 Oct 30'!$A$5:$A$45,0)) -> 2.5 | J10: 0 | K10: =I10+J10 -> 2.5 | L10: =ROUND(K10*60,0) -> 150 | M10: =I10*Assumptions!$B$4 -> 237.5 | N10: Estimate | O10: Oct 30 cycle budget from 1099 tab (covers catch-up for clients not completed in Q2). | P10: 3540 E Boot Track LLC
A11: 3540 E Boot Track LLC | B11: Sep 2026 Month End Close | C11: Monthly Financials | D11: 46325 | E11: Christine Johnson | F11: Planned | G11: Monthly | H11: Recurring Budgets | I11: =INDEX('Recurring Budgets'!$F$2:$F$125,MATCH(P11,'Recurring Budgets'!$A$2:$A$125,0)) -> 2.25 | J11: =INDEX('Recurring Budgets'!$G$2:$G$125,MATCH(P11,'Recurring Budgets'!$A$2:$A$125,0)) -> 0.7 | K11: =I11+J11 -> 2.95 | L11: =ROUND(K11*60,0) -> 177 | M11: =INDEX('Recurring Budgets'!$M$2:$M$125,MATCH(P11,'Recurring Budgets'!$A$2:$A$125,0)) -> 388.75 | N11: =INDEX('Recurring Budgets'!$P$2:$P$125,MATCH(P11,'Recurring Budgets'!$A$2:$A$125,0)) -> High | O11: =INDEX('Recurring Budgets'!$Q$2:$Q$125,MATCH(P11,'Recurring Budgets'!$A$2:$A$125,0)) -> Includes Month-end 2.4. Review = median of 7 closes reviewed in Harvest (0.70h). | P11: 3540 E Boot Track LLC|Monthly Financials|Month End Close|Monthly
A12: 4530 W Flint LLC | B12: Aug 2026 Month End Close | C12: Monthly Financials | D12: 46295 | E12: Christine Johnson | F12: In Progress - Review | G12: Monthly | H12: Recurring Budgets | I12: =INDEX('Recurring Budgets'!$F$2:$F$125,MATCH(P12,'Recurring Budgets'!$A$2:$A$125,0)) -> 0.8333 | J12: =INDEX('Recurring Budgets'!$G$2:$G$125,MATCH(P12,'Recurring Budgets'!$A$2:$A$125,0)) -> 0.7 | K12: =I12+J12 -> 1.5333 | L12: =ROUND(K12*60,0) -> 92 | M12: =INDEX('Recurring Budgets'!$M$2:$M$125,MATCH(P12,'Recurring Budgets'!$A$2:$A$125,0)) -> 254.1635 | N12: =INDEX('Recurring Budgets'!$P$2:$P$125,MATCH(P12,'Recurring Budgets'!$A$2:$A$125,0)) -> High | O12: =INDEX('Recurring Budgets'!$Q$2:$Q$125,MATCH(P12,'Recurring Budgets'!$A$2:$A$125,0)) -> Includes Month-end 0.8. Review = median of 7 closes reviewed in Harvest (0.70h). | P12: 4530 W Flint LLC|Monthly Financials|Month End Close|Monthly
A13: 4530 W Flint LLC | B13: 1099 Quarterly Review | C13: 1099 | D13: 46325 | E13: Unassigned | F13: Planned | G13: 1099 | H13: 1099 tab | I13: =INDEX('1099 Oct 30'!$F$5:$F$45,MATCH(P13,'1099 Oct 30'!$A$5:$A$45,0)) -> 2.5 | J13: 0 | K13: =I13+J13 -> 2.5 | L13: =ROUND(K13*60,0) -> 150 | M13: =I13*Assumptions!$B$4 -> 237.5 | N13: Estimate | O13: Oct 30 cycle budget from 1099 tab (covers catch-up for clients not completed in Q2). | P13: 4530 W Flint LLC
A14: 7327 Tierra Buena LLC | B14: Aug 2026 Month End Close | C14: Monthly Financials | D14: 46295 | E14: Christine Johnson | F14: In Progress - Review | G14: Monthly | H14: Recurring Budgets | I14: =INDEX('Recurring Budgets'!$F$2:$F$125,MATCH(P14,'Recurring Budgets'!$A$2:$A$125,0)) -> 1.1667 | J14: =INDEX('Recurring Budgets'!$G$2:$G$125,MATCH(P14,'Recurring Budgets'!$A$2:$A$125,0)) -> 0.7 | K14: =I14+J14 -> 1.8667 | L14: =ROUND(K14*60,0) -> 112 | M14: =INDEX('Recurring Budgets'!$M$2:$M$125,MATCH(P14,'Recurring Budgets'!$A$2:$A$125,0)) -> 285.8365 | N14: =INDEX('Recurring Budgets'!$P$2:$P$125,MATCH(P14,'Recurring Budgets'!$A$2:$A$125,0)) -> High | O14: =INDEX('Recurring Budgets'!$Q$2:$Q$125,MATCH(P14,'Recurring Budgets'!$A$2:$A$125,0)) -> Includes Month-end 1.3. Review = median of 7 closes reviewed in Harvest (0.70h). | P14: 7327 Tierra Buena LLC|Monthly Financials|Month End Close|Monthly
A15: 7327 Tierra Buena LLC | B15: 1099 Quarterly Review | C15: 1099 | D15: 46325 | E15: Unassigned | F15: Planned | G15: 1099 | H15: 1099 tab | I15: =INDEX('1099 Oct 30'!$F$5:$F$45,MATCH(P15,'1099 Oct 30'!$A$5:$A$45,0)) -> 1.5 | J15: 0 | K15: =I15+J15 -> 1.5 | L15: =ROUND(K15*60,0) -> 90 | M15: =I15*Assumptions!$B$4 -> 142.5 | N15: Estimate | O15: Oct 30 cycle budget from 1099 tab (covers catch-up for clients not completed in Q2). | P15: 7327 Tierra Buena LLC
A16: 7730 Evans LLC | B16: Sep 2026 Month End Close | C16: Monthly Financials | D16: 46301 | E16: Valentina Dikova | F16: In Progress | G16: Monthly | H16: Recurring Budgets | I16: =INDEX('Recurring Budgets'!$F$2:$F$125,MATCH(P16,'Recurring Budgets'!$A$2:$A$125,0)) -> 0.75 | J16: =INDEX('Recurring Budgets'!$G$2:$G$125,MATCH(P16,'Recurring Budgets'!$A$2:$A$125,0)) -> 0.3833 | K16: =I16+J16 -> 1.1333 | L16: =ROUND(K16*60,0) -> 68 | M16: =INDEX('Recurring Budgets'!$M$2:$M$125,MATCH(P16,'Recurring Budgets'!$A$2:$A$125,0)) -> 167.075 | N16: =INDEX('Recurring Budgets'!$P$2:$P$125,MATCH(P16,'Recurring Budgets'!$A$2:$A$125,0)) -> Medium | O16: =INDEX('Recurring Budgets'!$Q$2:$Q$125,MATCH(P16,'Recurring Budgets'!$A$2:$A$125,0)) -> Josephine's Apr–May 2026 closes + allowance for a new person (Valentina's hours not used). Review = median of 8 closes reviewed in Harvest (0.38h). | P16: 7730 Evans LLC|Monthly Financials|Month End Close|Monthly
A17: 7730 Evans LLC | B17: 1099 Quarterly Review | C17: 1099 | D17: 46325 | E17: Unassigned | F17: Planned | G17: 1099 | H17: 1099 tab | I17: =INDEX('1099 Oct 30'!$F$5:$F$45,MATCH(P17,'1099 Oct 30'!$A$5:$A$45,0)) -> 0.375 | J17: 0 | K17: =I17+J17 -> 0.375 | L17: =ROUND(K17*60,0) -> 23 | M17: =I17*Assumptions!$B$4 -> 35.625 | N17: Estimate | O17: Oct 30 cycle budget from 1099 tab (covers catch-up for clients not completed in Q2). | P17: 7730 Evans LLC
A18: 909 MAIN LLC | B18: Sep 2026 Month End Close | C18: Monthly Financials | D18: 46301 | E18: Valentina Dikova | F18: In Progress | G18: Monthly | H18: Recurring Budgets | I18: =INDEX('Recurring Budgets'!$F$2:$F$125,MATCH(P18,'Recurring Budgets'!$A$2:$A$125,0)) -> 1.25 | J18: =INDEX('Recurring Budgets'!$G$2:$G$125,MATCH(P18,'Recurring Budgets'!$A$2:$A$125,0)) -> 0.4833 | K18: =I18+J18 -> 1.7333 | L18: =ROUND(K18*60,0) -> 104 | M18: =INDEX('Recurring Budgets'!$M$2:$M$125,MATCH(P18,'Recurring Budgets'!$A$2:$A$125,0)) -> 239.575 | N18: =INDEX('Recurring Budgets'!$P$2:$P$125,MATCH(P18,'Recurring Budgets'!$A$2:$A$125,0)) -> Provisional | O18: =INDEX('Recurring Budgets'!$Q$2:$Q$125,MATCH(P18,'Recurring Budgets'!$A$2:$A$125,0)) -> Josephine's Apr–May 2026 closes + allowance for a new person (Valentina's hours not used). Will become an Airbnb – provisional. Revisit once it converts. Review = median of 8 closes reviewed in Harvest (0.48h). | P18: 909 MAIN LLC|Monthly Financials|Month End Close|Monthly
A19: 909 MAIN LLC | B19: 1099 Quarterly Review | C19: 1099 | D19: 46325 | E19: Unassigned | F19: Planned | G19: 1099 | H19: 1099 tab | I19: =INDEX('1099 Oct 30'!$F$5:$F$45,MATCH(P19,'1099 Oct 30'!$A$5:$A$45,0)) -> 0.375 | J19: 0 | K19: =I19+J19 -> 0.375 | L19: =ROUND(K19*60,0) -> 23 | M19: =I19*Assumptions!$B$4 -> 35.625 | N19: Estimate | O19: Oct 30 cycle budget from 1099 tab (covers catch-up for clients not completed in Q2). | P19: 909 MAIN LLC
A20: Amerisource HR Consulting Group LLC | B20: Aug 2026 Month End Close | C20: Monthly Financials | D20: 46275 | E20: Steven Nikolov | F20: In Progress | G20: Monthly | H20: Recurring Budgets | I20: =INDEX('Recurring Budgets'!$F$2:$F$125,MATCH(P20,'Recurring Budgets'!$A$2:$A$125,0)) -> 16.1667 | J20: =INDEX('Recurring Budgets'!$G$2:$G$125,MATCH(P20,'Recurring Budgets'!$A$2:$A$125,0)) -> 1 | K20: =I20+J20 -> 17.1667 | L20: =ROUND(K20*60,0) -> 1030 | M20: =INDEX('Recurring Budgets'!$M$2:$M$125,MATCH(P20,'Recurring Budgets'!$A$2:$A$125,0)) -> 1785.8365 | N20: =INDEX('Recurring Budgets'!$P$2:$P$125,MATCH(P20,'Recurring Budgets'!$A$2:$A$125,0)) -> High | O20: =INDEX('Recurring Budgets'!$Q$2:$Q$125,MATCH(P20,'Recurring Budgets'!$A$2:$A$125,0)) -> Includes Month-end 5.0, Payroll 11.7, CFO advisory 0.2. Review = median of 4 closes reviewed in Harvest (1.00h). | P20: Amerisource HR Consulting Group LLC|Monthly Financials|Month End Close|Monthly
A21: Amerisource HR Consulting Group LLC | B21: Bookkeeping & Bill Pay Oct 2, 2026 | C21: Bookkeeping | D21: 46297 | E21: Christine Johnson | F21: Planned | G21: Weekly | H21: Recurring Budgets | I21: =INDEX('Recurring Budgets'!$F$2:$F$125,MATCH(P21,'Recurring Budgets'!$A$2:$A$125,0)) -> 1.8333 | J21: =INDEX('Recurring Budgets'!$G$2:$G$125,MATCH(P21,'Recurring Budgets'!$A$2:$A$125,0)) -> 0 | K21: =I21+J21 -> 1.8333 | L21: =ROUND(K21*60,0) -> 110 | M21: =INDEX('Recurring Budgets'!$M$2:$M$125,MATCH(P21,'Recurring Budgets'!$A$2:$A$125,0)) -> 174.1635 | N21: =INDEX('Recurring Budgets'!$P$2:$P$125,MATCH(P21,'Recurring Budgets'!$A$2:$A$125,0)) -> High | O21: =INDEX('Recurring Budgets'!$Q$2:$Q$125,MATCH(P21,'Recurring Budgets'!$A$2:$A$125,0)) -> Weekly bookkeeping/settlement time ÷ weeks per month. | P21: Amerisource HR Consulting Group LLC|Bookkeeping|Bookkeeping & Bill Pay|Weekly
A22: Amerisource HR Consulting Group LLC | B22: Sep 2026 Month End Close | C22: Monthly Financials | D22: 46304 | E22: Valentina Dikova | F22: In Progress | G22: Monthly | H22: Recurring Budgets | I22: =INDEX('Recurring Budgets'!$F$2:$F$125,MATCH(P22,'Recurring Budgets'!$A$2:$A$125,0)) -> 16.1667 | J22: =INDEX('Recurring Budgets'!$G$2:$G$125,MATCH(P22,'Recurring Budgets'!$A$2:$A$125,0)) -> 1 | K22: =I22+J22 -> 17.1667 | L22: =ROUND(K22*60,0) -> 1030 | M22: =INDEX('Recurring Budgets'!$M$2:$M$125,MATCH(P22,'Recurring Budgets'!$A$2:$A$125,0)) -> 1785.8365 | N22: =INDEX('Recurring Budgets'!$P$2:$P$125,MATCH(P22,'Recurring Budgets'!$A$2:$A$125,0)) -> High | O22: =INDEX('Recurring Budgets'!$Q$2:$Q$125,MATCH(P22,'Recurring Budgets'!$A$2:$A$125,0)) -> Includes Month-end 5.0, Payroll 11.7, CFO advisory 0.2. Review = median of 4 closes reviewed in Harvest (1.00h). | P22: Amerisource HR Consulting Group LLC|Monthly Financials|Month End Close|Monthly
A23: Amerisource HR Consulting Group LLC | B23: 1099 Quarterly Review | C23: 1099 | D23: 46325 | E23: Unassigned | F23: Planned | G23: 1099 | H23: 1099 tab | I23: =INDEX('1099 Oct 30'!$F$5:$F$45,MATCH(P23,'1099 Oct 30'!$A$5:$A$45,0)) -> 0.75 | J23: 0 | K23: =I23+J23 -> 0.75 | L23: =ROUND(K23*60,0) -> 45 | M23: =I23*Assumptions!$B$4 -> 71.25 | N23: Estimate | O23: Oct 30 cycle budget from 1099 tab (covers catch-up for clients not completed in Q2). | P23: Amerisource HR Consulting Group LLC
A24: Amerisource HR Consulting Group LLC | B24: Adjusting Journal Entry Request 2025 | C24: Year-end review | D24: 46325 | E24: Christine Johnson | F24: In Progress - Review | G24: Annual | H24: Recurring Budgets | I24: =INDEX('Recurring Budgets'!$F$2:$F$125,MATCH(P24,'Recurring Budgets'!$A$2:$A$125,0)) -> 5.6667 | J24: =INDEX('Recurring Budgets'!$G$2:$G$125,MATCH(P24,'Recurring Budgets'!$A$2:$A$125,0)) -> 0 | K24: =I24+J24 -> 5.6667 | L24: =ROUND(K24*60,0) -> 340 | M24: =INDEX('Recurring Budgets'!$M$2:$M$125,MATCH(P24,'Recurring Budgets'!$A$2:$A$125,0)) -> 538.3365 | N24: =INDEX('Recurring Budgets'!$P$2:$P$125,MATCH(P24,'Recurring Budgets'!$A$2:$A$125,0)) -> High | O24: =INDEX('Recurring Budgets'!$Q$2:$Q$125,MATCH(P24,'Recurring Budgets'!$A$2:$A$125,0)) -> Year-end/tax hours Oct 2025–Sep 2026 (5.6h). | P24: Amerisource HR Consulting Group LLC|Year-end review|Adjusting Journal Entry Request|Annual
A25: BSD Contracting LLC | B25: Aug 2026 Month End Close | C25: Monthly Financials | D25: 46281 | E25: Christine Johnson | F25: In Progress - Review | G25: Monthly | H25: Recurring Budgets | I25: =INDEX('Recurring Budgets'!$F$2:$F$125,MATCH(P25,'Recurring Budgets'!$A$2:$A$125,0)) -> 0.75 | J25: =INDEX('Recurring Budgets'!$G$2:$G$125,MATCH(P25,'Recurring Budgets'!$A$2:$A$125,0)) -> 0.5 | K25: =I25+J25 -> 1.25 | L25: =ROUND(K25*60,0) -> 75 | M25: =INDEX('Recurring Budgets'!$M$2:$M$125,MATCH(P25,'Recurring Budgets'!$A$2:$A$125,0)) -> 196.25 | N25: =INDEX('Recurring Budgets'!$P$2:$P$125,MATCH(P25,'Recurring Budgets'!$A$2:$A$125,0)) -> High | O25: =INDEX('Recurring Budgets'!$Q$2:$Q$125,MATCH(P25,'Recurring Budgets'!$A$2:$A$125,0)) -> Includes Month-end 0.7, Payroll 0.4. Review = median of 4 closes reviewed in Harvest (0.50h). | P25: BSD Contracting LLC|Monthly Financials|Month End Close|Monthly
A26: BSD Contracting LLC | B26: Sep 2026 Month End Close | C26: Monthly Financials | D26: 46311 | E26: Christine Johnson | F26: In Progress | G26: Monthly | H26: Recurring Budgets | I26: =INDEX('Recurring Budgets'!$F$2:$F$125,MATCH(P26,'Recurring Budgets'!$A$2:$A$125,0)) -> 0.75 | J26: =INDEX('Recurring Budgets'!$G$2:$G$125,MATCH(P26,'Recurring Budgets'!$A$2:$A$125,0)) -> 0.5 | K26: =I26+J26 -> 1.25 | L26: =ROUND(K26*60,0) -> 75 | M26: =INDEX('Recurring Budgets'!$M$2:$M$125,MATCH(P26,'Recurring Budgets'!$A$2:$A$125,0)) -> 196.25 | N26: =INDEX('Recurring Budgets'!$P$2:$P$125,MATCH(P26,'Recurring Budgets'!$A$2:$A$125,0)) -> High | O26: =INDEX('Recurring Budgets'!$Q$2:$Q$125,MATCH(P26,'Recurring Budgets'!$A$2:$A$125,0)) -> Includes Month-end 0.7, Payroll 0.4. Review = median of 4 closes reviewed in Harvest (0.50h). | P26: BSD Contracting LLC|Monthly Financials|Month End Close|Monthly
A27: BSD Contracting LLC | B27: 1099 Quarterly Review | C27: 1099 | D27: 46325 | E27: Unassigned | F27: Planned | G27: 1099 | H27: 1099 tab | I27: =INDEX('1099 Oct 30'!$F$5:$F$45,MATCH(P27,'1099 Oct 30'!$A$5:$A$45,0)) -> 2 | J27: 0 | K27: =I27+J27 -> 2 | L27: =ROUND(K27*60,0) -> 120 | M27: =I27*Assumptions!$B$4 -> 190 | N27: Estimate | O27: Oct 30 cycle budget from 1099 tab (covers catch-up for clients not completed in Q2). | P27: BSD Contracting LLC
A28: Barrett Living Trust | B28: Aug 2026 Month End Close | C28: Accounting | D28: 46295 | E28: Christine Johnson | F28: In Progress | G28: Monthly | H28: Recurring Budgets | I28: =INDEX('Recurring Budgets'!$F$2:$F$125,MATCH(P28,'Recurring Budgets'!$A$2:$A$125,0)) -> 2.8333 | J28: =INDEX('Recurring Budgets'!$G$2:$G$125,MATCH(P28,'Recurring Budgets'!$A$2:$A$125,0)) -> 1.1 | K28: =I28+J28 -> 3.9333 | L28: =ROUND(K28*60,0) -> 236 | M28: =INDEX('Recurring Budgets'!$M$2:$M$125,MATCH(P28,'Recurring Budgets'!$A$2:$A$125,0)) -> 544.1635 | N28: =INDEX('Recurring Budgets'!$P$2:$P$125,MATCH(P28,'Recurring Budgets'!$A$2:$A$125,0)) -> High | O28: =INDEX('Recurring Budgets'!$Q$2:$Q$125,MATCH(P28,'Recurring Budgets'!$A$2:$A$125,0)) -> Includes Month-end 2.6, Bookkeeping 0.9. Review = 1.10h as logged (only 2 reviewed close(s) in Harvest – check). | P28: Barrett Living Trust|Accounting|Month End Close|Monthly
A29: Barrett Living Trust | B29: Adjusting Journal Entry Request 2025 | C29: Year-end review | D29: 46325 | E29: Christine Johnson | F29: In Progress - Review | G29: Annual | H29: Recurring Budgets | I29: =INDEX('Recurring Budgets'!$F$2:$F$125,MATCH(P29,'Recurring Budgets'!$A$2:$A$125,0)) -> 0.5 | J29: =INDEX('Recurring Budgets'!$G$2:$G$125,MATCH(P29,'Recurring Budgets'!$A$2:$A$125,0)) -> 0 | K29: =I29+J29 -> 0.5 | L29: =ROUND(K29*60,0) -> 30 | M29: =INDEX('Recurring Budgets'!$M$2:$M$125,MATCH(P29,'Recurring Budgets'!$A$2:$A$125,0)) -> 47.5 | N29: =INDEX('Recurring Budgets'!$P$2:$P$125,MATCH(P29,'Recurring Budgets'!$A$2:$A$125,0)) -> High | O29: =INDEX('Recurring Budgets'!$Q$2:$Q$125,MATCH(P29,'Recurring Budgets'!$A$2:$A$125,0)) -> Year-end/tax hours Oct 2025–Sep 2026 (0.5h). | P29: Barrett Living Trust|Year-end review|Adjusting Journal Entry Request|Annual
A30: BeckShar Companies | B30: Clean up Project - Review Scope of Work | C30: Ad hoc | D30: 46291 | E30: Jessica Bumphus | F30: Ready To Start | G30: One-time | H30: One-time estimate | I30: 2.5 | J30: 0 | K30: =I30+J30 -> 2.5 | L30: =ROUND(K30*60,0) -> 150 | M30: =I30*Assumptions!$B$4+J30*Assumptions!$B$5 -> 237.5 | N30: Estimate | O30: Size: Small. Scoping only; catalog Small (2–3h). Budget the cleanup itself once scoped.
A31: BeckShar Development LLC | B31: Aug 2026 Month End Close | C31: Monthly Financials | D31: 46282 | E31: Christine Johnson | F31: In Progress - Review | G31: Monthly | H31: Recurring Budgets | I31: =INDEX('Recurring Budgets'!$F$2:$F$125,MATCH(P31,'Recurring Budgets'!$A$2:$A$125,0)) -> 6.9167 | J31: =INDEX('Recurring Budgets'!$G$2:$G$125,MATCH(P31,'Recurring Budgets'!$A$2:$A$125,0)) -> 0.8 | K31: =I31+J31 -> 7.7167 | L31: =ROUND(K31*60,0) -> 463 | M31: =INDEX('Recurring Budgets'!$M$2:$M$125,MATCH(P31,'Recurring Budgets'!$A$2:$A$125,0)) -> 857.0865 | N31: =INDEX('Recurring Budgets'!$P$2:$P$125,MATCH(P31,'Recurring Budgets'!$A$2:$A$125,0)) -> High | O31: =INDEX('Recurring Budgets'!$Q$2:$Q$125,MATCH(P31,'Recurring Budgets'!$A$2:$A$125,0)) -> Includes Month-end 2.5, Bookkeeping 0.2, Payroll 1.6, CFO advisory 2.1. Review = median of 6 closes reviewed in Harvest (0.80h). | P31: BeckShar Development LLC|Monthly Financials|Month End Close|Monthly
A32: BeckShar Development LLC | B32: Sep 2026 Month End Close | C32: Monthly Financials | D32: 46304 | E32: Christine Johnson | F32: In Progress | G32: Monthly | H32: Recurring Budgets | I32: =INDEX('Recurring Budgets'!$F$2:$F$125,MATCH(P32,'Recurring Budgets'!$A$2:$A$125,0)) -> 6.9167 | J32: =INDEX('Recurring Budgets'!$G$2:$G$125,MATCH(P32,'Recurring Budgets'!$A$2:$A$125,0)) -> 0.8 | K32: =I32+J32 -> 7.7167 | L32: =ROUND(K32*60,0) -> 463 | M32: =INDEX('Recurring Budgets'!$M$2:$M$125,MATCH(P32,'Recurring Budgets'!$A$2:$A$125,0)) -> 857.0865 | N32: =INDEX('Recurring Budgets'!$P$2:$P$125,MATCH(P32,'Recurring Budgets'!$A$2:$A$125,0)) -> High | O32: =INDEX('Recurring Budgets'!$Q$2:$Q$125,MATCH(P32,'Recurring Budgets'!$A$2:$A$125,0)) -> Includes Month-end 2.5, Bookkeeping 0.2, Payroll 1.6, CFO advisory 2.1. Review = median of 6 closes reviewed in Harvest (0.80h). | P32: BeckShar Development LLC|Monthly Financials|Month End Close|Monthly
A33: BeckShar Development LLC | B33: 1099 Quarterly Review | C33: 1099 | D33: 46325 | E33: Unassigned | F33: Planned | G33: 1099 | H33: 1099 tab | I33: =INDEX('1099 Oct 30'!$F$5:$F$45,MATCH(P33,'1099 Oct 30'!$A$5:$A$45,0)) -> 0.75 | J33: 0 | K33: =I33+J33 -> 0.75 | L33: =ROUND(K33*60,0) -> 45 | M33: =I33*Assumptions!$B$4 -> 71.25 | N33: Estimate | O33: Oct 30 cycle budget from 1099 tab (covers catch-up for clients not completed in Q2). | P33: BeckShar Development LLC
A34: BeckShar Diamond Commercial LLC | B34: Aug 2026 Month End Close | C34: Monthly Financials | D34: 46276 | E34: Christine Johnson | F34: In Progress | G34: Monthly | H34: Recurring Budgets | I34: =INDEX('Recurring Budgets'!$F$2:$F$125,MATCH(P34,'Recurring Budgets'!$A$2:$A$125,0)) -> 0.4167 | J34: =INDEX('Recurring Budgets'!$G$2:$G$125,MATCH(P34,'Recurring Budgets'!$A$2:$A$125,0)) -> 0.5 | K34: =I34+J34 -> 0.9167 | L34: =ROUND(K34*60,0) -> 55 | M34: =INDEX('Recurring Budgets'!$M$2:$M$125,MATCH(P34,'Recurring Budgets'!$A$2:$A$125,0)) -> 164.5865 | N34: =INDEX('Recurring Budgets'!$P$2:$P$125,MATCH(P34,'Recurring Budgets'!$A$2:$A$125,0)) -> High | O34: =INDEX('Recurring Budgets'!$Q$2:$Q$125,MATCH(P34,'Recurring Budgets'!$A$2:$A$125,0)) -> Includes Month-end 0.7. Review = median of 4 closes reviewed in Harvest (0.50h). | P34: BeckShar Diamond Commercial LLC|Monthly Financials|Month End Close|Monthly
A35: BeckShar Diamond Commercial LLC | B35: Sep 2026 Month End Close | C35: Monthly Financials | D35: 46307 | E35: Christine Johnson | F35: In Progress | G35: Monthly | H35: Recurring Budgets | I35: =INDEX('Recurring Budgets'!$F$2:$F$125,MATCH(P35,'Recurring Budgets'!$A$2:$A$125,0)) -> 0.4167 | J35: =INDEX('Recurring Budgets'!$G$2:$G$125,MATCH(P35,'Recurring Budgets'!$A$2:$A$125,0)) -> 0.5 | K35: =I35+J35 -> 0.9167 | L35: =ROUND(K35*60,0) -> 55 | M35: =INDEX('Recurring Budgets'!$M$2:$M$125,MATCH(P35,'Recurring Budgets'!$A$2:$A$125,0)) -> 164.5865 | N35: =INDEX('Recurring Budgets'!$P$2:$P$125,MATCH(P35,'Recurring Budgets'!$A$2:$A$125,0)) -> High | O35: =INDEX('Recurring Budgets'!$Q$2:$Q$125,MATCH(P35,'Recurring Budgets'!$A$2:$A$125,0)) -> Includes Month-end 0.7. Review = median of 4 closes reviewed in Harvest (0.50h). | P35: BeckShar Diamond Commercial LLC|Monthly Financials|Month End Close|Monthly
A36: BeckShar Diamond Commercial LLC | B36: 1099 Quarterly Review | C36: 1099 | D36: 46325 | E36: Unassigned | F36: Planned | G36: 1099 | H36: 1099 tab | I36: =INDEX('1099 Oct 30'!$F$5:$F$45,MATCH(P36,'1099 Oct 30'!$A$5:$A$45,0)) -> 0.75 | J36: 0 | K36: =I36+J36 -> 0.75 | L36: =ROUND(K36*60,0) -> 45 | M36: =I36*Assumptions!$B$4 -> 71.25 | N36: Estimate | O36: Oct 30 cycle budget from 1099 tab (covers catch-up for clients not completed in Q2). | P36: BeckShar Diamond Commercial LLC
A37: BeckShar LLC | B37: Aug 2026 Month End Close | C37: Monthly Financials | D37: 46275 | E37: Steven Nikolov | F37: In Progress - Review | G37: Monthly | H37: Recurring Budgets | I37: =INDEX('Recurring Budgets'!$F$2:$F$125,MATCH(P37,'Recurring Budgets'!$A$2:$A$125,0)) -> 2.9167 | J37: =INDEX('Recurring Budgets'!$G$2:$G$125,MATCH(P37,'Recurring Budgets'!$A$2:$A$125,0)) -> 1.25 | K37: =I37+J37 -> 4.1667 | L37: =ROUND(K37*60,0) -> 250 | M37: =INDEX('Recurring Budgets'!$M$2:$M$125,MATCH(P37,'Recurring Budgets'!$A$2:$A$125,0)) -> 589.5865 | N37: =INDEX('Recurring Budgets'!$P$2:$P$125,MATCH(P37,'Recurring Budgets'!$A$2:$A$125,0)) -> High | O37: =INDEX('Recurring Budgets'!$Q$2:$Q$125,MATCH(P37,'Recurring Budgets'!$A$2:$A$125,0)) -> Includes Month-end 1.2, Bookkeeping 0.5, Payroll 1.3, Sales tax 0.8. Review = 1.25h as logged (only 2 reviewed close(s) in Harvest – check). | P37: BeckShar LLC|Monthly Financials|Month End Close|Monthly
A38: BeckShar LLC | B38: Sep 2026 Month End Close | C38: Monthly Financials | D38: 46304 | E38: Christine Johnson | F38: In Progress | G38: Monthly | H38: Recurring Budgets | I38: =INDEX('Recurring Budgets'!$F$2:$F$125,MATCH(P38,'Recurring Budgets'!$A$2:$A$125,0)) -> 2.9167 | J38: =INDEX('Recurring Budgets'!$G$2:$G$125,MATCH(P38,'Recurring Budgets'!$A$2:$A$125,0)) -> 1.25 | K38: =I38+J38 -> 4.1667 | L38: =ROUND(K38*60,0) -> 250 | M38: =INDEX('Recurring Budgets'!$M$2:$M$125,MATCH(P38,'Recurring Budgets'!$A$2:$A$125,0)) -> 589.5865 | N38: =INDEX('Recurring Budgets'!$P$2:$P$125,MATCH(P38,'Recurring Budgets'!$A$2:$A$125,0)) -> High | O38: =INDEX('Recurring Budgets'!$Q$2:$Q$125,MATCH(P38,'Recurring Budgets'!$A$2:$A$125,0)) -> Includes Month-end 1.2, Bookkeeping 0.5, Payroll 1.3, Sales tax 0.8. Review = 1.25h as logged (only 2 reviewed close(s) in Harvest – check). | P38: BeckShar LLC|Monthly Financials|Month End Close|Monthly
A39: BeckShar LLC | B39: 1099 Quarterly Review | C39: 1099 | D39: 46325 | E39: Unassigned | F39: Planned | G39: 1099 | H39: 1099 tab | I39: =INDEX('1099 Oct 30'!$F$5:$F$45,MATCH(P39,'1099 Oct 30'!$A$5:$A$45,0)) -> 2 | J39: 0 | K39: =I39+J39 -> 2 | L39: =ROUND(K39*60,0) -> 120 | M39: =I39*Assumptions!$B$4 -> 190 | N39: Estimate | O39: Oct 30 cycle budget from 1099 tab (covers catch-up for clients not completed in Q2). | P39: BeckShar LLC
A40: Bjerk Builders LLC | B40: Client Check-in Sep 13, 2026 | C40: Default | D40: 46297 | E40: Lisa Danforth | F40: In Progress | G40: One-time | H40: One-time estimate | I40: 0.5 | J40: 0 | K40: =I40+J40 -> 0.5 | L40: =ROUND(K40*60,0) -> 30 | M40: =I40*Assumptions!$B$4+J40*Assumptions!$B$5 -> 47.5 | N40: Estimate | O40: Size: Quick. No Bjerk time logged since Jan 2026 – confirm whether still active.
A41: Bjerk Builders LLC | B41: Client Check-in Sep 28, 2026 | C41: Default | D41: 46297 | E41: Lisa Danforth | F41: Ready To Start | G41: One-time | H41: One-time estimate | I41: 0.5 | J41: 0 | K41: =I41+J41 -> 0.5 | L41: =ROUND(K41*60,0) -> 30 | M41: =I41*Assumptions!$B$4+J41*Assumptions!$B$5 -> 47.5 | N41: Estimate | O41: Size: Quick. No Bjerk time logged since Jan 2026 – confirm whether still active.
A42: Building and Development Professionals LLC | B42: 2025 Clean up - Create WIP | C42: Ad hoc | D42: 46295 | E42: Lisa Danforth | F42: In Progress | G42: One-time | H42: One-time estimate | I42: 10 | J42: 0 | K42: =I42+J42 -> 10 | L42: =ROUND(K42*60,0) -> 600 | M42: =I42*Assumptions!$B$4+J42*Assumptions!$B$5 -> 950 | N42: Estimate | O42: Size: Large. WIP build for a contractor; BDP cleanup/CFO time so far ~4–16h/mo. Estimate – confirm scope.
A43: Building and Development Professionals LLC | B43: Month End Close | C43: Monthly Financials | D43: 46304 | E43: Lisa Danforth | F43: In Progress | G43: Monthly | H43: Recurring Budgets | I43: =INDEX('Recurring Budgets'!$F$2:$F$125,MATCH(P43,'Recurring Budgets'!$A$2:$A$125,0)) -> 2.75 | J43: =INDEX('Recurring Budgets'!$G$2:$G$125,MATCH(P43,'Recurring Budgets'!$A$2:$A$125,0)) -> 0.5 | K43: =I43+J43 -> 3.25 | L43: =ROUND(K43*60,0) -> 195 | M43: =INDEX('Recurring Budgets'!$M$2:$M$125,MATCH(P43,'Recurring Budgets'!$A$2:$A$125,0)) -> 812.5 | N43: =INDEX('Recurring Budgets'!$P$2:$P$125,MATCH(P43,'Recurring Budgets'!$A$2:$A$125,0)) -> High | O43: =INDEX('Recurring Budgets'!$Q$2:$Q$125,MATCH(P43,'Recurring Budgets'!$A$2:$A$125,0)) -> Includes Month-end 0.5, CFO advisory 1.9. Review = 0.5h placeholder (no close reviews found in Harvest) – check. | P43: Building and Development Professionals LLC|Monthly Financials|Month End Close|Monthly
A44: Building and Development Professionals LLC | B44: 1099 Quarterly Review | C44: 1099 | D44: 46325 | E44: Unassigned | F44: Planned | G44: 1099 | H44: 1099 tab | I44: =INDEX('1099 Oct 30'!$F$5:$F$45,MATCH(P44,'1099 Oct 30'!$A$5:$A$45,0)) -> 4 | J44: 0 | K44: =I44+J44 -> 4 | L44: =ROUND(K44*60,0) -> 240 | M44: =I44*Assumptions!$B$4 -> 380 | N44: Estimate | O44: Oct 30 cycle budget from 1099 tab (covers catch-up for clients not completed in Q2). | P44: Building and Development Professionals LLC
A45: Capital Financial LLC | B45: 2026 Budget Fix | C45: Ad hoc | D45: 46288 | E45: Christine Johnson | F45: Waiting - Waiting for info | G45: One-time | H45: One-time estimate | I45: 5.5 | J45: 0 | K45: =I45+J45 -> 5.5 | L45: =ROUND(K45*60,0) -> 330 | M45: =I45*Assumptions!$B$4+J45*Assumptions!$B$5 -> 522.5 | N45: Estimate | O45: Size: Medium. Catalog Medium (5–6h): budget build/fix.
A46: Capital Financial LLC | B46: Sep 2026 Month End Close | C46: Monthly Financials | D46: 46308 | E46: Christine Johnson | F46: In Progress | G46: Monthly | H46: Recurring Budgets | I46: =INDEX('Recurring Budgets'!$F$2:$F$125,MATCH(P46,'Recurring Budgets'!$A$2:$A$125,0)) -> 7.6667 | J46: =INDEX('Recurring Budgets'!$G$2:$G$125,MATCH(P46,'Recurring Budgets'!$A$2:$A$125,0)) -> 1.2 | K46: =I46+J46 -> 8.8667 | L46: =ROUND(K46*60,0) -> 532 | M46: =INDEX('Recurring Budgets'!$M$2:$M$125,MATCH(P46,'Recurring Budgets'!$A$2:$A$125,0)) -> 1028.3365 | N46: =INDEX('Recurring Budgets'!$P$2:$P$125,MATCH(P46,'Recurring Budgets'!$A$2:$A$125,0)) -> High | O46: =INDEX('Recurring Budgets'!$Q$2:$Q$125,MATCH(P46,'Recurring Budgets'!$A$2:$A$125,0)) -> Includes Month-end 3.4, Bookkeeping 0.7, Payroll 2.7, CFO advisory 0.3. Aug–Sep 2026 excluded (one-time payroll JE re-entry, resolved). Review = median of 3 closes reviewed in Harvest (1.20h). | P46: Capital Financial LLC|Monthly Financials|Month End Close|Monthly
A47: Capital Financial LLC | B47: 1099 Quarterly Review | C47: 1099 | D47: 46325 | E47: Unassigned | F47: Planned | G47: 1099 | H47: 1099 tab | I47: =INDEX('1099 Oct 30'!$F$5:$F$45,MATCH(P47,'1099 Oct 30'!$A$5:$A$45,0)) -> 0.75 | J47: 0 | K47: =I47+J47 -> 0.75 | L47: =ROUND(K47*60,0) -> 45 | M47: =I47*Assumptions!$B$4 -> 71.25 | N47: Estimate | O47: Oct 30 cycle budget from 1099 tab (covers catch-up for clients not completed in Q2). | P47: Capital Financial LLC
A48: Catalpa Industrial Park Inc | B48: Aug 2026 Month End Close | C48: Monthly Financials | D48: 46295 | E48: Christine Johnson | F48: In Progress | G48: Monthly | H48: Recurring Budgets | I48: =INDEX('Recurring Budgets'!$F$2:$F$125,MATCH(P48,'Recurring Budgets'!$A$2:$A$125,0)) -> 4.4167 | J48: =INDEX('Recurring Budgets'!$G$2:$G$125,MATCH(P48,'Recurring Budgets'!$A$2:$A$125,0)) -> 0.7 | K48: =I48+J48 -> 5.1167 | L48: =ROUND(K48*60,0) -> 307 | M48: =INDEX('Recurring Budgets'!$M$2:$M$125,MATCH(P48,'Recurring Budgets'!$A$2:$A$125,0)) -> 594.5865 | N48: =INDEX('Recurring Budgets'!$P$2:$P$125,MATCH(P48,'Recurring Budgets'!$A$2:$A$125,0)) -> High | O48: =INDEX('Recurring Budgets'!$Q$2:$Q$125,MATCH(P48,'Recurring Budgets'!$A$2:$A$125,0)) -> Includes Month-end 4.7. Review = median of 6 closes reviewed in Harvest (0.70h). | P48: Catalpa Industrial Park Inc|Monthly Financials|Month End Close|Monthly
A49: Catalpa Industrial Park Inc | B49: 1099 Quarterly Review | C49: 1099 | D49: 46325 | E49: Unassigned | F49: Planned | G49: 1099 | H49: 1099 tab | I49: =INDEX('1099 Oct 30'!$F$5:$F$45,MATCH(P49,'1099 Oct 30'!$A$5:$A$45,0)) -> 4 | J49: 0 | K49: =I49+J49 -> 4 | L49: =ROUND(K49*60,0) -> 240 | M49: =I49*Assumptions!$B$4 -> 380 | N49: Estimate | O49: Oct 30 cycle budget from 1099 tab (covers catch-up for clients not completed in Q2). | P49: Catalpa Industrial Park Inc
A50: Desert Quail Creative Classroom LLC | B50: Sep 2026 Month End Close | C50: Monthly Financials | D50: 46302 | E50: Valentina Dikova | F50: Planned | G50: Monthly | H50: Recurring Budgets | I50: =INDEX('Recurring Budgets'!$F$2:$F$125,MATCH(P50,'Recurring Budgets'!$A$2:$A$125,0)) -> 0.75 | J50: =INDEX('Recurring Budgets'!$G$2:$G$125,MATCH(P50,'Recurring Budgets'!$A$2:$A$125,0)) -> 0.5 | K50: =I50+J50 -> 1.25 | L50: =ROUND(K50*60,0) -> 75 | M50: =INDEX('Recurring Budgets'!$M$2:$M$125,MATCH(P50,'Recurring Budgets'!$A$2:$A$125,0)) -> 196.25 | N50: =INDEX('Recurring Budgets'!$P$2:$P$125,MATCH(P50,'Recurring Budgets'!$A$2:$A$125,0)) -> Medium | O50: =INDEX('Recurring Budgets'!$Q$2:$Q$125,MATCH(P50,'Recurring Budgets'!$A$2:$A$125,0)) -> Josephine's Apr–May 2026 closes + allowance for a new person (Valentina's hours not used). Review = median of 7 closes reviewed in Harvest (0.50h). | P50: Desert Quail Creative Classroom LLC|Monthly Financials|Month End Close|Monthly
A51: Desert Quail Creative Classroom LLC | B51: 1099 Quarterly Review | C51: 1099 | D51: 46325 | E51: Unassigned | F51: Planned | G51: 1099 | H51: 1099 tab | I51: =INDEX('1099 Oct 30'!$F$5:$F$45,MATCH(P51,'1099 Oct 30'!$A$5:$A$45,0)) -> 0.75 | J51: 0 | K51: =I51+J51 -> 0.75 | L51: =ROUND(K51*60,0) -> 45 | M51: =I51*Assumptions!$B$4 -> 71.25 | N51: Estimate | O51: Oct 30 cycle budget from 1099 tab (covers catch-up for clients not completed in Q2). | P51: Desert Quail Creative Classroom LLC
A52: Educational Services Holdings LLC | B52: Aug 2026 Month End Close | C52: Monthly Financials | D52: 46269 | E52: Unassigned | F52: In Progress - Review | G52: Monthly | H52: Recurring Budgets | I52: =INDEX('Recurring Budgets'!$F$2:$F$125,MATCH(P52,'Recurring Budgets'!$A$2:$A$125,0)) -> 5.75 | J52: =INDEX('Recurring Budgets'!$G$2:$G$125,MATCH(P52,'Recurring Budgets'!$A$2:$A$125,0)) -> 0.4833 | K52: =I52+J52 -> 6.2333 | L52: =ROUND(K52*60,0) -> 374 | M52: =INDEX('Recurring Budgets'!$M$2:$M$125,MATCH(P52,'Recurring Budgets'!$A$2:$A$125,0)) -> 1558.325 | N52: =INDEX('Recurring Budgets'!$P$2:$P$125,MATCH(P52,'Recurring Budgets'!$A$2:$A$125,0)) -> Low – based on Valentina's hours | O52: =INDEX('Recurring Budgets'!$Q$2:$Q$125,MATCH(P52,'Recurring Budgets'!$A$2:$A$125,0)) -> Includes Month-end 1.8, CFO advisory 3.8. Review = median of 4 closes reviewed in Harvest (0.48h). | P52: Educational Services Holdings LLC|Monthly Financials|Month End Close|Monthly
A53: Educational Services Holdings LLC | B53: Sep 2026 Month End Close | C53: Monthly Financials | D53: 46301 | E53: Valentina Dikova | F53: In Progress | G53: Monthly | H53: Recurring Budgets | I53: =INDEX('Recurring Budgets'!$F$2:$F$125,MATCH(P53,'Recurring Budgets'!$A$2:$A$125,0)) -> 5.75 | J53: =INDEX('Recurring Budgets'!$G$2:$G$125,MATCH(P53,'Recurring Budgets'!$A$2:$A$125,0)) -> 0.4833 | K53: =I53+J53 -> 6.2333 | L53: =ROUND(K53*60,0) -> 374 | M53: =INDEX('Recurring Budgets'!$M$2:$M$125,MATCH(P53,'Recurring Budgets'!$A$2:$A$125,0)) -> 1558.325 | N53: =INDEX('Recurring Budgets'!$P$2:$P$125,MATCH(P53,'Recurring Budgets'!$A$2:$A$125,0)) -> Low – based on Valentina's hours | O53: =INDEX('Recurring Budgets'!$Q$2:$Q$125,MATCH(P53,'Recurring Budgets'!$A$2:$A$125,0)) -> Includes Month-end 1.8, CFO advisory 3.8. Review = median of 4 closes reviewed in Harvest (0.48h). | P53: Educational Services Holdings LLC|Monthly Financials|Month End Close|Monthly
A54: Educational Services Holdings LLC | B54: 1099 Quarterly Review | C54: 1099 | D54: 46325 | E54: Unassigned | F54: Planned | G54: 1099 | H54: 1099 tab | I54: =INDEX('1099 Oct 30'!$F$5:$F$45,MATCH(P54,'1099 Oct 30'!$A$5:$A$45,0)) -> 0.75 | J54: 0 | K54: =I54+J54 -> 0.75 | L54: =ROUND(K54*60,0) -> 45 | M54: =I54*Assumptions!$B$4 -> 71.25 | N54: Estimate | O54: Oct 30 cycle budget from 1099 tab (covers catch-up for clients not completed in Q2). | P54: Educational Services Holdings LLC
A55: Educational Services Intermediate LLC | B55: 1099 Quarterly Review | C55: Default | D55: 46325 | E55: Unassigned | F55: Planned | G55: 1099 | H55: Excluded | N55: Excluded | O55: No work for this entity (per Josephine). No budget set – consider closing the Karbon item.
A56: Educational Services LLC (dba ESI) | B56: Aug 2026 Month End Close | C56: Monthly Financials | D56: 46286 | E56: Steven Nikolov | F56: Ready To Start | G56: Monthly | H56: Recurring Budgets | I56: =INDEX('Recurring Budgets'!$F$2:$F$125,MATCH(P56,'Recurring Budgets'!$A$2:$A$125,0)) -> 5.5 | J56: =INDEX('Recurring Budgets'!$G$2:$G$125,MATCH(P56,'Recurring Budgets'!$A$2:$A$125,0)) -> 1.75 | K56: =I56+J56 -> 7.25 | L56: =ROUND(K56*60,0) -> 435 | M56: =INDEX('Recurring Budgets'!$M$2:$M$125,MATCH(P56,'Recurring Budgets'!$A$2:$A$125,0)) -> 1812.5 | N56: =INDEX('Recurring Budgets'!$P$2:$P$125,MATCH(P56,'Recurring Budgets'!$A$2:$A$125,0)) -> High | O56: =INDEX('Recurring Budgets'!$Q$2:$Q$125,MATCH(P56,'Recurring Budgets'!$A$2:$A$125,0)) -> Includes Month-end 0.1, CFO advisory 6.2. Steven's CFO client; in-house controller does the books. Forecast/budget meetings treated as recurring CFO work. Jul light because client's controller was out. Review = median of 7 closes reviewed in Harvest (1.75h). | P56: Educational Services LLC (dba ESI)|Monthly Financials|Month End Close|Monthly
A57: Educational Services LLC (dba ESI) | B57: Sep 2026 Month End Close | C57: Monthly Financials | D57: 46316 | E57: Steven Nikolov | F57: Ready To Start | G57: Monthly | H57: Recurring Budgets | I57: =INDEX('Recurring Budgets'!$F$2:$F$125,MATCH(P57,'Recurring Budgets'!$A$2:$A$125,0)) -> 5.5 | J57: =INDEX('Recurring Budgets'!$G$2:$G$125,MATCH(P57,'Recurring Budgets'!$A$2:$A$125,0)) -> 1.75 | K57: =I57+J57 -> 7.25 | L57: =ROUND(K57*60,0) -> 435 | M57: =INDEX('Recurring Budgets'!$M$2:$M$125,MATCH(P57,'Recurring Budgets'!$A$2:$A$125,0)) -> 1812.5 | N57: =INDEX('Recurring Budgets'!$P$2:$P$125,MATCH(P57,'Recurring Budgets'!$A$2:$A$125,0)) -> High | O57: =INDEX('Recurring Budgets'!$Q$2:$Q$125,MATCH(P57,'Recurring Budgets'!$A$2:$A$125,0)) -> Includes Month-end 0.1, CFO advisory 6.2. Steven's CFO client; in-house controller does the books. Forecast/budget meetings treated as recurring CFO work. Jul light because client's controller was out. Review = median of 7 closes reviewed in Harvest (1.75h). | P57: Educational Services LLC (dba ESI)|Monthly Financials|Month End Close|Monthly
A58: Eight Eleven LLC | B58: 1099 Quarterly Review | C58: 1099 | D58: 46265 | E58: Christine Johnson | F58: Waiting - Waiting for client | G58: 1099 | H58: One-time estimate | I58: 0.75 | J58: 0 | K58: =I58+J58 -> 0.75 | L58: =ROUND(K58*60,0) -> 45 | M58: =I58*Assumptions!$B$4+J58*Assumptions!$B$5 -> 71.25 | N58: Estimate | O58: Overdue Q2 review waiting for client: remaining steps 4–7 only (client approval, W-9 follow-up, save W-9s). The Q3 item carries the Oct 30 review.
A59: Eight Eleven LLC | B59: Aug 2026 Month End Close | C59: Monthly Financials | D59: 46295 | E59: Christine Johnson | F59: In Progress - Review | G59: Monthly | H59: Recurring Budgets | I59: =INDEX('Recurring Budgets'!$F$2:$F$125,MATCH(P59,'Recurring Budgets'!$A$2:$A$125,0)) -> 22.1667 | J59: =INDEX('Recurring Budgets'!$G$2:$G$125,MATCH(P59,'Recurring Budgets'!$A$2:$A$125,0)) -> 1.5 | K59: =I59+J59 -> 23.6667 | L59: =ROUND(K59*60,0) -> 1420 | M59: =INDEX('Recurring Budgets'!$M$2:$M$125,MATCH(P59,'Recurring Budgets'!$A$2:$A$125,0)) -> 2480.8365 | N59: =INDEX('Recurring Budgets'!$P$2:$P$125,MATCH(P59,'Recurring Budgets'!$A$2:$A$125,0)) -> High | O59: =INDEX('Recurring Budgets'!$Q$2:$Q$125,MATCH(P59,'Recurring Budgets'!$A$2:$A$125,0)) -> Includes Month-end 8.3, Payroll 9.4, CFO advisory 1.1. Sep 2026 excluded (Christine out of time, not less work). Review = median of 10 closes reviewed in Harvest (1.50h). | P59: Eight Eleven LLC|Monthly Financials|Month End Close|Monthly
A60: Eight Eleven LLC | B60: AR & AP Cleanup | C60: Ad hoc | D60: 46295 | E60: Christine Johnson | F60: In Progress | G60: One-time | H60: One-time estimate | I60: 8 | J60: 0 | K60: =I60+J60 -> 8 | L60: =ROUND(K60*60,0) -> 480 | M60: =I60*Assumptions!$B$4+J60*Assumptions!$B$5 -> 760 | N60: Estimate | O60: Size: Medium–Large. AR/AP cleanup; Eight Eleven AP/AR cleanup ran 3–19h/mo in spring. Estimate – confirm what is left.
A61: Eight Eleven LLC | B61: Weekly Accounting Work Sep 29, 2026 | C61: Accounting | D61: 46300 | E61: Christine Johnson | F61: In Progress | G61: Weekly | H61: Recurring Budgets | I61: =INDEX('Recurring Budgets'!$F$2:$F$125,MATCH(P61,'Recurring Budgets'!$A$2:$A$125,0)) -> 2.5833 | J61: =INDEX('Recurring Budgets'!$G$2:$G$125,MATCH(P61,'Recurring Budgets'!$A$2:$A$125,0)) -> 0 | K61: =I61+J61 -> 2.5833 | L61: =ROUND(K61*60,0) -> 155 | M61: =INDEX('Recurring Budgets'!$M$2:$M$125,MATCH(P61,'Recurring Budgets'!$A$2:$A$125,0)) -> 245.4135 | N61: =INDEX('Recurring Budgets'!$P$2:$P$125,MATCH(P61,'Recurring Budgets'!$A$2:$A$125,0)) -> High | O61: =INDEX('Recurring Budgets'!$Q$2:$Q$125,MATCH(P61,'Recurring Budgets'!$A$2:$A$125,0)) -> Weekly bookkeeping/settlement time ÷ weeks per month. Sep 2026 excluded (Christine out of time, not less work). | P61: Eight Eleven LLC|Accounting|Weekly Accounting Work|Weekly
A62: Eight Eleven LLC | B62: Weekly Accounting Work Oct 6, 2026 | C62: Accounting | D62: 46307 | E62: Christine Johnson | F62: Planned | G62: Weekly | H62: Recurring Budgets | I62: =INDEX('Recurring Budgets'!$F$2:$F$125,MATCH(P62,'Recurring Budgets'!$A$2:$A$125,0)) -> 2.5833 | J62: =INDEX('Recurring Budgets'!$G$2:$G$125,MATCH(P62,'Recurring Budgets'!$A$2:$A$125,0)) -> 0 | K62: =I62+J62 -> 2.5833 | L62: =ROUND(K62*60,0) -> 155 | M62: =INDEX('Recurring Budgets'!$M$2:$M$125,MATCH(P62,'Recurring Budgets'!$A$2:$A$125,0)) -> 245.4135 | N62: =INDEX('Recurring Budgets'!$P$2:$P$125,MATCH(P62,'Recurring Budgets'!$A$2:$A$125,0)) -> High | O62: =INDEX('Recurring Budgets'!$Q$2:$Q$125,MATCH(P62,'Recurring Budgets'!$A$2:$A$125,0)) -> Weekly bookkeeping/settlement time ÷ weeks per month. Sep 2026 excluded (Christine out of time, not less work). | P62: Eight Eleven LLC|Accounting|Weekly Accounting Work|Weekly
A63: Eight Eleven LLC | B63: Sep 2026 Month End Close | C63: Monthly Financials | D63: 46311 | E63: Christine Johnson | F63: In Progress | G63: Monthly | H63: Recurring Budgets | I63: =INDEX('Recurring Budgets'!$F$2:$F$125,MATCH(P63,'Recurring Budgets'!$A$2:$A$125,0)) -> 22.1667 | J63: =INDEX('Recurring Budgets'!$G$2:$G$125,MATCH(P63,'Recurring Budgets'!$A$2:$A$125,0)) -> 1.5 | K63: =I63+J63 -> 23.6667 | L63: =ROUND(K63*60,0) -> 1420 | M63: =INDEX('Recurring Budgets'!$M$2:$M$125,MATCH(P63,'Recurring Budgets'!$A$2:$A$125,0)) -> 2480.8365 | N63: =INDEX('Recurring Budgets'!$P$2:$P$125,MATCH(P63,'Recurring Budgets'!$A$2:$A$125,0)) -> High | O63: =INDEX('Recurring Budgets'!$Q$2:$Q$125,MATCH(P63,'Recurring Budgets'!$A$2:$A$125,0)) -> Includes Month-end 8.3, Payroll 9.4, CFO advisory 1.1. Sep 2026 excluded (Christine out of time, not less work). Review = median of 10 closes reviewed in Harvest (1.50h). | P63: Eight Eleven LLC|Monthly Financials|Month End Close|Monthly
A64: Eight Eleven LLC | B64: 1099 Quarterly Review | C64: 1099 | D64: 46325 | E64: Unassigned | F64: Planned | G64: 1099 | H64: 1099 tab | I64: =INDEX('1099 Oct 30'!$F$5:$F$45,MATCH(P64,'1099 Oct 30'!$A$5:$A$45,0)) -> 2 | J64: 0 | K64: =I64+J64 -> 2 | L64: =ROUND(K64*60,0) -> 120 | M64: =I64*Assumptions!$B$4 -> 190 | N64: Estimate | O64: Oct 30 cycle budget from 1099 tab (covers catch-up for clients not completed in Q2). | P64: Eight Eleven LLC
A65: FiveOliver LLC | B65: Month End Close Clean up Jan 2026 | C65: Monthly Financials | D65: 46304 | E65: Lisa Danforth | F65: In Progress | G65: One-time | H65: One-time estimate | I65: 3 | J65: 0 | K65: =I65+J65 -> 3 | L65: =ROUND(K65*60,0) -> 180 | M65: =I65*Assumptions!$B$4+J65*Assumptions!$B$5 -> 285 | N65: Estimate | O65: Size: Small. FiveOliver time so far is mostly tax; small catch-up close. Estimate.
A66: FiveOliver LLC | B66: 1099 Quarterly Review | C66: 1099 | D66: 46325 | E66: Unassigned | F66: Planned | G66: 1099 | H66: 1099 tab | I66: =INDEX('1099 Oct 30'!$F$5:$F$45,MATCH(P66,'1099 Oct 30'!$A$5:$A$45,0)) -> 4 | J66: 0 | K66: =I66+J66 -> 4 | L66: =ROUND(K66*60,0) -> 240 | M66: =I66*Assumptions!$B$4 -> 380 | N66: Estimate | O66: Oct 30 cycle budget from 1099 tab (covers catch-up for clients not completed in Q2). | P66: FiveOliver LLC
A67: GAV Enterprises Inc | B67: Year-End Tax Coordination Aug 2026 | C67: Default | D67: 46248 | E67: Steven Nikolov | F67: Ready To Start | G67: Annual | H67: Recurring Budgets | I67: =INDEX('Recurring Budgets'!$F$2:$F$125,MATCH(P67,'Recurring Budgets'!$A$2:$A$125,0)) -> 0.3333 | J67: =INDEX('Recurring Budgets'!$G$2:$G$125,MATCH(P67,'Recurring Budgets'!$A$2:$A$125,0)) -> 0 | K67: =I67+J67 -> 0.3333 | L67: =ROUND(K67*60,0) -> 20 | M67: =INDEX('Recurring Budgets'!$M$2:$M$125,MATCH(P67,'Recurring Budgets'!$A$2:$A$125,0)) -> 31.6635 | N67: =INDEX('Recurring Budgets'!$P$2:$P$125,MATCH(P67,'Recurring Budgets'!$A$2:$A$125,0)) -> High | O67: =INDEX('Recurring Budgets'!$Q$2:$Q$125,MATCH(P67,'Recurring Budgets'!$A$2:$A$125,0)) -> Year-end/tax hours Oct 2025–Sep 2026 (0.8h) split across 2 year-end items. | P67: GAV Enterprises Inc|Default|Year-End Tax Coordination|Annual
A68: GAV Enterprises Inc | B68: Jul-Sep 2026 Quarter End Close | C68: Accounting | D68: 46321 | E68: Valentina Dikova | F68: In Progress | G68: Quarterly | H68: Recurring Budgets | I68: =INDEX('Recurring Budgets'!$F$2:$F$125,MATCH(P68,'Recurring Budgets'!$A$2:$A$125,0)) -> 18.5833 | J68: =INDEX('Recurring Budgets'!$G$2:$G$125,MATCH(P68,'Recurring Budgets'!$A$2:$A$125,0)) -> 1.5 | K68: =I68+J68 -> 20.0833 | L68: =ROUND(K68*60,0) -> 1205 | M68: =INDEX('Recurring Budgets'!$M$2:$M$125,MATCH(P68,'Recurring Budgets'!$A$2:$A$125,0)) -> 2140.4135 | N68: =INDEX('Recurring Budgets'!$P$2:$P$125,MATCH(P68,'Recurring Budgets'!$A$2:$A$125,0)) -> High | O68: =INDEX('Recurring Budgets'!$Q$2:$Q$125,MATCH(P68,'Recurring Budgets'!$A$2:$A$125,0)) -> Includes Month-end 10.4, Bookkeeping 7.8, CFO advisory 0.7. Review = 0.25h as logged (only 1 reviewed close(s) in Harvest – check). Quarterly review from history: Q3 2025 Lisa 1.0 first pass + 0.5 complete = 1.5h; Jan–Jun 2024 review ~1.5h. | P68: GAV Enterprises Inc|Accounting|Quarter End Close|Quarterly
A69: GAV Enterprises Inc | B69: 1099 Quarterly Review | C69: 1099 | D69: 46325 | E69: Unassigned | F69: Planned | G69: 1099 | H69: 1099 tab | I69: =INDEX('1099 Oct 30'!$F$5:$F$45,MATCH(P69,'1099 Oct 30'!$A$5:$A$45,0)) -> 1.5 | J69: 0 | K69: =I69+J69 -> 1.5 | L69: =ROUND(K69*60,0) -> 90 | M69: =I69*Assumptions!$B$4 -> 142.5 | N69: Estimate | O69: Oct 30 cycle budget from 1099 tab (covers catch-up for clients not completed in Q2). | P69: GAV Enterprises Inc
A70: GAV Enterprises Inc | B70: Adjusting Journal Entry Request 2026 | C70: Year-end review | D70: 46325 | E70: Jessica Bumphus | F70: Ready To Start | G70: Annual | H70: Recurring Budgets | I70: =INDEX('Recurring Budgets'!$F$2:$F$125,MATCH(P70,'Recurring Budgets'!$A$2:$A$125,0)) -> 0.3333 | J70: =INDEX('Recurring Budgets'!$G$2:$G$125,MATCH(P70,'Recurring Budgets'!$A$2:$A$125,0)) -> 0 | K70: =I70+J70 -> 0.3333 | L70: =ROUND(K70*60,0) -> 20 | M70: =INDEX('Recurring Budgets'!$M$2:$M$125,MATCH(P70,'Recurring Budgets'!$A$2:$A$125,0)) -> 31.6635 | N70: =INDEX('Recurring Budgets'!$P$2:$P$125,MATCH(P70,'Recurring Budgets'!$A$2:$A$125,0)) -> High | O70: =INDEX('Recurring Budgets'!$Q$2:$Q$125,MATCH(P70,'Recurring Budgets'!$A$2:$A$125,0)) -> Year-end/tax hours Oct 2025–Sep 2026 (0.8h) split across 2 year-end items. | P70: GAV Enterprises Inc|Year-end review|Adjusting Journal Entry Request|Annual
A71: International Alliance Group LLC | B71: Jun 2026 Month End Close | C71: Monthly Financials | D71: 46219 | E71: Steven Nikolov | F71: In Progress - Review | G71: Monthly | H71: Excluded | N71: Excluded | O71: On hold – IAG brought in-house. No budget set.
A72: International Alliance Group LLC | B72: Quarterly Financial Reports to MidFirst Bank | C72: Sales tax | D72: 46224 | E72: Jessica Bumphus | F72: Waiting - Waiting for client | G72: Quarterly | H72: Excluded | N72: Excluded | O72: On hold – IAG brought in-house. No budget set.
A73: International Alliance Group LLC | B73: Jul 2026 Month End Close | C73: Monthly Financials | D73: 46248 | E73: Steven Nikolov | F73: In Progress - Review | G73: Monthly | H73: Excluded | N73: Excluded | O73: On hold – IAG brought in-house. No budget set.
A74: International Alliance Group LLC | B74: AR Aging Reports to MidFirst Sep | C74: Bookkeeping | D74: 46273 | E74: Jessica Bumphus | F74: Waiting - Waiting for client | G74: One-time | H74: Excluded | N74: Excluded | O74: On hold – IAG brought in-house. No budget set.
A75: International Alliance Group LLC | B75: Aug 2026 Month End Close | C75: Monthly Financials | D75: 46281 | E75: Valentina Dikova | F75: Waiting - Waiting for client | G75: Monthly | H75: Excluded | N75: Excluded | O75: On hold – IAG brought in-house. No budget set.
A76: International Alliance Group LLC | B76: Aug 2026 Hawaii Monthly Tax Filing - Onyx Prepares & Files | C76: Sales tax | D76: 46283 | E76: Valentina Dikova | F76: Waiting - Waiting for client | G76: Monthly | H76: Excluded | N76: Excluded | O76: On hold – IAG brought in-house. No budget set.
A77: International Alliance Group LLC | B77: Sep 28, 2026 Mexico Payroll Processing | C77: Accounting | D77: 46293 | E77: Jessica Bumphus | F77: Ready To Start | G77: One-time | H77: Excluded | N77: Excluded | O77: On hold – IAG brought in-house. No budget set.
A78: International Alliance Group LLC | B78: Bookkeeping & Bill Pay Sep 30, 2026 | C78: Accounting | D78: 46295 | E78: Jessica Bumphus | F78: In Progress | G78: Weekly | H78: Excluded | N78: Excluded | O78: On hold – IAG brought in-house. No budget set.
A79: International Alliance Group LLC | B79: Bookkeeping & Bill Pay Oct 7, 2026 | C79: Accounting | D79: 46302 | E79: Christine Johnson | F79: Planned | G79: Weekly | H79: Excluded | N79: Excluded | O79: On hold – IAG brought in-house. No budget set.
A80: International Alliance Group LLC | B80: AR Aging Reports to MidFirst Oct | C80: Bookkeeping | D80: 46303 | E80: Christine Johnson | F80: Ready To Start | G80: One-time | H80: Excluded | N80: Excluded | O80: On hold – IAG brought in-house. No budget set.
A81: International Alliance Group LLC | B81: Quarterly 1GPA Filing | C81: Accounting | D81: 46310 | E81: Josephine Mack | F81: Waiting - Waiting for client | G81: Quarterly | H81: Excluded | N81: Excluded | O81: On hold – IAG brought in-house. No budget set.
A82: International Alliance Group LLC | B82: Quarterly Sales Tax Returns - Onyx Prepares the Returns for Client | C82: Sales tax | D82: 46310 | E82: Valentina Dikova | F82: Planned | G82: Quarterly | H82: Excluded | N82: Excluded | O82: On hold – IAG brought in-house. No budget set.
... A86: International Alliance Group LLC | B86: Adjusting Journal Entry Request 2025/2026 | C86: Year-end review | D86: 46325 | E86: Steven Nikolov | F86: Ready To Start | G86: Annual | H86: Excluded | N86: Excluded | O86: On hold – IAG brought in-house. No budget set.
A87: KAMM ADGT LLC | B87: Sep 2026 Month End Close | C87: Monthly Financials | D87: 46301 | E87: Valentina Dikova | F87: In Progress | G87: Monthly | H87: Recurring Budgets | I87: =INDEX('Recurring Budgets'!$F$2:$F$125,MATCH(P87,'Recurring Budgets'!$A$2:$A$125,0)) -> 0.5 | J87: =INDEX('Recurring Budgets'!$G$2:$G$125,MATCH(P87,'Recurring Budgets'!$A$2:$A$125,0)) -> 0.3833 | K87: =I87+J87 -> 0.8833 | L87: =ROUND(K87*60,0) -> 53 | M87: =INDEX('Recurring Budgets'!$M$2:$M$125,MATCH(P87,'Recurring Budgets'!$A$2:$A$125,0)) -> 143.325 | N87: =INDEX('Recurring Budgets'!$P$2:$P$125,MATCH(P87,'Recurring Budgets'!$A$2:$A$125,0)) -> Medium | O87: =INDEX('Recurring Budgets'!$Q$2:$Q$125,MATCH(P87,'Recurring Budgets'!$A$2:$A$125,0)) -> Josephine's Apr–May 2026 closes + allowance for a new person (Valentina's hours not used). Review = median of 8 closes reviewed in Harvest (0.38h). | P87: KAMM ADGT LLC|Monthly Financials|Month End Close|Monthly
A88: KAMM ADGT LLC | B88: 1099 Quarterly Review | C88: 1099 | D88: 46325 | E88: Unassigned | F88: Planned | G88: 1099 | H88: 1099 tab | I88: =INDEX('1099 Oct 30'!$F$5:$F$45,MATCH(P88,'1099 Oct 30'!$A$5:$A$45,0)) -> 0.375 | J88: 0 | K88: =I88+J88 -> 0.375 | L88: =ROUND(K88*60,0) -> 23 | M88: =I88*Assumptions!$B$4 -> 35.625 | N88: Estimate | O88: Oct 30 cycle budget from 1099 tab (covers catch-up for clients not completed in Q2). | P88: KAMM ADGT LLC
A89: Korman LLC | B89: 2024 Review - Work Through Open Items | C89: Ad hoc | D89: 46290 | E89: Jessica Bumphus | F89: Ready To Start | G89: One-time | H89: One-time estimate | I89: 5.5 | J89: 0 | K89: =I89+J89 -> 5.5 | L89: =ROUND(K89*60,0) -> 330 | M89: =I89*Assumptions!$B$4+J89*Assumptions!$B$5 -> 522.5 | N89: Estimate | O89: Size: Medium. Catalog Medium; Korman has run 8–9h/mo since Aug.
A90: Little Moo's LLC | B90: Sep 2026 Month End Close | C90: Monthly Financials | D90: 46301 | E90: Valentina Dikova | F90: In Progress | G90: Monthly | H90: Recurring Budgets | I90: =INDEX('Recurring Budgets'!$F$2:$F$125,MATCH(P90,'Recurring Budgets'!$A$2:$A$125,0)) -> 1.6667 | J90: =INDEX('Recurring Budgets'!$G$2:$G$125,MATCH(P90,'Recurring Budgets'!$A$2:$A$125,0)) -> 0.3833 | K90: =I90+J90 -> 2.05 | L90: =ROUND(K90*60,0) -> 123 | M90: =INDEX('Recurring Budgets'!$M$2:$M$125,MATCH(P90,'Recurring Budgets'!$A$2:$A$125,0)) -> 254.1615 | N90: =INDEX('Recurring Budgets'!$P$2:$P$125,MATCH(P90,'Recurring Budgets'!$A$2:$A$125,0)) -> Provisional | O90: =INDEX('Recurring Budgets'!$Q$2:$Q$125,MATCH(P90,'Recurring Budgets'!$A$2:$A$125,0)) -> Includes Month-end 1.7, CFO advisory 0.1. Store opens Oct 2026 (Square POS, sales tax, inventory; payroll later) – provisional, pre-opening level. Revisit after 2–3 months open. Review = median of 8 closes reviewed in Harvest (0.38h). | P90: Little Moo's LLC|Monthly Financials|Month End Close|Monthly
A91: Little Moo's LLC | B91: Sep 2026 Sales Tax Filing - Onyx Prepares the Returns for Client | C91: Sales tax | D91: 46310 | E91: Valentina Dikova | F91: Planned | G91: Monthly | H91: Recurring Budgets | I91: =INDEX('Recurring Budgets'!$F$2:$F$125,MATCH(P91,'Recurring Budgets'!$A$2:$A$125,0)) -> 0.9167 | J91: =INDEX('Recurring Budgets'!$G$2:$G$125,MATCH(P91,'Recurring Budgets'!$A$2:$A$125,0)) -> 0 | K91: =I91+J91 -> 0.9167 | L91: =ROUND(K91*60,0) -> 55 | M91: =INDEX('Recurring Budgets'!$M$2:$M$125,MATCH(P91,'Recurring Budgets'!$A$2:$A$125,0)) -> 87.0865 | N91: =INDEX('Recurring Budgets'!$P$2:$P$125,MATCH(P91,'Recurring Budgets'!$A$2:$A$125,0)) -> Provisional | O91: =INDEX('Recurring Budgets'!$Q$2:$Q$125,MATCH(P91,'Recurring Budgets'!$A$2:$A$125,0)) -> Sales tax time per month. Store opens Oct 2026 (Square POS, sales tax, inventory; payroll later) – provisional, pre-opening level. Revisit after 2–3 months open. | P91: Little Moo's LLC|Sales tax|Sales Tax Filing - Onyx Prepares the Returns for Client|Monthly
A92: Little Moo's LLC | B92: 1099 Quarterly Review | C92: 1099 | D92: 46325 | E92: Unassigned | F92: Planned | G92: 1099 | H92: 1099 tab | I92: =INDEX('1099 Oct 30'!$F$5:$F$45,MATCH(P92,'1099 Oct 30'!$A$5:$A$45,0)) -> 0.375 | J92: 0 | K92: =I92+J92 -> 0.375 | L92: =ROUND(K92*60,0) -> 23 | M92: =I92*Assumptions!$B$4 -> 35.625 | N92: Estimate | O92: Oct 30 cycle budget from 1099 tab (covers catch-up for clients not completed in Q2). | P92: Little Moo's LLC
A93: Midwest Contracting Inc | B93: 1099 Quarterly Review | C93: 1099 | D93: 46265 | E93: Christine Johnson | F93: Waiting - Waiting for client | G93: 1099 | H93: One-time estimate | I93: 0.75 | J93: 0 | K93: =I93+J93 -> 0.75 | L93: =ROUND(K93*60,0) -> 45 | M93: =I93*Assumptions!$B$4+J93*Assumptions!$B$5 -> 71.25 | N93: Estimate | O93: Overdue Q2 review waiting for client: remaining steps 4–7 only (client approval, W-9 follow-up, save W-9s). The Q3 item carries the Oct 30 review.
A94: Midwest Contracting Inc | B94: Aug 2026 Month End Close | C94: Monthly Financials | D94: 46295 | E94: Christine Johnson | F94: Waiting - Waiting for client | G94: Monthly | H94: Recurring Budgets | I94: =INDEX('Recurring Budgets'!$F$2:$F$125,MATCH(P94,'Recurring Budgets'!$A$2:$A$125,0)) -> 35.3333 | J94: =INDEX('Recurring Budgets'!$G$2:$G$125,MATCH(P94,'Recurring Budgets'!$A$2:$A$125,0)) -> 1.5 | K94: =I94+J94 -> 36.8333 | L94: =ROUND(K94*60,0) -> 2210 | M94: =INDEX('Recurring Budgets'!$M$2:$M$125,MATCH(P94,'Recurring Budgets'!$A$2:$A$125,0)) -> 3731.6635 | N94: =INDEX('Recurring Budgets'!$P$2:$P$125,MATCH(P94,'Recurring Budgets'!$A$2:$A$125,0)) -> High | O94: =INDEX('Recurring Budgets'!$Q$2:$Q$125,MATCH(P94,'Recurring Budgets'!$A$2:$A$125,0)) -> Includes Month-end 13.9, Payroll 12.1, Sales tax 0.5, CFO advisory 7.4. Review = median of 5 closes reviewed in Harvest (1.50h). | P94: Midwest Contracting Inc|Monthly Financials|Month End Close|Monthly
A95: Midwest Contracting Inc | B95: Weekly Accounting Sep 29, 2026 | C95: Accounting | D95: 46300 | E95: Christine Johnson | F95: In Progress | G95: Weekly | H95: Recurring Budgets | I95: =INDEX('Recurring Budgets'!$F$2:$F$125,MATCH(P95,'Recurring Budgets'!$A$2:$A$125,0)) -> 2.25 | J95: =INDEX('Recurring Budgets'!$G$2:$G$125,MATCH(P95,'Recurring Budgets'!$A$2:$A$125,0)) -> 0 | K95: =I95+J95 -> 2.25 | L95: =ROUND(K95*60,0) -> 135 | M95: =INDEX('Recurring Budgets'!$M$2:$M$125,MATCH(P95,'Recurring Budgets'!$A$2:$A$125,0)) -> 213.75 | N95: =INDEX('Recurring Budgets'!$P$2:$P$125,MATCH(P95,'Recurring Budgets'!$A$2:$A$125,0)) -> High | O95: =INDEX('Recurring Budgets'!$Q$2:$Q$125,MATCH(P95,'Recurring Budgets'!$A$2:$A$125,0)) -> Weekly bookkeeping/settlement time ÷ weeks per month. | P95: Midwest Contracting Inc|Accounting|Weekly Accounting|Weekly
A96: Midwest Contracting Inc | B96: Weekly Accounting Oct 6, 2026 | C96: Accounting | D96: 46307 | E96: Christine Johnson | F96: Planned | G96: Weekly | H96: Recurring Budgets | I96: =INDEX('Recurring Budgets'!$F$2:$F$125,MATCH(P96,'Recurring Budgets'!$A$2:$A$125,0)) -> 2.25 | J96: =INDEX('Recurring Budgets'!$G$2:$G$125,MATCH(P96,'Recurring Budgets'!$A$2:$A$125,0)) -> 0 | K96: =I96+J96 -> 2.25 | L96: =ROUND(K96*60,0) -> 135 | M96: =INDEX('Recurring Budgets'!$M$2:$M$125,MATCH(P96,'Recurring Budgets'!$A$2:$A$125,0)) -> 213.75 | N96: =INDEX('Recurring Budgets'!$P$2:$P$125,MATCH(P96,'Recurring Budgets'!$A$2:$A$125,0)) -> High | O96: =INDEX('Recurring Budgets'!$Q$2:$Q$125,MATCH(P96,'Recurring Budgets'!$A$2:$A$125,0)) -> Weekly bookkeeping/settlement time ÷ weeks per month. | P96: Midwest Contracting Inc|Accounting|Weekly Accounting|Weekly
A97: Midwest Contracting Inc | B97: Sep 2026 Month End Close | C97: Monthly Financials | D97: 46311 | E97: Christine Johnson | F97: In Progress | G97: Monthly | H97: Recurring Budgets | I97: =INDEX('Recurring Budgets'!$F$2:$F$125,MATCH(P97,'Recurring Budgets'!$A$2:$A$125,0)) -> 35.3333 | J97: =INDEX('Recurring Budgets'!$G$2:$G$125,MATCH(P97,'Recurring Budgets'!$A$2:$A$125,0)) -> 1.5 | K97: =I97+J97 -> 36.8333 | L97: =ROUND(K97*60,0) -> 2210 | M97: =INDEX('Recurring Budgets'!$M$2:$M$125,MATCH(P97,'Recurring Budgets'!$A$2:$A$125,0)) -> 3731.6635 | N97: =INDEX('Recurring Budgets'!$P$2:$P$125,MATCH(P97,'Recurring Budgets'!$A$2:$A$125,0)) -> High | O97: =INDEX('Recurring Budgets'!$Q$2:$Q$125,MATCH(P97,'Recurring Budgets'!$A$2:$A$125,0)) -> Includes Month-end 13.9, Payroll 12.1, Sales tax 0.5, CFO advisory 7.4. Review = median of 5 closes reviewed in Harvest (1.50h). | P97: Midwest Contracting Inc|Monthly Financials|Month End Close|Monthly
A98: Midwest Contracting Inc | B98: 1099 Quarterly Review | C98: 1099 | D98: 46325 | E98: Unassigned | F98: Planned | G98: 1099 | H98: 1099 tab | I98: =INDEX('1099 Oct 30'!$F$5:$F$45,MATCH(P98,'1099 Oct 30'!$A$5:$A$45,0)) -> 2 | J98: 0 | K98: =I98+J98 -> 2 | L98: =ROUND(K98*60,0) -> 120 | M98: =I98*Assumptions!$B$4 -> 190 | N98: Estimate | O98: Oct 30 cycle budget from 1099 tab (covers catch-up for clients not completed in Q2). | P98: Midwest Contracting Inc
A99: Mohrschladt Capital LP | B99: Aug 2026 Month End Close | C99: Monthly Financials | D99: 46295 | E99: Christine Johnson | F99: In Progress | G99: Monthly | H99: Recurring Budgets | I99: =INDEX('Recurring Budgets'!$F$2:$F$125,MATCH(P99,'Recurring Budgets'!$A$2:$A$125,0)) -> 3.25 | J99: =INDEX('Recurring Budgets'!$G$2:$G$125,MATCH(P99,'Recurring Budgets'!$A$2:$A$125,0)) -> 0.7 | K99: =I99+J99 -> 3.95 | L99: =ROUND(K99*60,0) -> 237 | M99: =INDEX('Recurring Budgets'!$M$2:$M$125,MATCH(P99,'Recurring Budgets'!$A$2:$A$125,0)) -> 483.75 | N99: =INDEX('Recurring Budgets'!$P$2:$P$125,MATCH(P99,'Recurring Budgets'!$A$2:$A$125,0)) -> High | O99: =INDEX('Recurring Budgets'!$Q$2:$Q$125,MATCH(P99,'Recurring Budgets'!$A$2:$A$125,0)) -> Includes Month-end 2.6, Bookkeeping 0.4, CFO advisory 0.1. Review = median of 5 closes reviewed in Harvest (0.70h). | P99: Mohrschladt Capital LP|Monthly Financials|Month End Close|Monthly
A100: Mohrschladt Capital LP | B100: 1099 Quarterly Review | C100: 1099 | D100: 46325 | E100: Unassigned | F100: Planned | G100: 1099 | H100: 1099 tab | I100: =INDEX('1099 Oct 30'!$F$5:$F$45,MATCH(P100,'1099 Oct 30'!$A$5:$A$45,0)) -> 1.5 | J100: 0 | K100: =I100+J100 -> 1.5 | L100: =ROUND(K100*60,0) -> 90 | M100: =I100*Assumptions!$B$4 -> 142.5 | N100: Estimate | O100: Oct 30 cycle budget from 1099 tab (covers catch-up for clients not completed in Q2). | P100: Mohrschladt Capital LP
A101: Mohrschladt Howarth Associates Inc | B101: Aug 2026 Month End Close | C101: Monthly Financials | D101: 46295 | E101: Lisa Danforth | F101: In Progress - Review | G101: Monthly | H101: Recurring Budgets | I101: =INDEX('Recurring Budgets'!$F$2:$F$125,MATCH(P101,'Recurring Budgets'!$A$2:$A$125,0)) -> 1.75 | J101: =INDEX('Recurring Budgets'!$G$2:$G$125,MATCH(P101,'Recurring Budgets'!$A$2:$A$125,0)) -> 0.7 | K101: =I101+J101 -> 2.45 | L101: =ROUND(K101*60,0) -> 147 | M101: =INDEX('Recurring Budgets'!$M$2:$M$125,MATCH(P101,'Recurring Budgets'!$A$2:$A$125,0)) -> 341.25 | N101: =INDEX('Recurring Budgets'!$P$2:$P$125,MATCH(P101,'Recurring Budgets'!$A$2:$A$125,0)) -> High | O101: =INDEX('Recurring Budgets'!$Q$2:$Q$125,MATCH(P101,'Recurring Budgets'!$A$2:$A$125,0)) -> Includes Month-end 1.9. Review = median of 7 closes reviewed in Harvest (0.70h). | P101: Mohrschladt Howarth Associates Inc|Monthly Financials|Month End Close|Monthly
A102: Mohrschladt Howarth Associates Inc | B102: 1099 Quarterly Review | C102: 1099 | D102: 46325 | E102: Unassigned | F102: Planned | G102: 1099 | H102: 1099 tab | I102: =INDEX('1099 Oct 30'!$F$5:$F$45,MATCH(P102,'1099 Oct 30'!$A$5:$A$45,0)) -> 4 | J102: 0 | K102: =I102+J102 -> 4 | L102: =ROUND(K102*60,0) -> 240 | M102: =I102*Assumptions!$B$4 -> 380 | N102: Estimate | O102: Oct 30 cycle budget from 1099 tab (covers catch-up for clients not completed in Q2). | P102: Mohrschladt Howarth Associates Inc
A103: Mountain Trade Supply Inc | B103: Month End Close Clean up July 2026 | C103: Monthly Financials | D103: 46290 | E103: Jessica Bumphus | F103: In Progress | G103: One-time | H103: One-time estimate | I103: 8 | J103: 0.5 | K103: =I103+J103 -> 8.5 | L103: =ROUND(K103*60,0) -> 510 | M103: =I103*Assumptions!$B$4+J103*Assumptions!$B$5 -> 885 | N103: Estimate | O103: Size: Medium–Large. Jessica began July close late Sept alongside audit; first close after takeover. Estimate.
...

Sheet Client Summary
A1: Monthly equivalent budget per client (recurring items only; excludes one-time items and the Oct 30 1099 catch-up)
A3: Client Name | B3: Work (hrs / month) | C3: CFO Review (hrs / month) | D3: Total (hrs / month) | E3: Lowest confidence on client | F3: Note
A4: 1402 W Victory LLC | B4: =SUMIFS('Recurring Budgets'!$N$2:$N$125,'Recurring Budgets'!$B$2:$B$125,A4) -> 0.91666667 | C4: =SUMIFS('Recurring Budgets'!$O$2:$O$125,'Recurring Budgets'!$B$2:$B$125,A4) -> 0.7 | D4: =B4+C4 -> 1.6166667 | E4: High
A5: 15650 Northsight LLC | B5: =SUMIFS('Recurring Budgets'!$N$2:$N$125,'Recurring Budgets'!$B$2:$B$125,A5) -> 0.75 | C5: =SUMIFS('Recurring Budgets'!$O$2:$O$125,'Recurring Budgets'!$B$2:$B$125,A5) -> 0.41666667 | D5: =B5+C5 -> 1.1666667 | E5: High
